Workbook
Name C_VAL: COSTING!$M$4:$M$17
Name CODE_ING: COSTING!$L$4:$L$17
Name CUM_URG: 'SUPPLY-UR'!$M:$M
Name MEN_COD: MENU2!$A:$A
Name MEN_DES: MENU2!$B:$B
Name MEN_GMS: MENU2!$E:$E
Name MEN_QTY: MENU2!#REF!
Name MISC_DATE: #REF!
Name NativeTimeline_DATE: #N/A
Name SAL_AMT: #REF!
Name SAL_CAT: #REF!
Name SAL_DATE: #REF!
Name Slicer_Category: #N/A
Name SUM_DIS: 'SALES''26'!$H:$H
Name SUM_GRO: 'SALES''26'!$K:$K
Name SUM_GRS: 'SALES''26'!$E:$E
Name SUM_MISC: #REF!
Name SUM_NET: 'SALES''26'!$I:$I
Name SUM_PER: 'SALES''26'!$N:$N
Name SUM_PRO: 'SALES''26'!$A:$A
Name SUM_QTY: 'SALES''26'!$D:$D
Name SUP_AMT: #REF!
Name SUP_DATE: #REF!
Name SUP_NAME: #REF!
Name SUP_QTY: #REF!

Sheet MENU2
A1: MENU DATABASE
A3: CODE | B3: DESCRIPTION | E3: QTY
B4: DON BURI BOWLS
B5: CHICKEN
A6: CF_060 | B6: [DB] Oyakudon (Set A) | C6: DON BURI (CHICKEN) | E6: 2
A7: EGG | B7: [DB] Oyakudon (Set A) | C7: DON BURI (CHICKEN) | E7: 2
A8: TSS | B8: [DB] Oyakudon (Set A) | C8: DON BURI (CHICKEN) | E8: 130
A9: CF_060 | B9: [DB] Oyakudon (Set B) | C9: DON BURI (CHICKEN) | E9: 2
A10: EGG | B10: [DB] Oyakudon (Set B) | C10: DON BURI (CHICKEN) | E10: 2
A11: TSS | B11: [DB] Oyakudon (Set B) | C11: DON BURI (CHICKEN) | E11: 130
A12: KNI | B12: [DB] Oyakudon (Set B) | C12: DON BURI (CHICKEN) | E12: 0.25
A13: CAR | B13: [DB] Oyakudon (Set B) | C13: DON BURI (CHICKEN) | E13: 1
A14: CT_120 | B14: [DB] Karaagedon (Set A) | C14: DON BURI (CHICKEN) | E14: 1
A15: B+B | B15: [DB] Karaagedon (Set A) | C15: DON BURI (CHICKEN) | E15: 1
A16: CT_120 | B16: [DB] Karaagedon (Set B) | C16: DON BURI (CHICKEN) | E16: 1
A17: KNI | B17: [DB] Karaagedon (Set B) | C17: DON BURI (CHICKEN) | E17: 0.25
A18: ICT | B18: [DB] Karaagedon (Set B) | C18: DON BURI (CHICKEN)
A19: TSS | B19: [DB] Karaagedon (Set B) | C19: DON BURI (CHICKEN) | E19: 30
A20: CF_060 | B20: [DB] Shoyu Miso Buttered Chicken (Set A) | C20: DON BURI (CHICKEN) | E20: 2
A21: SHO | B21: [DB] Shoyu Miso Buttered Chicken (Set A) | C21: DON BURI (CHICKEN) | E21: 10
A22: CF_060 | B22: [DB] Torikatsu (Set A) | C22: DON BURI (CHICKEN) | E22: 2
A23: CF_060 | B23: [DB] Torikatsu (Set B) | E23: 2
A24: ICT | B24: [DB] Torikatsu (Set B) | E24: 1
A25: CF_060 | B25: [DB] Torikatsudon (Set A) | C25: DON BURI (CHICKEN) | E25: 2
A26: EGG | B26: [DB] Torikatsudon (Set A) | C26: DON BURI (CHICKEN) | E26: 2
A27: CF_060 | B27: [DB] Torikatsudon (Set B) | C27: STARDEALS | E27: 2
A28: TSS | B28: [DB] Torikatsudon (Set B) | C28: STARDEALS | E28: 130
A29: ICT | B29: [DB] Torikatsudon (Set B) | C29: STARDEALS | E29: 1
A30: EGG | B30: [DB] Torikatsudon (Set B) | C30: STARDEALS | E30: 2
A31: B+B | B31: [DB] Torikatsudon (Set B) | C31: STARDEALS | E31: 1
A32: CT_150 | B32: [DB] Chicken Terriyaki (Set B) | C32: DON BURI (CHICKEN) | E32: 1
A33: TER | B33: [DB] Chicken Terriyaki (Set B) | C33: DON BURI (CHICKEN) | E33: 1
A34: KNI | B34: [DB] Chicken Terriyaki (Set B) | C34: DON BURI (CHICKEN) | E34: 0.25
A35: ICT | B35: [DB] Chicken Terriyaki (Set B) | C35: DON BURI (CHICKEN) | E35: 1
A36: VDB | B36: [DB] Chicken Terriyaki (Set B) | C36: DON BURI (CHICKEN) | E36: 1
A37: CF_060 | B37: Chicken Misono Set A | E37: 2
A38: CF_060 | B38: [DB] Chicken Teppanyaki/Misono (Set A) | C38: DON BURI (CHICKEN) | E38: 2
A39: TEP | B39: [DB] Chicken Teppanyaki/Misono (Set A) | C39: DON BURI (CHICKEN) | E39: 1
A40: VDB | B40: [DB] Chicken Teppanyaki/Misono (Set A) | C40: DON BURI (CHICKEN) | E40: 1
A41: CF_040 | B41: [DB] Yakitori (Set A) | C41: DON BURI (CHICKEN) | E41: 3
A42: CF_040 | B42: [DB] Yakitori (Set B) | C42: DON BURI (CHICKEN) | E42: 3
A43: ICT | B43: [DB] Yakitori (Set B) | C43: DON BURI (CHICKEN) | E43: 1
A44: CF_060 | B44: [DB] Torikatsu Curry (Set A) | C44: DON BURI (CHICKEN) | E44: 2
A45: CF_060 | B45: [DB] Torikatsu Curry (Set B) | E45: 2
A46: KNI | B46: [DB] Torikatsu Curry (Set B) | E46: 0.25
A47: ICT | B47: [DB] Torikatsu Curry (Set B) | E47: 1
A48: CF_060 | B48: [DB] Torikatsu Omelette Curry (Set A) | C48: DON BURI (CHICKEN) | E48: 2
A49: EGG | B49: [DB] Torikatsu Omelette Curry (Set A) | C49: DON BURI (CHICKEN) | E49: 2
A50: CF_060 | B50: [DB] Torikatsu Omelette Curry (Set B) | E50: 2
A51: EGG | B51: [DB] Torikatsu Omelette Curry (Set B) | E51: 2
A52: KNI | B52: [DB] Torikatsu Omelette Curry (Set B) | E52: 0.25
A53: ICT | B53: [DB] Torikatsu Omelette Curry (Set B) | E53: 1
A54: CF_060 | B54: [DB] Shoyu Miso Buttered Chicken (Set B) | E54: 2
A55: ICT | B55: [DB] Shoyu Miso Buttered Chicken (Set B)
A56: PL_060 | B56: [DB] Katsudon (Set A) | C56: DON BURI (PORK) | E56: 2
A57: TSS | B57: [DB] Katsudon (Set A) | C57: DON BURI (PORK) | E57: 130
A58: EGG | B58: [DB] Katsudon (Set A) | C58: DON BURI (PORK)
A59: PL_060 | B59: [DB] Shoyu Miso Buttered Pork (Set A) | E59: 2
A60: KNI | B60: [DB] Shoyu Miso Buttered Pork (Set A) | E60: 0.25
A61: PL_060 | B61: [DB] Shoyu Miso Buttered Pork (Set B) | E61: 2
A62: KNI | B62: [DB] Shoyu Miso Buttered Pork (Set B) | E62: 0.25
A63: ICT | B63: [DB] Shoyu Miso Buttered Pork (Set B) | E63: 1
A64: TUN | B64: [DB] Mixed Seafood Teppanyaki (Set A) | E64: 40
A65: TEP | B65: [DB] Mixed Seafood Teppanyaki (Set A) | E65: 1
A66: SQD | B66: [DB] Mixed Seafood Teppanyaki (Set A) | E66: 40
A67: PDT | B67: [DB] Mixed Seafood Teppanyaki (Set A) | E67: 2
A68: TUN | B68: [DB] Mixed Seafood Teppanyaki (Set B) | E68: 40
A69: SQD | B69: [DB] Mixed Seafood Teppanyaki (Set B) | E69: 40
A70: PDT | B70: [DB] Mixed Seafood Teppanyaki (Set B) | E70: 2
... A73: ICT | B73: [DB] Mixed Seafood Teppanyaki (Set B) | E73: 1
A74: CT_120 | B74: [DB] Crispy Chicken w/ Egg (Set B) | C74: DON BURI (CHICKEN) | E74: 1
A75: KNI | B75: [DB] Crispy Chicken w/ Egg (Set B) | C75: DON BURI (CHICKEN) | E75: 0.25
A76: ICT | B76: [DB] Crispy Chicken w/ Egg (Set B) | C76: DON BURI (CHICKEN) | E76: 1
A77: CT_120 | B77: [DB] Crispy Chicken w/ Egg (Set A) | C77: DON BURI (CHICKEN) | E77: 1
A78: EGG | B78: [DB] Crispy Chicken w/ Egg (Set A) | C78: DON BURI (CHICKEN) | E78: 1
A79: CT_150 | B79: [DB] Grilled Chicken Terriyaki (Set A) | C79: DON BURI (CHICKEN) | E79: 1
A80: TER | B80: [DB] Grilled Chicken Terriyaki (Set A) | C80: DON BURI (CHICKEN) | E80: 1
A81: TUN | B81: [DB] Mixed Seafood Misono (Set A) | C81: DON BURI (SEAFOOD) | E81: 40
A82: SQD | B82: [DB] Mixed Seafood Misono (Set A) | C82: DON BURI (SEAFOOD) | E82: 40
A83: PDT | B83: [DB] Mixed Seafood Misono (Set A) | C83: DON BURI (SEAFOOD) | E83: 2
A84: KNI | B84: [DB] Mixed Seafood Misono (Set A) | C84: DON BURI (SEAFOOD) | E84: 0.25
A85: TEP | B85: [DB] Mixed Seafood Misono (Set A) | C85: DON BURI (SEAFOOD) | E85: 1
... A91: ICT | B91: [DB] Mixed Seafood Misono (Set B) | C91: DON BURI (SEAFOOD) | E91: 1
B96: PORK
A97: PL_060 | B97: [DB] Tonkatsu (Set A) | C97: DON BURI (PORK) | E97: 2
A98: PL_060 | B98: Tonkatsu Set B | E98: 2
A99: PL_060 | B99: [DB] Tonkatsu (Set B) | C99: DON BURI (PORK) | E99: 2
A100: ICT | B100: [DB] Tonkatsu (Set B) | C100: DON BURI (PORK) | E100: 0
A101: PL_060 | B101: [DB] Katsudon (Set B) | C101: DON BURI (PORK) | E101: 2
A102: EGG | B102: [DB] Katsudon (Set B) | C102: DON BURI (PORK) | E102: 2
A103: B+B | B103: [DB] Katsudon (Set B) | C103: DON BURI (PORK) | E103: 1
A104: TSS | B104: [DB] Katsudon (Set B) | C104: DON BURI (PORK) | E104: 130
A105: KNI | B105: [DB] Katsudon (Set B) | C105: DON BURI (PORK) | E105: 0.25
A106: ICT | B106: [DB] Katsudon (Set B) | C106: DON BURI (PORK) | E106: 1
A107: PL_060 | B107: [DB] Pork Teppanyaki/Misono (Set A) | C107: DON BURI (PORK) | E107: 2
A108: TEP | B108: [DB] Pork Teppanyaki/Misono (Set A) | C108: DON BURI (PORK) | E108: 1
A109: VDB | B109: [DB] Pork Teppanyaki/Misono (Set A) | C109: DON BURI (PORK) | E109: 1
A110: PL_060 | B110: Pork Teppanyaki Set B | E110: 2
A111: TEP | B111: Pork Teppanyaki Set B | E111: 1
A112: PL_060 | B112: Katsu Curry Set A | E112: 2
...

Sheet SUPPLY-UR
A1: SUPPLY - UNIT RATES
B4: SUPPLIER | C4: PRODUCT | E4: QUANTITY | F4: UNIT | G4: Detailed Quantity | H4: UNIT RATE | I4: AMOUNT | K4: Wastage/ Fluctuation | L4: NET | M4: Unit Rate per gms | P4: =H28*1.3 -> 318.5
C6: Japanese Rice - Sakura | E6: 1 | F6: kg | H6: 80 | I6: =H6*E6 -> 80
C7: Cane Vinegar | E7: 1 | F7: bot | H7: 105
C8: Sugar | E8: 1 | F8: kg | H8: 90
B9: BANRI | C9: Gyoza Wrapper | E9: 1 | F9: pk | I9: =H9*E9 -> 0
B10: BANRI | C10: Ramen Noodles | E10: 1 | F10: kg | H10: 220 | I10: =H10*E10 -> 220 | K10: 0.2 | L10: =1000*(100%-K10) -> 800 | M10: =IFERROR(H10/L10,0) -> 0.275
B11: BANRI | C11: Shoyo Soy Sauce | E11: 1 | F11: bot | G11: 1000 | H11: 450 | I11: =H11*E11 -> 450 | K11: 0.25 | L11: =G11*(100%-K11) -> 750 | M11: =IFERROR(H11/L11,0) -> 0.6
B12: FIRST ENTERPRISES | C12: Sola | E12: 1 | F12: case | G12: 24 | H12: 1221.75 | I12: =H12*E12 -> 1221.75 | K12: 0 | L12: =G12*(100%-K12) -> 24 | M12: =IFERROR(H12/L12,0) -> 50.90625
B13: FIRST REGAL | C13: Palm Oil | E13: 1 | F13: can | G13: 18000 | H13: 1670 | I13: =H13*E13 -> 1670 | K13: 0.2 | L13: =G13*(100%-K13) -> 14400 | M13: =IFERROR(H13/L13,0) -> 0.11597222
B14: FRANCESCO | C14: Chicken Breast | D14: CHX | E14: 1 | F14: kg | G14: 1000 | H14: 295 | I14: =H14*E14 -> 295 | K14: 0.2 | L14: =1000*(100%-K14) -> 800 | M14: =IFERROR(H14/L14,0) -> 0.36875
B15: FRANCESCO | C15: Chicken Legs - boneless | D15: CHX | E15: 1 | F15: kg | G15: 1000 | H15: 280 | I15: =H15*E15 -> 280 | K15: 0.2 | L15: =1000*(100%-K15) -> 800 | M15: =IFERROR(H15/L15,0) -> 0.35
B16: FRANCESCO | C16: Nobashi | D16: NOB | E16: 1 | F16: pk | G16: 25 | H16: 325 | I16: =H16*E16 -> 325 | K16: 0.05 | L16: =G16*(100%-K16) -> 23.75 | M16: =IFERROR(H16/L16,0) -> 13.684211
B17: FRANCESCO | C17: PDT - shrimp | E17: 1 | F17: kg | G17: 48 | H17: 650 | I17: =H17*E17 -> 650 | K17: 0.25 | L17: =G17*(100%-K17) -> 36 | M17: =IFERROR(H17/L17,0) -> 18.055556
B18: FRANCESCO | C18: Salmon | E18: 1 | F18: kg | G18: 1000 | H18: 1200 | I18: =H18*E18 -> 1200 | K18: 0.65 | L18: =G18*(100%-K18) -> 350 | M18: =IFERROR(H18/L18,0) -> 3.4285714 | O18: =3.48+0.256 -> 3.736 | P18: 5.3 | Q18: =O18/P18 -> 0.70490566
B19: FRANCESCO | C19: Squid Tube | E19: 1 | F19: kg | G19: 1000 | H19: 290 | I19: =H19*E19 -> 290 | K19: 0.25 | L19: =G19*(100%-K19) -> 750 | M19: =IFERROR(H19/L19,0) -> 0.38666667
B20: FRANCESCO | C20: Tuna Steak | E20: 1 | F20: kg | G20: 1000 | H20: 520 | I20: =H20*E20 -> 520 | K20: 0.35 | L20: =G20*(100%-K20) -> 650 | M20: =IFERROR(H20/L20,0) -> 0.8
B21: HI-QRYS | C21: Rice | E21: 1 | F21: sack | G21: 25000 | H21: 1600 | I21: =H21*E21 -> 1600 | K21: 0 | L21: =G21*(100%-K21) -> 25000 | M21: =IFERROR(H21/L21,0) -> 0.064 | N21: 150 | O21: =M21*N21 -> 9.6 | P21: 1 CUP = 210 gms
B22: MJT GAS | C22: Gas | E22: 1 | F22: tank | G22: 22 | H22: 2134 | I22: =H22*E22 -> 2134 | K22: 0.25 | L22: =G22*(100%-K22) -> 16.5 | M22: =IFERROR(H22/L22,0) -> 129.33333
B23: SHOKURYOHIN | C23: Aonori | E23: 1 | F23: pk | G23: 500 | H23: 650 | I23: =H23*E23 -> 650 | K23: 0.25 | L23: =G23*(100%-K23) -> 375 | M23: =IFERROR(H23/L23,0) -> 1.7333333
B24: SHOKURYOHIN | C24: Baran | E24: 1 | F24: box | H24: 95 | I24: =H24*E24 -> 95 | K24: 0.2 | L24: =G24*(100%-K24) -> 0 | M24: =IFERROR(H24/L24,0) -> 0
B25: SHOKURYOHIN | C25: Benishoga | E25: 1 | F25: kg | H25: 230 | I25: =H25*E25 -> 230 | K25: 0.25 | L25: =G25*(100%-K25) -> 0 | M25: =IFERROR(H25/L25,0) -> 0 | O25: =2.5*O21 -> 24
B26: SHOKURYOHIN | C26: Chicken Breast | D26: CHX | E26: 1 | F26: kg | G26: 1000 | H26: 270 | I26: =H26*E26 -> 270 | K26: 0.2 | L26: =G26*(100%-K26) -> 800 | M26: =IFERROR(H26/L26,0) -> 0.3375 | P26: 0.4 | Q26: 0.35 | R26: 0.45
B27: SHOKURYOHIN | C27: Chicken Fillet - leg | D27: CHX | E27: 1 | F27: kg | G27: 1000 | H27: 390 | I27: =H27*E27 -> 390 | K27: 0.3 | L27: =G27*(100%-K27) -> 700 | M27: =IFERROR(H27/L27,0) -> 0.55714286 | N27: 150 | O27: =M27*N27 -> 83.571429 | P27: =$O$27*P26 -> 33.428571 | Q27: =$O$27*Q26 -> 29.25 | R27: =$O$27*R26 -> 37.607143 | S27: =SUBTOTAL(9,O27:R27) -> 0
B28: SHOKURYOHIN | C28: Chicken Legs - boneless | D28: CHX | E28: 1 | F28: kg | G28: 1000 | H28: 245 | I28: =H28*E28 -> 245 | K28: 0.3 | L28: =G28*(100%-K28) -> 700 | M28: =IFERROR(H28/L28,0) -> 0.35 | N28: 40 | O28: =M28*N28 -> 14 | P28: =O28*2.2 -> 30.8
B29: SHOKURYOHIN | C29: Curry Flakes | E29: 1 | F29: kg | G29: 1000 | H29: 475 | I29: =H29*E29 -> 475 | K29: 0.25 | L29: =G29*(100%-K29) -> 750 | M29: =IFERROR(H29/L29,0) -> 0.63333333 | O29: =2.5/O25 -> 0.10416667
B30: SHOKURYOHIN | C30: Ebiko | E30: 1 | F30: pk | G30: 500 | H30: 850 | I30: =H30*E30 -> 850 | K30: 0.08 | L30: =G30*(100%-K30) -> 460 | M30: =IFERROR(H30/L30,0) -> 1.8478261
B31: SHOKURYOHIN | C31: Gary Pink | E31: 1 | F31: kg | G31: 1000 | H31: 200 | I31: =H31*E31 -> 200 | K31: 0.2 | L31: =G31*(100%-K31) -> 800 | M31: =IFERROR(H31/L31,0) -> 0.25
B32: SHOKURYOHIN | C32: Hondashi - Mrutomo | E32: 1 | F32: kg | G32: 1000 | H32: 450 | I32: =H32*E32 -> 450 | K32: 0.2 | L32: =G32*(100%-K32) -> 800 | M32: =IFERROR(H32/L32,0) -> 0.5625
B33: SHOKURYOHIN | C33: Kani | D33: KAN | E33: 1 | F33: pk | G33: 30 | H33: 250 | I33: =H33*E33 -> 250 | K33: 0.15 | L33: =G33*(100%-K33) -> 25.5 | M33: =IFERROR(H33/L33,0) -> 9.8039216
B34: SHOKURYOHIN | C34: Katsubohi - Bunito Flakes | E34: 1 | F34: kg | G34: 1000 | H34: 850 | I34: =H34*E34 -> 850 | K34: 0.25 | L34: =G34*(100%-K34) -> 750 | M34: =IFERROR(H34/L34,0) -> 1.1333333
B35: SHOKURYOHIN | C35: Kikkoman - Yamasa | E35: 1 | F35: can | G35: 18000 | H35: 2700 | I35: =H35*E35 -> 2700 | K35: 0.3 | L35: =G35*(100%-K35) -> 12600 | M35: =IFERROR(H35/L35,0) -> 0.21428571
B36: SHOKURYOHIN | C36: Miso | E36: 1 | F36: pk | G36: 1000 | H36: 150 | I36: =H36*E36 -> 150 | K36: 0.2 | L36: =G36*(100%-K36) -> 800 | M36: =IFERROR(H36/L36,0) -> 0.1875
B37: SHOKURYOHIN | C37: Mayonaise | E37: 1 | F37: kg | G37: 1000 | H37: 360 | I37: =H37*E37 -> 360 | K37: 0.05 | L37: =G37*(100%-K37) -> 950 | M37: =IFERROR(H37/L37,0) -> 0.37894737
B38: SHOKURYOHIN | C38: Naruto | E38: 1 | F38: pk | G38: 160 | H38: 92 | I38: =H38*E38 -> 92 | K38: 0.25 | L38: =G38*(100%-K38) -> 120 | M38: =IFERROR(H38/L38,0) -> 0.76666667
B39: SHOKURYOHIN | C39: Nori sheet | E39: 1 | F39: pk | G39: 100 | H39: 700 | I39: =H39*E39 -> 700 | K39: 0.15 | L39: =G39*(100%-K39) -> 85 | M39: =IFERROR(H39/L39,0) -> 8.2352941
B40: SHOKURYOHIN | C40: Okonomiyaki | E40: 1 | F40: bot | G40: 2100 | H40: 475 | I40: =H40*E40 -> 475 | K40: 0.25 | L40: =G40*(100%-K40) -> 1575 | M40: =IFERROR(H40/L40,0) -> 0.3015873
B41: SHOKURYOHIN | C41: Orikaki | E41: 1 | F41: kg | G41: 1000 | H41: 1250 | I41: =H41*E41 -> 1250 | K41: 0.25 | L41: =G41*(100%-K41) -> 750 | M41: =IFERROR(H41/L41,0) -> 1.6666667
B42: SHOKURYOHIN | C42: Pork Belly | D42: PRK | E42: 1 | F42: kg | G42: 1000 | H42: 330 | I42: =H42*E42 -> 330 | K42: 0.45 | L42: =G42*(100%-K42) -> 550 | M42: =IFERROR(H42/L42,0) -> 0.6 | N42: 50 | O42: =M42*N42 -> 30
B43: SHOKURYOHIN | C43: Porkloin | D43: PRK | E43: 1 | F43: kg | G43: 1000 | H43: 290 | I43: =H43*E43 -> 290 | K43: 0.25 | L43: =G43*(100%-K43) -> 750 | M43: =IFERROR(H43/L43,0) -> 0.38666667
B44: SHOKURYOHIN | C44: Ramen Paste - Tonkotsu | E44: 1 | F44: kg | G44: 1000 | H44: 680 | I44: =H44*E44 -> 680 | K44: 0.25 | L44: =G44*(100%-K44) -> 750 | M44: =IFERROR(H44/L44,0) -> 0.90666667
B45: SHOKURYOHIN | C45: Ryo Oil | E45: 1 | F45: bot | G45: 980 | H45: 360 | I45: =H45*E45 -> 360 | K45: 0.15 | L45: =G45*(100%-K45) -> 833 | M45: =IFERROR(H45/L45,0) -> 0.43217287
B46: SHOKURYOHIN | C46: Takuan | E46: 1 | F46: pc | H46: 115 | I46: =H46*E46 -> 115 | K46: 0.25 | L46: =G46*(100%-K46) -> 0 | M46: =IFERROR(H46/L46,0) -> 0
B47: SHOKURYOHIN | C47: Tonkatsu Sauce - Bulldog | E47: 1 | F47: bot | G47: 2100 | H47: 430 | I47: =H47*E47 -> 430 | K47: 0.25 | L47: =G47*(100%-K47) -> 1575 | M47: =IFERROR(H47/L47,0) -> 0.27301587
B48: SHOKURYOHIN | C48: Tugarashi | E48: 1 | F48: pk | G48: 300 | H48: 230 | I48: =H48*E48 -> 230 | K48: 0.25 | L48: =G48*(100%-K48) -> 225 | M48: =IFERROR(H48/L48,0) -> 1.0222222
B49: SHOKURYOHIN | C49: Wasabi | E49: 1 | F49: kg | H49: 450 | I49: =H49*E49 -> 450 | K49: 0.2 | L49: =G49*(100%-K49) -> 0 | M49: =IFERROR(H49/L49,0) -> 0
B50: MY OWN | C50: Beef | D50: BEF | E50: 1 | F50: kg | G50: 1000 | H50: 385 | I50: =H50*E50 -> 385 | K50: 0.4 | L50: =G50*(100%-K50) -> 600 | M50: =IFERROR(H50/L50,0) -> 0.64166667
B51: MY OWN | C51: Ground Beef | D51: BEF | E51: 1 | F51: kg | G51: 1000 | H51: 385 | I51: =H51*E51 -> 385 | K51: 0.4 | L51: =G51*(100%-K51) -> 600 | M51: =IFERROR(H51/L51,0) -> 0.64166667
B52: SHOKURYOHIN | C52: Maruzen | E52: 1 | F52: pk | G52: 1000 | H52: 680 | I52: =H52*E52 -> 680 | K52: 0.03 | L52: =G52*(100%-K52) -> 970 | M52: =IFERROR(H52/L52,0) -> 0.70103093
B53: HI-TOP | C53: Black Fungus | E53: 1 | F53: pk | G53: 500 | H53: 48 | I53: =H53*E53 -> 48 | K53: -0.1 | L53: =G53*(100%-K53) -> 550 | M53: =IFERROR(H53/L53,0) -> 0.087272727 | N53: tenga ng daga
C54: Spring Onion | E54: 1 | G54: 80 | H54: 40 | I54: =H54*E54 -> 40 | K54: 0.3 | L54: =G54*(100%-K54) -> 56 | M54: =IFERROR(H54/L54,0) -> 0.71428571
C55: Leek Onion | E55: 1 | G55: 120 | H55: 30 | I55: =H55*E55 -> 30 | K55: 0.3 | L55: =G55*(100%-K55) -> 84 | M55: =IFERROR(H55/L55,0) -> 0.35714286
C56: Black Sesame | E56: 1 | G56: 100 | H56: 90 | I56: =H56*E56 -> 90 | K56: 0.3 | L56: =G56*(100%-K56) -> 70 | M56: =IFERROR(H56/L56,0) -> 1.2857143
C57: Egg | E57: 1 | G57: 30 | H57: 255 | I57: =H57*E57 -> 255 | K57: 0.25 | L57: =G57*(100%-K57) -> 22.5 | M57: =IFERROR(H57/L57,0) -> 11.333333
B58: HI-TOP | C58: Mushroom | E58: 1 | F58: pk | G58: 100 | H58: 147 | I58: =H58*E58 -> 147 | K58: 0.15 | L58: =G58*(100%-K58) -> 85 | M58: =IFERROR(H58/L58,0) -> 1.7294118
B59: HI-TOP | C59: Tufo | E59: 1 | F59: pk | G59: 300 | H59: 50 | I59: =H59*E59 -> 50 | K59: 0.25 | L59: =G59*(100%-K59) -> 225 | M59: =IFERROR(H59/L59,0) -> 0.22222222
C60: Carrots | E60: 1 | F60: kg | G60: 1000 | H60: 142 | I60: =H60*E60 -> 142 | K60: 0.25 | L60: =G60*(100%-K60) -> 750 | M60: =IFERROR(H60/L60,0) -> 0.18933333
C61: Cabbage | E61: 1 | F61: kg | G61: 1000 | H61: 110 | I61: =H61*E61 -> 110 | K61: 0.35 | L61: =G61*(100%-K61) -> 650 | M61: =IFERROR(H61/L61,0) -> 0.16923077
C62: Togue | E62: 1 | F62: kg | G62: 1000 | H62: 60 | I62: =H62*E62 -> 60 | K62: 0.4 | L62: =G62*(100%-K62) -> 600 | M62: =IFERROR(H62/L62,0) -> 0.1
C63: Bell Pepper | E63: 1 | F63: kg | G63: 1000 | H63: 300 | I63: =H63*E63 -> 300 | K63: 0.3 | L63: =G63*(100%-K63) -> 700 | M63: =IFERROR(H63/L63,0) -> 0.42857143
C64: White Onion | E64: 1 | F64: kg | G64: 1000 | H64: 140 | I64: =H64*E64 -> 140 | K64: 0.3 | L64: =G64*(100%-K64) -> 700 | M64: =IFERROR(H64/L64,0) -> 0.2
C65: Garlic | E65: 1 | F65: kg | G65: 1000 | H65: 180 | I65: =H65*E65 -> 180 | K65: 0.3 | L65: =G65*(100%-K65) -> 700 | M65: =IFERROR(H65/L65,0) -> 0.25714286
C66: All purpose Flour | E66: 1 | F66: kg | G66: 1000 | H66: 60 | I66: =H66*E66 -> 60 | K66: 0.25 | L66: =G66*(100%-K66) -> 750 | M66: =IFERROR(H66/L66,0) -> 0.08
C67: Panko Orange | E67: 1 | F67: kg | G67: 1000 | H67: 280 | I67: =H67*E67 -> 280 | K67: 0.25 | L67: =G67*(100%-K67) -> 750 | M67: =IFERROR(H67/L67,0) -> 0.37333333
C68: Packaging | E68: 1 | F68: pc | G68: 1 | H68: 12 | I68: =H68*E68 -> 12 | K68: 0 | L68: =G68*(100%-K68) -> 1 | M68: =IFERROR(H68/L68,0) -> 12
C69: Baguio Pechay | E69: 1 | F69: kg | G69: 1000 | H69: 120 | I69: =H69*E69 -> 120 | K69: 0.3 | L69: =G69*(100%-K69) -> 700 | M69: =IFERROR(H69/L69,0) -> 0.17142857
B70: MY OWN | C70: Ground Pork | D70: PRK | E70: 1 | F70: kg | G70: 1000 | H70: 350 | I70: =H70*E70 -> 350 | K70: 0.25 | L70: =G70*(100%-K70) -> 750 | M70: =IFERROR(H70/L70,0) -> 0.46666667
B71: SHOKURYOHIN | C71: Tantanmen | E71: 2 | F71: kg | G71: 1000 | H71: 950 | I71: =H71*E71 -> 1900 | K71: 0.15 | L71: =G71*(100%-K71) -> 850 | M71: =IFERROR(H71/L71,0) -> 1.1176471
B72: HI-TOP | C72: Mirin | E72: 1 | F72: bot | G72: 500 | H72: 196 | I72: =H72*E72 -> 196 | K72: 0.08 | L72: =G72*(100%-K72) -> 460 | M72: =IFERROR(H72/L72,0) -> 0.42608696
C73: Mango | E73: 1 | F73: kg | G73: 1000 | H73: 300 | I73: =H73*E73 -> 300 | K73: 0.5 | L73: =G73*(100%-K73) -> 500 | M73: =IFERROR(H73/L73,0) -> 0.6
C74: Cucumber | E74: 1 | F74: kg | G74: 1000 | H74: 250 | I74: =H74*E74 -> 250 | K74: 0.5 | L74: =G74*(100%-K74) -> 500 | M74: =IFERROR(H74/L74,0) -> 0.5
C75: Packaging | E75: 1 | F75: pc | G75: 1 | H75: 12 | I75: =H75*E75 -> 12 | K75: 0 | L75: =G75*(100%-K75) -> 1 | M75: =IFERROR(H75/L75,0) -> 12
C76: Sushi Rice | E76: 1 | F76: kg | G76: 1000 | H76: =(2*H6)+H7+(1*H8)+1 -> 356 | I76: =H76*E76 -> 356 | K76: 0.1 | L76: =G76*(100%-K76) -> 900 | M76: =IFERROR(H76/L76,0) -> 0.39555556
B77: HI-TOP | C77: Kani - Sushi | D77: KAN | E77: 1 | F77: pk | G77: 30 | H77: 270 | I77: =H77*E77 -> 270 | K77: 0.15 | L77: =G77*(100%-K77) -> 25.5 | M77: =IFERROR(H77/L77,0) -> 10.588235 | N77: ICHIBAN
B78: HI-TOP | C78: Kikkoman | E78: 1 | F78: bot | G78: 1000 | H78: 258 | I78: =H78*E78 -> 258 | K78: 0.2 | L78: =G78*(100%-K78) -> 800 | M78: =IFERROR(H78/L78,0) -> 0.3225
C79: BATTER
I89: =H89*E89 -> 0 | L89: =G89*(100%-K89) -> 0 | M89: =IFERROR(H89/L89,0) -> 0
I90: =H90*E90 -> 0 | L90: =G90*(100%-K90) -> 0 | M90: =IFERROR(H90/L90,0) -> 0
N91: 3.25
N92: 1.35
N93: =N91/2 -> 1.625

Sheet SUM-SALES25
R2: Sukiyaki Beef 50gms | S2: Ground Beef | T2: Sukiyaki Beef 30gms | U2: Ground Beef 60gms | V2: Porkloin 50gms | W2: Porkloin 60gms | X2: Porkloin 20gms | Y2: Pork Belly 60gms | Z2: Pork Belly 120gms | AA2: Chicken Fillet 40gms | AB2: Chicken Fillet 50gms | AC2: Chicken Fillet 60gms | AD2: Chicken Thigh 120gms | AE2: Chicken Thigh 150gms | AG2: Tuna | AH2: Salmon | AI2: Squid | AJ2: Squid 10 | AM2: Kani | AN2: Nobashi | AO2: Shrimp | AP2: Gyoza | AQ2: Tempura Sauce | AR2: Teppanyaki Sauce | AS2: Terriyaki Sauce | AT2: Marusen/ Ebara | AU2: Shoyo Sauce | AV2: Sushi Rice | AW2: Okonomiyaki Sauce | AX2: Ramen Noodle | AY2: Egg Noodle | AZ2: Egg | BA2: Breaded+ Bater | BB2: Benishoga | BC2: All Purpose Flour | BD2: Tufo | BE2: Ice Tea | BF2: Mushroom | BG2: Mushroom Okonomiyaki | BH2: M&M Vegetables | BI2: Donburi Vegetables | BJ2: REG. Vegetables | BK2: Vegetabales Okonomiyaki | BL2: Moyashi | BM2: Cucumber | BN2: Cooking Oil | BO2: TOTAL | BQ2: PORKLOIN | BR2: SUKIYAKI BEEF | BS2: GROUND BEEF | BT2: PORK | BU2: CHICKEN FILLET | BV2: CHICKEN BREAST | BW2: CHICKKEN THIGH
A3: Category | B3: (All) | R3: =R5*50 -> 100 | S3: =S5*50 -> 0 | T3: =T5*30 -> 0 | U3: =U5*60 -> 0 | V3: =V5*50 -> 0 | W3: =W5*60 -> 0 | X3: =X5*20 -> 0 | Y3: =Y5*60 -> 120 | Z3: =Z5*120 -> 0 | AA3: =AA5*40 -> 0 | AB3: =AB5*50 -> 0 | AC3: =AC5*60 -> 120 | AD3: =AD5*120 -> 120 | AE3: =AE5*150 -> 0 | AF3: =AF5*150 -> 0 | BQ3: PL | BR3: SB | BS3: GB | BT3: PB | BU3: CF | BV3: CB | BW3: CT
R4: SB_050 | S4: GB_050 | T4: SB_030 | U4: GB_060 | V4: PL_050 | W4: PL_060 | X4: PL_020 | Y4: PB_060 | Z4: PB_120 | AA4: CF_040 | AB4: CF_050 | AC4: CF_060 | AD4: CT_120 | AE4: CT_150 | AG4: TUN | AH4: SAL | AI4: SQD | AJ4: SQD_10 | AK4: SQD_15 | AL4: SQD_20 | AM4: KNI | AN4: EBI | AO4: PDT | AP4: GZA | AQ4: TSS | AR4: TEP | AS4: TER | AT4: MZN | AU4: SHO | AV4: SUS | AW4: OKO | AX4: NOD | AY4: ENOD | AZ4: EGG | BA4: B+B | BB4: BSG | BC4: APF | BD4: TUF | BE4: ICT | BF4: MUS | BG4: MUO | BH4: VMM | BI4: VDB | BJ4: VRG | BK4: VOK | BL4: VMO | BM4: CUC | BN4: OIL
B5: Sum of Net sales | C5: Sum of Items sold | Q5: Sum of Items sold | R5: =SUM(R6:R223) -> 2 | S5: =SUM(S6:S223) -> 0 | T5: =SUM(T6:T223) -> 0 | U5: =SUM(U6:U223) -> 0 | V5: =SUM(V6:V223) -> 0 | W5: =SUM(W6:W223) -> 0 | X5: =SUM(X6:X223) -> 0 | Y5: =SUM(Y6:Y223) -> 2 | ... AE5: =SUM(AE6:AE223) -> 0 | AG5: =SUM(AG6:AG223) -> 60 | AH5: =SUM(AH6:AH223) -> 80 | AI5: =SUM(AI6:AI223) -> 20 | AJ5: =SUM(AJ6:AJ223) -> 1 | AK5: =SUM(AK6:AK223) -> 0 | AL5: =SUM(AL6:AL223) -> 0 | AM5: =SUM(AM6:AM223) -> 3.25 | AN5: =SUM(AN6:AN223) -> 2 | ... BN5: =SUM(BN6:BN223) -> 0
A6: [DB] Crispy Chicken w/ Egg (Set B) | B6: 345 | C6: 1 | Q6: 1 | R6: {=IFERROR(_xlfn.XLOOKUP($A6&R$4,MEN_DES&MEN_COD,MEN_GMS),0)} -> 0 | S6: {=IFERROR(_xlfn.XLOOKUP($A6&S$4,MEN_DES&MEN_COD,MEN_GMS),0)*$Q6} -> 0 | T6: {=IFERROR(_xlfn.XLOOKUP($A6&T$4,MEN_DES&MEN_COD,MEN_GMS),0)*$Q6} -> 0 | U6: {=IFERROR(_xlfn.XLOOKUP($A6&U$4,MEN_DES&MEN_COD,MEN_GMS),0)*$Q6} -> 0 | V6: {=IFERROR(_xlfn.XLOOKUP($A6&V$4,MEN_DES&MEN_COD,MEN_GMS),0)*$Q6} -> 0 | W6: {=IFERROR(_xlfn.XLOOKUP($A6&W$4,MEN_DES&MEN_COD,MEN_GMS),0)*$Q6} -> 0 | X6: {=IFERROR(_xlfn.XLOOKUP($A6&X$4,MEN_DES&MEN_COD,MEN_GMS),0)*$Q6} -> 0 | Y6: {=IFERROR(_xlfn.XLOOKUP($A6&Y$4,MEN_DES&MEN_COD,MEN_GMS),0)*$Q6} -> 0 | Z6: {=IFERROR(_xlfn.XLOOKUP($A6&Z$4,MEN_DES&MEN_COD,MEN_GMS),0)*$Q6} -> 0 | ... AE6: {=IFERROR(_xlfn.XLOOKUP($A6&AE$4,MEN_DES&MEN_COD,MEN_GMS),0)*$Q6} -> 0 | AG6: {=IFERROR(_xlfn.XLOOKUP($A6&AG$4,MEN_DES&MEN_COD,MEN_GMS),0)*$Q6} -> 0 | AH6: {=IFERROR(_xlfn.XLOOKUP($A6&AH$4,MEN_DES&MEN_COD,MEN_GMS),0)*$Q6} -> 0 | AI6: {=IFERROR(_xlfn.XLOOKUP($A6&AI$4,MEN_DES&MEN_COD,MEN_GMS),0)*$Q6} -> 0 | AJ6: {=IFERROR(_xlfn.XLOOKUP($A6&AJ$4,MEN_DES&MEN_COD,MEN_GMS),0)*$Q6} -> 0 | AK6: {=IFERROR(_xlfn.XLOOKUP($A6&AK$4,MEN_DES&MEN_COD,MEN_GMS),0)*$Q6} -> 0 | AL6: {=IFERROR(_xlfn.XLOOKUP($A6&AL$4,MEN_DES&MEN_COD,MEN_GMS),0)*$Q6} -> 0 | AM6: {=IFERROR(_xlfn.XLOOKUP($A6&AM$4,MEN_DES&MEN_COD,MEN_GMS),0)*$Q6} -> 0.25 | AN6: {=IFERROR(_xlfn.XLOOKUP($A6&AN$4,MEN_DES&MEN_COD,MEN_GMS),0)*$Q6} -> 0 | ... BN6: {=IFERROR(_xlfn.XLOOKUP($A6&BN$4,MEN_DES&MEN_COD,MEN_GMS),0)*$Q6} -> 0 | BO6: =SUM(R6:BN6) -> 2.25
A7: [DS] Coke/Sprite/Royal/Rootbeer | B7: 88 | C7: 1 | Q7: 1 | R7: {=IFERROR(_xlfn.XLOOKUP($A7&R$4,MEN_DES&MEN_COD,MEN_GMS),0)} -> 0 | S7: {=IFERROR(_xlfn.XLOOKUP($A7&S$4,MEN_DES&MEN_COD,MEN_GMS),0)*$Q7} -> 0 | T7: {=IFERROR(_xlfn.XLOOKUP($A7&T$4,MEN_DES&MEN_COD,MEN_GMS),0)*$Q7} -> 0 | U7: {=IFERROR(_xlfn.XLOOKUP($A7&U$4,MEN_DES&MEN_COD,MEN_GMS),0)*$Q7} -> 0 | V7: {=IFERROR(_xlfn.XLOOKUP($A7&V$4,MEN_DES&MEN_COD,MEN_GMS),0)*$Q7} -> 0 | W7: {=IFERROR(_xlfn.XLOOKUP($A7&W$4,MEN_DES&MEN_COD,MEN_GMS),0)*$Q7} -> 0 | X7: {=IFERROR(_xlfn.XLOOKUP($A7&X$4,MEN_DES&MEN_COD,MEN_GMS),0)*$Q7} -> 0 | Y7: {=IFERROR(_xlfn.XLOOKUP($A7&Y$4,MEN_DES&MEN_COD,MEN_GMS),0)*$Q7} -> 0 | Z7: {=IFERROR(_xlfn.XLOOKUP($A7&Z$4,MEN_DES&MEN_COD,MEN_GMS),0)*$Q7} -> 0 | ... AE7: {=IFERROR(_xlfn.XLOOKUP($A7&AE$4,MEN_DES&MEN_COD,MEN_GMS),0)*$Q7} -> 0 | AG7: {=IFERROR(_xlfn.XLOOKUP($A7&AG$4,MEN_DES&MEN_COD,MEN_GMS),0)*$Q7} -> 0 | AH7: {=IFERROR(_xlfn.XLOOKUP($A7&AH$4,MEN_DES&MEN_COD,MEN_GMS),0)*$Q7} -> 0 | AI7: {=IFERROR(_xlfn.XLOOKUP($A7&AI$4,MEN_DES&MEN_COD,MEN_GMS),0)*$Q7} -> 0 | AJ7: {=IFERROR(_xlfn.XLOOKUP($A7&AJ$4,MEN_DES&MEN_COD,MEN_GMS),0)*$Q7} -> 0 | AK7: {=IFERROR(_xlfn.XLOOKUP($A7&AK$4,MEN_DES&MEN_COD,MEN_GMS),0)*$Q7} -> 0 | AL7: {=IFERROR(_xlfn.XLOOKUP($A7&AL$4,MEN_DES&MEN_COD,MEN_GMS),0)*$Q7} -> 0 | AM7: {=IFERROR(_xlfn.XLOOKUP($A7&AM$4,MEN_DES&MEN_COD,MEN_GMS),0)*$Q7} -> 0 | AN7: {=IFERROR(_xlfn.XLOOKUP($A7&AN$4,MEN_DES&MEN_COD,MEN_GMS),0)*$Q7} -> 0 | ... BN7: {=IFERROR(_xlfn.XLOOKUP($A7&BN$4,MEN_DES&MEN_COD,MEN_GMS),0)*$Q7} -> 0 | BO7: =SUM(R7:BN7) -> 0
A8: [DS] Sola | B8: 118 | C8: 1 | Q8: 1 | R8: {=IFERROR(_xlfn.XLOOKUP($A8&R$4,MEN_DES&MEN_COD,MEN_GMS),0)*$Q8} -> 0 | S8: {=IFERROR(_xlfn.XLOOKUP($A8&S$4,MEN_DES&MEN_COD,MEN_GMS),0)*$Q8} -> 0 | T8: {=IFERROR(_xlfn.XLOOKUP($A8&T$4,MEN_DES&MEN_COD,MEN_GMS),0)*$Q8} -> 0 | U8: {=IFERROR(_xlfn.XLOOKUP($A8&U$4,MEN_DES&MEN_COD,MEN_GMS),0)*$Q8} -> 0 | V8: {=IFERROR(_xlfn.XLOOKUP($A8&V$4,MEN_DES&MEN_COD,MEN_GMS),0)*$Q8} -> 0 | W8: {=IFERROR(_xlfn.XLOOKUP($A8&W$4,MEN_DES&MEN_COD,MEN_GMS),0)*$Q8} -> 0 | X8: {=IFERROR(_xlfn.XLOOKUP($A8&X$4,MEN_DES&MEN_COD,MEN_GMS),0)*$Q8} -> 0 | Y8: {=IFERROR(_xlfn.XLOOKUP($A8&Y$4,MEN_DES&MEN_COD,MEN_GMS),0)*$Q8} -> 0 | ... AE8: {=IFERROR(_xlfn.XLOOKUP($A8&AE$4,MEN_DES&MEN_COD,MEN_GMS),0)*$Q8} -> 0 | AG8: {=IFERROR(_xlfn.XLOOKUP($A8&AG$4,MEN_DES&MEN_COD,MEN_GMS),0)*$Q8} -> 0 | AH8: {=IFERROR(_xlfn.XLOOKUP($A8&AH$4,MEN_DES&MEN_COD,MEN_GMS),0)*$Q8} -> 0 | AI8: {=IFERROR(_xlfn.XLOOKUP($A8&AI$4,MEN_DES&MEN_COD,MEN_GMS),0)*$Q8} -> 0 | AJ8: {=IFERROR(_xlfn.XLOOKUP($A8&AJ$4,MEN_DES&MEN_COD,MEN_GMS),0)*$Q8} -> 0 | AK8: {=IFERROR(_xlfn.XLOOKUP($A8&AK$4,MEN_DES&MEN_COD,MEN_GMS),0)*$Q8} -> 0 | AL8: {=IFERROR(_xlfn.XLOOKUP($A8&AL$4,MEN_DES&MEN_COD,MEN_GMS),0)*$Q8} -> 0 | AM8: {=IFERROR(_xlfn.XLOOKUP($A8&AM$4,MEN_DES&MEN_COD,MEN_GMS),0)*$Q8} -> 0 | AN8: {=IFERROR(_xlfn.XLOOKUP($A8&AN$4,MEN_DES&MEN_COD,MEN_GMS),0)*$Q8} -> 0 | ... BN8: {=IFERROR(_xlfn.XLOOKUP($A8&BN$4,MEN_DES&MEN_COD,MEN_GMS),0)*$Q8} -> 0 | BO8: =SUM(R8:BN8) -> 0
A9: [MM] SF w/ Tuna & Salmon Sashimi & Ebi Tempura | B9: 310 | C9: 1 | Q9: 1 | R9: {=IFERROR(_xlfn.XLOOKUP($A9&R$4,MEN_DES&MEN_COD,MEN_GMS),0)*$Q9} -> 0 | S9: {=IFERROR(_xlfn.XLOOKUP($A9&S$4,MEN_DES&MEN_COD,MEN_GMS),0)*$Q9} -> 0 | T9: {=IFERROR(_xlfn.XLOOKUP($A9&T$4,MEN_DES&MEN_COD,MEN_GMS),0)*$Q9} -> 0 | U9: {=IFERROR(_xlfn.XLOOKUP($A9&U$4,MEN_DES&MEN_COD,MEN_GMS),0)*$Q9} -> 0 | V9: {=IFERROR(_xlfn.XLOOKUP($A9&V$4,MEN_DES&MEN_COD,MEN_GMS),0)*$Q9} -> 0 | W9: {=IFERROR(_xlfn.XLOOKUP($A9&W$4,MEN_DES&MEN_COD,MEN_GMS),0)*$Q9} -> 0 | X9: {=IFERROR(_xlfn.XLOOKUP($A9&X$4,MEN_DES&MEN_COD,MEN_GMS),0)*$Q9} -> 0 | Y9: {=IFERROR(_xlfn.XLOOKUP($A9&Y$4,MEN_DES&MEN_COD,MEN_GMS),0)*$Q9} -> 0 | ... AE9: {=IFERROR(_xlfn.XLOOKUP($A9&AE$4,MEN_DES&MEN_COD,MEN_GMS),0)*$Q9} -> 0 | AG9: {=IFERROR(_xlfn.XLOOKUP($A9&AG$4,MEN_DES&MEN_COD,MEN_GMS),0)*$Q9} -> 30 | AH9: {=IFERROR(_xlfn.XLOOKUP($A9&AH$4,MEN_DES&MEN_COD,MEN_GMS),0)*$Q9} -> 30 | AI9: {=IFERROR(_xlfn.XLOOKUP($A9&AI$4,MEN_DES&MEN_COD,MEN_GMS),0)*$Q9} -> 0 | AJ9: {=IFERROR(_xlfn.XLOOKUP($A9&AJ$4,MEN_DES&MEN_COD,MEN_GMS),0)*$Q9} -> 1 | AK9: {=IFERROR(_xlfn.XLOOKUP($A9&AK$4,MEN_DES&MEN_COD,MEN_GMS),0)*$Q9} -> 0 | AL9: {=IFERROR(_xlfn.XLOOKUP($A9&AL$4,MEN_DES&MEN_COD,MEN_GMS),0)*$Q9} -> 0 | AM9: {=IFERROR(_xlfn.XLOOKUP($A9&AM$4,MEN_DES&MEN_COD,MEN_GMS),0)*$Q9} -> 0 | AN9: {=IFERROR(_xlfn.XLOOKUP($A9&AN$4,MEN_DES&MEN_COD,MEN_GMS),0)*$Q9} -> 2 | ... BN9: {=IFERROR(_xlfn.XLOOKUP($A9&BN$4,MEN_DES&MEN_COD,MEN_GMS),0)*$Q9} -> 0 | BO9: =SUM(R9:BN9) -> 96
A10: [MR] California Maki | B10: 570 | C10: 3 | Q10: 3 | R10: {=IFERROR(_xlfn.XLOOKUP($A10&R$4,MEN_DES&MEN_COD,MEN_GMS),0)*$Q10} -> 0 | S10: {=IFERROR(_xlfn.XLOOKUP($A10&S$4,MEN_DES&MEN_COD,MEN_GMS),0)*$Q10} -> 0 | T10: {=IFERROR(_xlfn.XLOOKUP($A10&T$4,MEN_DES&MEN_COD,MEN_GMS),0)*$Q10} -> 0 | U10: {=IFERROR(_xlfn.XLOOKUP($A10&U$4,MEN_DES&MEN_COD,MEN_GMS),0)*$Q10} -> 0 | V10: {=IFERROR(_xlfn.XLOOKUP($A10&V$4,MEN_DES&MEN_COD,MEN_GMS),0)*$Q10} -> 0 | W10: {=IFERROR(_xlfn.XLOOKUP($A10&W$4,MEN_DES&MEN_COD,MEN_GMS),0)*$Q10} -> 0 | X10: {=IFERROR(_xlfn.XLOOKUP($A10&X$4,MEN_DES&MEN_COD,MEN_GMS),0)*$Q10} -> 0 | Y10: {=IFERROR(_xlfn.XLOOKUP($A10&Y$4,MEN_DES&MEN_COD,MEN_GMS),0)*$Q10} -> 0 | ... AE10: {=IFERROR(_xlfn.XLOOKUP($A10&AE$4,MEN_DES&MEN_COD,MEN_GMS),0)*$Q10} -> 0 | AG10: {=IFERROR(_xlfn.XLOOKUP($A10&AG$4,MEN_DES&MEN_COD,MEN_GMS),0)*$Q10} -> 0 | AH10: {=IFERROR(_xlfn.XLOOKUP($A10&AH$4,MEN_DES&MEN_COD,MEN_GMS),0)*$Q10} -> 0 | AI10: {=IFERROR(_xlfn.XLOOKUP($A10&AI$4,MEN_DES&MEN_COD,MEN_GMS),0)*$Q10} -> 0 | AJ10: {=IFERROR(_xlfn.XLOOKUP($A10&AJ$4,MEN_DES&MEN_COD,MEN_GMS),0)*$Q10} -> 0 | AK10: {=IFERROR(_xlfn.XLOOKUP($A10&AK$4,MEN_DES&MEN_COD,MEN_GMS),0)*$Q10} -> 0 | AL10: {=IFERROR(_xlfn.XLOOKUP($A10&AL$4,MEN_DES&MEN_COD,MEN_GMS),0)*$Q10} -> 0 | AM10: {=IFERROR(_xlfn.XLOOKUP($A10&AM$4,MEN_DES&MEN_COD,MEN_GMS),0)*$Q10} -> 3 | AN10: {=IFERROR(_xlfn.XLOOKUP($A10&AN$4,MEN_DES&MEN_COD,MEN_GMS),0)*$Q10} -> 0 | ... BN10: {=IFERROR(_xlfn.XLOOKUP($A10&BN$4,MEN_DES&MEN_COD,MEN_GMS),0)*$Q10} -> 0 | BO10: =SUM(R10:BN10) -> 370.5
A11: [MR] Salmon Spicy | B11: 330 | C11: 1 | Q11: 1 | R11: {=IFERROR(_xlfn.XLOOKUP($A11&R$4,MEN_DES&MEN_COD,MEN_GMS),0)*$Q11} -> 0 | S11: {=IFERROR(_xlfn.XLOOKUP($A11&S$4,MEN_DES&MEN_COD,MEN_GMS),0)*$Q11} -> 0 | T11: {=IFERROR(_xlfn.XLOOKUP($A11&T$4,MEN_DES&MEN_COD,MEN_GMS),0)*$Q11} -> 0 | U11: {=IFERROR(_xlfn.XLOOKUP($A11&U$4,MEN_DES&MEN_COD,MEN_GMS),0)*$Q11} -> 0 | V11: {=IFERROR(_xlfn.XLOOKUP($A11&V$4,MEN_DES&MEN_COD,MEN_GMS),0)*$Q11} -> 0 | W11: {=IFERROR(_xlfn.XLOOKUP($A11&W$4,MEN_DES&MEN_COD,MEN_GMS),0)*$Q11} -> 0 | X11: {=IFERROR(_xlfn.XLOOKUP($A11&X$4,MEN_DES&MEN_COD,MEN_GMS),0)*$Q11} -> 0 | Y11: {=IFERROR(_xlfn.XLOOKUP($A11&Y$4,MEN_DES&MEN_COD,MEN_GMS),0)*$Q11} -> 0 | ... AE11: {=IFERROR(_xlfn.XLOOKUP($A11&AE$4,MEN_DES&MEN_COD,MEN_GMS),0)*$Q11} -> 0 | AG11: {=IFERROR(_xlfn.XLOOKUP($A11&AG$4,MEN_DES&MEN_COD,MEN_GMS),0)*$Q11} -> 0 | AH11: {=IFERROR(_xlfn.XLOOKUP($A11&AH$4,MEN_DES&MEN_COD,MEN_GMS),0)*$Q11} -> 50 | AI11: {=IFERROR(_xlfn.XLOOKUP($A11&AI$4,MEN_DES&MEN_COD,MEN_GMS),0)*$Q11} -> 0 | AJ11: {=IFERROR(_xlfn.XLOOKUP($A11&AJ$4,MEN_DES&MEN_COD,MEN_GMS),0)*$Q11} -> 0 | AK11: {=IFERROR(_xlfn.XLOOKUP($A11&AK$4,MEN_DES&MEN_COD,MEN_GMS),0)*$Q11} -> 0 | AL11: {=IFERROR(_xlfn.XLOOKUP($A11&AL$4,MEN_DES&MEN_COD,MEN_GMS),0)*$Q11} -> 0 | AM11: {=IFERROR(_xlfn.XLOOKUP($A11&AM$4,MEN_DES&MEN_COD,MEN_GMS),0)*$Q11} -> 0 | AN11: {=IFERROR(_xlfn.XLOOKUP($A11&AN$4,MEN_DES&MEN_COD,MEN_GMS),0)*$Q11} -> 0 | ... BN11: {=IFERROR(_xlfn.XLOOKUP($A11&BN$4,MEN_DES&MEN_COD,MEN_GMS),0)*$Q11} -> 0 | BO11: =SUM(R11:BN11) -> 150
A12: [PR] 4pcs Gyoza | B12: 173.38 | C12: 1 | Q12: 1 | R12: {=IFERROR(_xlfn.XLOOKUP($A12&R$4,MEN_DES&MEN_COD,MEN_GMS),0)*$Q12} -> 0 | S12: {=IFERROR(_xlfn.XLOOKUP($A12&S$4,MEN_DES&MEN_COD,MEN_GMS),0)*$Q12} -> 0 | T12: {=IFERROR(_xlfn.XLOOKUP($A12&T$4,MEN_DES&MEN_COD,MEN_GMS),0)*$Q12} -> 0 | U12: {=IFERROR(_xlfn.XLOOKUP($A12&U$4,MEN_DES&MEN_COD,MEN_GMS),0)*$Q12} -> 0 | V12: {=IFERROR(_xlfn.XLOOKUP($A12&V$4,MEN_DES&MEN_COD,MEN_GMS),0)*$Q12} -> 0 | W12: {=IFERROR(_xlfn.XLOOKUP($A12&W$4,MEN_DES&MEN_COD,MEN_GMS),0)*$Q12} -> 0 | X12: {=IFERROR(_xlfn.XLOOKUP($A12&X$4,MEN_DES&MEN_COD,MEN_GMS),0)*$Q12} -> 0 | Y12: {=IFERROR(_xlfn.XLOOKUP($A12&Y$4,MEN_DES&MEN_COD,MEN_GMS),0)*$Q12} -> 0 | ... AE12: {=IFERROR(_xlfn.XLOOKUP($A12&AE$4,MEN_DES&MEN_COD,MEN_GMS),0)*$Q12} -> 0 | AG12: {=IFERROR(_xlfn.XLOOKUP($A12&AG$4,MEN_DES&MEN_COD,MEN_GMS),0)*$Q12} -> 0 | AH12: {=IFERROR(_xlfn.XLOOKUP($A12&AH$4,MEN_DES&MEN_COD,MEN_GMS),0)*$Q12} -> 0 | AI12: {=IFERROR(_xlfn.XLOOKUP($A12&AI$4,MEN_DES&MEN_COD,MEN_GMS),0)*$Q12} -> 0 | AJ12: {=IFERROR(_xlfn.XLOOKUP($A12&AJ$4,MEN_DES&MEN_COD,MEN_GMS),0)*$Q12} -> 0 | AK12: {=IFERROR(_xlfn.XLOOKUP($A12&AK$4,MEN_DES&MEN_COD,MEN_GMS),0)*$Q12} -> 0 | AL12: {=IFERROR(_xlfn.XLOOKUP($A12&AL$4,MEN_DES&MEN_COD,MEN_GMS),0)*$Q12} -> 0 | AM12: {=IFERROR(_xlfn.XLOOKUP($A12&AM$4,MEN_DES&MEN_COD,MEN_GMS),0)*$Q12} -> 0 | AN12: {=IFERROR(_xlfn.XLOOKUP($A12&AN$4,MEN_DES&MEN_COD,MEN_GMS),0)*$Q12} -> 0 | ... BN12: {=IFERROR(_xlfn.XLOOKUP($A12&BN$4,MEN_DES&MEN_COD,MEN_GMS),0)*$Q12} -> 0 | BO12: =SUM(R12:BN12) -> 0
A13: [PR] Chicken Misono | B13: 159 | C13: 1 | Q13: 1 | R13: {=IFERROR(_xlfn.XLOOKUP($A13&R$4,MEN_DES&MEN_COD,MEN_GMS),0)*$Q13} -> 0 | S13: {=IFERROR(_xlfn.XLOOKUP($A13&S$4,MEN_DES&MEN_COD,MEN_GMS),0)*$Q13} -> 0 | T13: {=IFERROR(_xlfn.XLOOKUP($A13&T$4,MEN_DES&MEN_COD,MEN_GMS),0)*$Q13} -> 0 | U13: {=IFERROR(_xlfn.XLOOKUP($A13&U$4,MEN_DES&MEN_COD,MEN_GMS),0)*$Q13} -> 0 | V13: {=IFERROR(_xlfn.XLOOKUP($A13&V$4,MEN_DES&MEN_COD,MEN_GMS),0)*$Q13} -> 0 | W13: {=IFERROR(_xlfn.XLOOKUP($A13&W$4,MEN_DES&MEN_COD,MEN_GMS),0)*$Q13} -> 0 | X13: {=IFERROR(_xlfn.XLOOKUP($A13&X$4,MEN_DES&MEN_COD,MEN_GMS),0)*$Q13} -> 0 | Y13: {=IFERROR(_xlfn.XLOOKUP($A13&Y$4,MEN_DES&MEN_COD,MEN_GMS),0)*$Q13} -> 0 | ... AE13: {=IFERROR(_xlfn.XLOOKUP($A13&AE$4,MEN_DES&MEN_COD,MEN_GMS),0)*$Q13} -> 0 | AG13: {=IFERROR(_xlfn.XLOOKUP($A13&AG$4,MEN_DES&MEN_COD,MEN_GMS),0)*$Q13} -> 0 | AH13: {=IFERROR(_xlfn.XLOOKUP($A13&AH$4,MEN_DES&MEN_COD,MEN_GMS),0)*$Q13} -> 0 | AI13: {=IFERROR(_xlfn.XLOOKUP($A13&AI$4,MEN_DES&MEN_COD,MEN_GMS),0)*$Q13} -> 0 | AJ13: {=IFERROR(_xlfn.XLOOKUP($A13&AJ$4,MEN_DES&MEN_COD,MEN_GMS),0)*$Q13} -> 0 | AK13: {=IFERROR(_xlfn.XLOOKUP($A13&AK$4,MEN_DES&MEN_COD,MEN_GMS),0)*$Q13} -> 0 | AL13: {=IFERROR(_xlfn.XLOOKUP($A13&AL$4,MEN_DES&MEN_COD,MEN_GMS),0)*$Q13} -> 0 | AM13: {=IFERROR(_xlfn.XLOOKUP($A13&AM$4,MEN_DES&MEN_COD,MEN_GMS),0)*$Q13} -> 0 | AN13: {=IFERROR(_xlfn.XLOOKUP($A13&AN$4,MEN_DES&MEN_COD,MEN_GMS),0)*$Q13} -> 0 | ... BN13: {=IFERROR(_xlfn.XLOOKUP($A13&BN$4,MEN_DES&MEN_COD,MEN_GMS),0)*$Q13} -> 0 | BO13: =SUM(R13:BN13) -> 3
A14: [PR] Okonomiyaki Buttered Chicken | B14: 209 | C14: 1 | Q14: 1 | R14: {=IFERROR(_xlfn.XLOOKUP($A14&R$4,MEN_DES&MEN_COD,MEN_GMS),0)*$Q14} -> 0 | S14: {=IFERROR(_xlfn.XLOOKUP($A14&S$4,MEN_DES&MEN_COD,MEN_GMS),0)*$Q14} -> 0 | T14: {=IFERROR(_xlfn.XLOOKUP($A14&T$4,MEN_DES&MEN_COD,MEN_GMS),0)*$Q14} -> 0 | U14: {=IFERROR(_xlfn.XLOOKUP($A14&U$4,MEN_DES&MEN_COD,MEN_GMS),0)*$Q14} -> 0 | V14: {=IFERROR(_xlfn.XLOOKUP($A14&V$4,MEN_DES&MEN_COD,MEN_GMS),0)*$Q14} -> 0 | W14: {=IFERROR(_xlfn.XLOOKUP($A14&W$4,MEN_DES&MEN_COD,MEN_GMS),0)*$Q14} -> 0 | X14: {=IFERROR(_xlfn.XLOOKUP($A14&X$4,MEN_DES&MEN_COD,MEN_GMS),0)*$Q14} -> 0 | Y14: {=IFERROR(_xlfn.XLOOKUP($A14&Y$4,MEN_DES&MEN_COD,MEN_GMS),0)*$Q14} -> 0 | ... AE14: {=IFERROR(_xlfn.XLOOKUP($A14&AE$4,MEN_DES&MEN_COD,MEN_GMS),0)*$Q14} -> 0 | AG14: {=IFERROR(_xlfn.XLOOKUP($A14&AG$4,MEN_DES&MEN_COD,MEN_GMS),0)*$Q14} -> 0 | AH14: {=IFERROR(_xlfn.XLOOKUP($A14&AH$4,MEN_DES&MEN_COD,MEN_GMS),0)*$Q14} -> 0 | AI14: {=IFERROR(_xlfn.XLOOKUP($A14&AI$4,MEN_DES&MEN_COD,MEN_GMS),0)*$Q14} -> 0 | AJ14: {=IFERROR(_xlfn.XLOOKUP($A14&AJ$4,MEN_DES&MEN_COD,MEN_GMS),0)*$Q14} -> 0 | AK14: {=IFERROR(_xlfn.XLOOKUP($A14&AK$4,MEN_DES&MEN_COD,MEN_GMS),0)*$Q14} -> 0 | AL14: {=IFERROR(_xlfn.XLOOKUP($A14&AL$4,MEN_DES&MEN_COD,MEN_GMS),0)*$Q14} -> 0 | AM14: {=IFERROR(_xlfn.XLOOKUP($A14&AM$4,MEN_DES&MEN_COD,MEN_GMS),0)*$Q14} -> 0 | AN14: {=IFERROR(_xlfn.XLOOKUP($A14&AN$4,MEN_DES&MEN_COD,MEN_GMS),0)*$Q14} -> 0 | ... BN14: {=IFERROR(_xlfn.XLOOKUP($A14&BN$4,MEN_DES&MEN_COD,MEN_GMS),0)*$Q14} -> 0 | BO14: =SUM(R14:BN14) -> 0
A15: [RM] Spicy Roast Pork Tomato Ramen | B15: 372.92 | C15: 1 | Q15: 1 | R15: {=IFERROR(_xlfn.XLOOKUP($A15&R$4,MEN_DES&MEN_COD,MEN_GMS),0)*$Q15} -> 0 | S15: {=IFERROR(_xlfn.XLOOKUP($A15&S$4,MEN_DES&MEN_COD,MEN_GMS),0)*$Q15} -> 0 | T15: {=IFERROR(_xlfn.XLOOKUP($A15&T$4,MEN_DES&MEN_COD,MEN_GMS),0)*$Q15} -> 0 | U15: {=IFERROR(_xlfn.XLOOKUP($A15&U$4,MEN_DES&MEN_COD,MEN_GMS),0)*$Q15} -> 0 | V15: {=IFERROR(_xlfn.XLOOKUP($A15&V$4,MEN_DES&MEN_COD,MEN_GMS),0)*$Q15} -> 0 | W15: {=IFERROR(_xlfn.XLOOKUP($A15&W$4,MEN_DES&MEN_COD,MEN_GMS),0)*$Q15} -> 0 | X15: {=IFERROR(_xlfn.XLOOKUP($A15&X$4,MEN_DES&MEN_COD,MEN_GMS),0)*$Q15} -> 0 | Y15: {=IFERROR(_xlfn.XLOOKUP($A15&Y$4,MEN_DES&MEN_COD,MEN_GMS),0)*$Q15} -> 1 | ... AE15: {=IFERROR(_xlfn.XLOOKUP($A15&AE$4,MEN_DES&MEN_COD,MEN_GMS),0)*$Q15} -> 0 | AG15: {=IFERROR(_xlfn.XLOOKUP($A15&AG$4,MEN_DES&MEN_COD,MEN_GMS),0)*$Q15} -> 0 | AH15: {=IFERROR(_xlfn.XLOOKUP($A15&AH$4,MEN_DES&MEN_COD,MEN_GMS),0)*$Q15} -> 0 | AI15: {=IFERROR(_xlfn.XLOOKUP($A15&AI$4,MEN_DES&MEN_COD,MEN_GMS),0)*$Q15} -> 0 | AJ15: {=IFERROR(_xlfn.XLOOKUP($A15&AJ$4,MEN_DES&MEN_COD,MEN_GMS),0)*$Q15} -> 0 | AK15: {=IFERROR(_xlfn.XLOOKUP($A15&AK$4,MEN_DES&MEN_COD,MEN_GMS),0)*$Q15} -> 0 | AL15: {=IFERROR(_xlfn.XLOOKUP($A15&AL$4,MEN_DES&MEN_COD,MEN_GMS),0)*$Q15} -> 0 | AM15: {=IFERROR(_xlfn.XLOOKUP($A15&AM$4,MEN_DES&MEN_COD,MEN_GMS),0)*$Q15} -> 0 | AN15: {=IFERROR(_xlfn.XLOOKUP($A15&AN$4,MEN_DES&MEN_COD,MEN_GMS),0)*$Q15} -> 0 | ... BN15: {=IFERROR(_xlfn.XLOOKUP($A15&BN$4,MEN_DES&MEN_COD,MEN_GMS),0)*$Q15} -> 0 | BO15: =SUM(R15:BN15) -> 48
A16: [RM] Tonkotsu Ramen | B16: 348.7 | C16: 1 | Q16: 1 | R16: {=IFERROR(_xlfn.XLOOKUP($A16&R$4,MEN_DES&MEN_COD,MEN_GMS),0)*$Q16} -> 0 | S16: {=IFERROR(_xlfn.XLOOKUP($A16&S$4,MEN_DES&MEN_COD,MEN_GMS),0)*$Q16} -> 0 | T16: {=IFERROR(_xlfn.XLOOKUP($A16&T$4,MEN_DES&MEN_COD,MEN_GMS),0)*$Q16} -> 0 | U16: {=IFERROR(_xlfn.XLOOKUP($A16&U$4,MEN_DES&MEN_COD,MEN_GMS),0)*$Q16} -> 0 | V16: {=IFERROR(_xlfn.XLOOKUP($A16&V$4,MEN_DES&MEN_COD,MEN_GMS),0)*$Q16} -> 0 | W16: {=IFERROR(_xlfn.XLOOKUP($A16&W$4,MEN_DES&MEN_COD,MEN_GMS),0)*$Q16} -> 0 | X16: {=IFERROR(_xlfn.XLOOKUP($A16&X$4,MEN_DES&MEN_COD,MEN_GMS),0)*$Q16} -> 0 | Y16: {=IFERROR(_xlfn.XLOOKUP($A16&Y$4,MEN_DES&MEN_COD,MEN_GMS),0)*$Q16} -> 1 | ... AE16: {=IFERROR(_xlfn.XLOOKUP($A16&AE$4,MEN_DES&MEN_COD,MEN_GMS),0)*$Q16} -> 0 | AG16: {=IFERROR(_xlfn.XLOOKUP($A16&AG$4,MEN_DES&MEN_COD,MEN_GMS),0)*$Q16} -> 0 | AH16: {=IFERROR(_xlfn.XLOOKUP($A16&AH$4,MEN_DES&MEN_COD,MEN_GMS),0)*$Q16} -> 0 | AI16: {=IFERROR(_xlfn.XLOOKUP($A16&AI$4,MEN_DES&MEN_COD,MEN_GMS),0)*$Q16} -> 0 | AJ16: {=IFERROR(_xlfn.XLOOKUP($A16&AJ$4,MEN_DES&MEN_COD,MEN_GMS),0)*$Q16} -> 0 | AK16: {=IFERROR(_xlfn.XLOOKUP($A16&AK$4,MEN_DES&MEN_COD,MEN_GMS),0)*$Q16} -> 0 | AL16: {=IFERROR(_xlfn.XLOOKUP($A16&AL$4,MEN_DES&MEN_COD,MEN_GMS),0)*$Q16} -> 0 | AM16: {=IFERROR(_xlfn.XLOOKUP($A16&AM$4,MEN_DES&MEN_COD,MEN_GMS),0)*$Q16} -> 0 | AN16: {=IFERROR(_xlfn.XLOOKUP($A16&AN$4,MEN_DES&MEN_COD,MEN_GMS),0)*$Q16} -> 0 | ... BN16: {=IFERROR(_xlfn.XLOOKUP($A16&BN$4,MEN_DES&MEN_COD,MEN_GMS),0)*$Q16} -> 0 | BO16: =SUM(R16:BN16) -> 48
A17: [SB] Cheesy Beef Terriyaki Burrito | B17: 690 | C17: 2 | Q17: 2 | R17: {=IFERROR(_xlfn.XLOOKUP($A17&R$4,MEN_DES&MEN_COD,MEN_GMS),0)*$Q17} -> 2 | S17: {=IFERROR(_xlfn.XLOOKUP($A17&S$4,MEN_DES&MEN_COD,MEN_GMS),0)*$Q17} -> 0 | T17: {=IFERROR(_xlfn.XLOOKUP($A17&T$4,MEN_DES&MEN_COD,MEN_GMS),0)*$Q17} -> 0 | U17: {=IFERROR(_xlfn.XLOOKUP($A17&U$4,MEN_DES&MEN_COD,MEN_GMS),0)*$Q17} -> 0 | V17: {=IFERROR(_xlfn.XLOOKUP($A17&V$4,MEN_DES&MEN_COD,MEN_GMS),0)*$Q17} -> 0 | W17: {=IFERROR(_xlfn.XLOOKUP($A17&W$4,MEN_DES&MEN_COD,MEN_GMS),0)*$Q17} -> 0 | X17: {=IFERROR(_xlfn.XLOOKUP($A17&X$4,MEN_DES&MEN_COD,MEN_GMS),0)*$Q17} -> 0 | Y17: {=IFERROR(_xlfn.XLOOKUP($A17&Y$4,MEN_DES&MEN_COD,MEN_GMS),0)*$Q17} -> 0 | ... AE17: {=IFERROR(_xlfn.XLOOKUP($A17&AE$4,MEN_DES&MEN_COD,MEN_GMS),0)*$Q17} -> 0 | AG17: {=IFERROR(_xlfn.XLOOKUP($A17&AG$4,MEN_DES&MEN_COD,MEN_GMS),0)*$Q17} -> 0 | AH17: {=IFERROR(_xlfn.XLOOKUP($A17&AH$4,MEN_DES&MEN_COD,MEN_GMS),0)*$Q17} -> 0 | AI17: {=IFERROR(_xlfn.XLOOKUP($A17&AI$4,MEN_DES&MEN_COD,MEN_GMS),0)*$Q17} -> 0 | AJ17: {=IFERROR(_xlfn.XLOOKUP($A17&AJ$4,MEN_DES&MEN_COD,MEN_GMS),0)*$Q17} -> 0 | AK17: {=IFERROR(_xlfn.XLOOKUP($A17&AK$4,MEN_DES&MEN_COD,MEN_GMS),0)*$Q17} -> 0 | AL17: {=IFERROR(_xlfn.XLOOKUP($A17&AL$4,MEN_DES&MEN_COD,MEN_GMS),0)*$Q17} -> 0 | AM17: {=IFERROR(_xlfn.XLOOKUP($A17&AM$4,MEN_DES&MEN_COD,MEN_GMS),0)*$Q17} -> 0 | AN17: {=IFERROR(_xlfn.XLOOKUP($A17&AN$4,MEN_DES&MEN_COD,MEN_GMS),0)*$Q17} -> 0 | ... BN17: {=IFERROR(_xlfn.XLOOKUP($A17&BN$4,MEN_DES&MEN_COD,MEN_GMS),0)*$Q17} -> 0 | BO17: =SUM(R17:BN17) -> 2
A18: [ST] Okonomiyaki Cheesy Beef (Regular) | B18: 320 | C18: 1 | Q18: 1 | R18: {=IFERROR(_xlfn.XLOOKUP($A18&R$4,MEN_DES&MEN_COD,MEN_GMS),0)*$Q18} -> 0 | S18: {=IFERROR(_xlfn.XLOOKUP($A18&S$4,MEN_DES&MEN_COD,MEN_GMS),0)*$Q18} -> 0 | T18: {=IFERROR(_xlfn.XLOOKUP($A18&T$4,MEN_DES&MEN_COD,MEN_GMS),0)*$Q18} -> 0 | U18: {=IFERROR(_xlfn.XLOOKUP($A18&U$4,MEN_DES&MEN_COD,MEN_GMS),0)*$Q18} -> 0 | V18: {=IFERROR(_xlfn.XLOOKUP($A18&V$4,MEN_DES&MEN_COD,MEN_GMS),0)*$Q18} -> 0 | W18: {=IFERROR(_xlfn.XLOOKUP($A18&W$4,MEN_DES&MEN_COD,MEN_GMS),0)*$Q18} -> 0 | X18: {=IFERROR(_xlfn.XLOOKUP($A18&X$4,MEN_DES&MEN_COD,MEN_GMS),0)*$Q18} -> 0 | Y18: {=IFERROR(_xlfn.XLOOKUP($A18&Y$4,MEN_DES&MEN_COD,MEN_GMS),0)*$Q18} -> 0 | ... AE18: {=IFERROR(_xlfn.XLOOKUP($A18&AE$4,MEN_DES&MEN_COD,MEN_GMS),0)*$Q18} -> 0 | AG18: {=IFERROR(_xlfn.XLOOKUP($A18&AG$4,MEN_DES&MEN_COD,MEN_GMS),0)*$Q18} -> 0 | AH18: {=IFERROR(_xlfn.XLOOKUP($A18&AH$4,MEN_DES&MEN_COD,MEN_GMS),0)*$Q18} -> 0 | AI18: {=IFERROR(_xlfn.XLOOKUP($A18&AI$4,MEN_DES&MEN_COD,MEN_GMS),0)*$Q18} -> 0 | AJ18: {=IFERROR(_xlfn.XLOOKUP($A18&AJ$4,MEN_DES&MEN_COD,MEN_GMS),0)*$Q18} -> 0 | AK18: {=IFERROR(_xlfn.XLOOKUP($A18&AK$4,MEN_DES&MEN_COD,MEN_GMS),0)*$Q18} -> 0 | AL18: {=IFERROR(_xlfn.XLOOKUP($A18&AL$4,MEN_DES&MEN_COD,MEN_GMS),0)*$Q18} -> 0 | AM18: {=IFERROR(_xlfn.XLOOKUP($A18&AM$4,MEN_DES&MEN_COD,MEN_GMS),0)*$Q18} -> 0 | AN18: {=IFERROR(_xlfn.XLOOKUP($A18&AN$4,MEN_DES&MEN_COD,MEN_GMS),0)*$Q18} -> 0 | ... BN18: {=IFERROR(_xlfn.XLOOKUP($A18&BN$4,MEN_DES&MEN_COD,MEN_GMS),0)*$Q18} -> 0 | BO18: =SUM(R18:BN18) -> 0
A19: Shoyu Seafood Ramen | B19: 289 | C19: 1 | Q19: 1 | R19: {=IFERROR(_xlfn.XLOOKUP($A19&R$4,MEN_DES&MEN_COD,MEN_GMS),0)*$Q19} -> 0 | S19: {=IFERROR(_xlfn.XLOOKUP($A19&S$4,MEN_DES&MEN_COD,MEN_GMS),0)*$Q19} -> 0 | T19: {=IFERROR(_xlfn.XLOOKUP($A19&T$4,MEN_DES&MEN_COD,MEN_GMS),0)*$Q19} -> 0 | U19: {=IFERROR(_xlfn.XLOOKUP($A19&U$4,MEN_DES&MEN_COD,MEN_GMS),0)*$Q19} -> 0 | V19: {=IFERROR(_xlfn.XLOOKUP($A19&V$4,MEN_DES&MEN_COD,MEN_GMS),0)*$Q19} -> 0 | W19: {=IFERROR(_xlfn.XLOOKUP($A19&W$4,MEN_DES&MEN_COD,MEN_GMS),0)*$Q19} -> 0 | X19: {=IFERROR(_xlfn.XLOOKUP($A19&X$4,MEN_DES&MEN_COD,MEN_GMS),0)*$Q19} -> 0 | Y19: {=IFERROR(_xlfn.XLOOKUP($A19&Y$4,MEN_DES&MEN_COD,MEN_GMS),0)*$Q19} -> 0 | ... AE19: {=IFERROR(_xlfn.XLOOKUP($A19&AE$4,MEN_DES&MEN_COD,MEN_GMS),0)*$Q19} -> 0 | AG19: {=IFERROR(_xlfn.XLOOKUP($A19&AG$4,MEN_DES&MEN_COD,MEN_GMS),0)*$Q19} -> 30 | AH19: {=IFERROR(_xlfn.XLOOKUP($A19&AH$4,MEN_DES&MEN_COD,MEN_GMS),0)*$Q19} -> 0 | AI19: {=IFERROR(_xlfn.XLOOKUP($A19&AI$4,MEN_DES&MEN_COD,MEN_GMS),0)*$Q19} -> 20 | AJ19: {=IFERROR(_xlfn.XLOOKUP($A19&AJ$4,MEN_DES&MEN_COD,MEN_GMS),0)*$Q19} -> 0 | AK19: {=IFERROR(_xlfn.XLOOKUP($A19&AK$4,MEN_DES&MEN_COD,MEN_GMS),0)*$Q19} -> 0 | AL19: {=IFERROR(_xlfn.XLOOKUP($A19&AL$4,MEN_DES&MEN_COD,MEN_GMS),0)*$Q19} -> 0 | AM19: {=IFERROR(_xlfn.XLOOKUP($A19&AM$4,MEN_DES&MEN_COD,MEN_GMS),0)*$Q19} -> 0 | AN19: {=IFERROR(_xlfn.XLOOKUP($A19&AN$4,MEN_DES&MEN_COD,MEN_GMS),0)*$Q19} -> 0 | ... BN19: {=IFERROR(_xlfn.XLOOKUP($A19&BN$4,MEN_DES&MEN_COD,MEN_GMS),0)*$Q19} -> 0 | BO19: =SUM(R19:BN19) -> 99
A20: Grand Total | B20: 4323 | C20: 17 | Q20: 17 | R20: {=IFERROR(_xlfn.XLOOKUP($A20&R$4,MEN_DES&MEN_COD,MEN_GMS),0)*$Q20} -> 0 | S20: {=IFERROR(_xlfn.XLOOKUP($A20&S$4,MEN_DES&MEN_COD,MEN_GMS),0)*$Q20} -> 0 | T20: {=IFERROR(_xlfn.XLOOKUP($A20&T$4,MEN_DES&MEN_COD,MEN_GMS),0)*$Q20} -> 0 | U20: {=IFERROR(_xlfn.XLOOKUP($A20&U$4,MEN_DES&MEN_COD,MEN_GMS),0)*$Q20} -> 0 | V20: {=IFERROR(_xlfn.XLOOKUP($A20&V$4,MEN_DES&MEN_COD,MEN_GMS),0)*$Q20} -> 0 | W20: {=IFERROR(_xlfn.XLOOKUP($A20&W$4,MEN_DES&MEN_COD,MEN_GMS),0)*$Q20} -> 0 | X20: {=IFERROR(_xlfn.XLOOKUP($A20&X$4,MEN_DES&MEN_COD,MEN_GMS),0)*$Q20} -> 0 | Y20: {=IFERROR(_xlfn.XLOOKUP($A20&Y$4,MEN_DES&MEN_COD,MEN_GMS),0)*$Q20} -> 0 | ... AE20: {=IFERROR(_xlfn.XLOOKUP($A20&AE$4,MEN_DES&MEN_COD,MEN_GMS),0)*$Q20} -> 0 | AG20: {=IFERROR(_xlfn.XLOOKUP($A20&AG$4,MEN_DES&MEN_COD,MEN_GMS),0)*$Q20} -> 0 | AH20: {=IFERROR(_xlfn.XLOOKUP($A20&AH$4,MEN_DES&MEN_COD,MEN_GMS),0)*$Q20} -> 0 | AI20: {=IFERROR(_xlfn.XLOOKUP($A20&AI$4,MEN_DES&MEN_COD,MEN_GMS),0)*$Q20} -> 0 | AJ20: {=IFERROR(_xlfn.XLOOKUP($A20&AJ$4,MEN_DES&MEN_COD,MEN_GMS),0)*$Q20} -> 0 | AK20: {=IFERROR(_xlfn.XLOOKUP($A20&AK$4,MEN_DES&MEN_COD,MEN_GMS),0)*$Q20} -> 0 | AL20: {=IFERROR(_xlfn.XLOOKUP($A20&AL$4,MEN_DES&MEN_COD,MEN_GMS),0)*$Q20} -> 0 | AM20: {=IFERROR(_xlfn.XLOOKUP($A20&AM$4,MEN_DES&MEN_COD,MEN_GMS),0)*$Q20} -> 0 | AN20: {=IFERROR(_xlfn.XLOOKUP($A20&AN$4,MEN_DES&MEN_COD,MEN_GMS),0)*$Q20} -> 0 | ... BN20: {=IFERROR(_xlfn.XLOOKUP($A20&BN$4,MEN_DES&MEN_COD,MEN_GMS),0)*$Q20} -> 0 | BO20: =SUM(R20:BN20) -> 0
R21: {=IFERROR(_xlfn.XLOOKUP($A21&R$4,MEN_DES&MEN_COD,MEN_GMS),0)*$Q21} -> 0 | S21: {=IFERROR(_xlfn.XLOOKUP($A21&S$4,MEN_DES&MEN_COD,MEN_GMS),0)*$Q21} -> 0 | T21: {=IFERROR(_xlfn.XLOOKUP($A21&T$4,MEN_DES&MEN_COD,MEN_GMS),0)*$Q21} -> 0 | U21: {=IFERROR(_xlfn.XLOOKUP($A21&U$4,MEN_DES&MEN_COD,MEN_GMS),0)*$Q21} -> 0 | V21: {=IFERROR(_xlfn.XLOOKUP($A21&V$4,MEN_DES&MEN_COD,MEN_GMS),0)*$Q21} -> 0 | W21: {=IFERROR(_xlfn.XLOOKUP($A21&W$4,MEN_DES&MEN_COD,MEN_GMS),0)*$Q21} -> 0 | X21: {=IFERROR(_xlfn.XLOOKUP($A21&X$4,MEN_DES&MEN_COD,MEN_GMS),0)*$Q21} -> 0 | Y21: {=IFERROR(_xlfn.XLOOKUP($A21&Y$4,MEN_DES&MEN_COD,MEN_GMS),0)*$Q21} -> 0 | ... AE21: {=IFERROR(_xlfn.XLOOKUP($A21&AE$4,MEN_DES&MEN_COD,MEN_GMS),0)*$Q21} -> 0 | AG21: {=IFERROR(_xlfn.XLOOKUP($A21&AG$4,MEN_DES&MEN_COD,MEN_GMS),0)*$Q21} -> 0 | AH21: {=IFERROR(_xlfn.XLOOKUP($A21&AH$4,MEN_DES&MEN_COD,MEN_GMS),0)*$Q21} -> 0 | AI21: {=IFERROR(_xlfn.XLOOKUP($A21&AI$4,MEN_DES&MEN_COD,MEN_GMS),0)*$Q21} -> 0 | AJ21: {=IFERROR(_xlfn.XLOOKUP($A21&AJ$4,MEN_DES&MEN_COD,MEN_GMS),0)*$Q21} -> 0 | AK21: {=IFERROR(_xlfn.XLOOKUP($A21&AK$4,MEN_DES&MEN_COD,MEN_GMS),0)*$Q21} -> 0 | AL21: {=IFERROR(_xlfn.XLOOKUP($A21&AL$4,MEN_DES&MEN_COD,MEN_GMS),0)*$Q21} -> 0 | AM21: {=IFERROR(_xlfn.XLOOKUP($A21&AM$4,MEN_DES&MEN_COD,MEN_GMS),0)*$Q21} -> 0 | AN21: {=IFERROR(_xlfn.XLOOKUP($A21&AN$4,MEN_DES&MEN_COD,MEN_GMS),0)*$Q21} -> 0 | ... BN21: {=IFERROR(_xlfn.XLOOKUP($A21&BN$4,MEN_DES&MEN_COD,MEN_GMS),0)*$Q21} -> 0 | BO21: =SUM(R21:BN21) -> 0
R22: {=IFERROR(_xlfn.XLOOKUP($A22&R$4,MEN_DES&MEN_COD,MEN_GMS),0)*$Q22} -> 0 | S22: {=IFERROR(_xlfn.XLOOKUP($A22&S$4,MEN_DES&MEN_COD,MEN_GMS),0)*$Q22} -> 0 | T22: {=IFERROR(_xlfn.XLOOKUP($A22&T$4,MEN_DES&MEN_COD,MEN_GMS),0)*$Q22} -> 0 | U22: {=IFERROR(_xlfn.XLOOKUP($A22&U$4,MEN_DES&MEN_COD,MEN_GMS),0)*$Q22} -> 0 | V22: {=IFERROR(_xlfn.XLOOKUP($A22&V$4,MEN_DES&MEN_COD,MEN_GMS),0)*$Q22} -> 0 | W22: {=IFERROR(_xlfn.XLOOKUP($A22&W$4,MEN_DES&MEN_COD,MEN_GMS),0)*$Q22} -> 0 | X22: {=IFERROR(_xlfn.XLOOKUP($A22&X$4,MEN_DES&MEN_COD,MEN_GMS),0)*$Q22} -> 0 | Y22: {=IFERROR(_xlfn.XLOOKUP($A22&Y$4,MEN_DES&MEN_COD,MEN_GMS),0)*$Q22} -> 0 | ... AE22: {=IFERROR(_xlfn.XLOOKUP($A22&AE$4,MEN_DES&MEN_COD,MEN_GMS),0)*$Q22} -> 0 | AG22: {=IFERROR(_xlfn.XLOOKUP($A22&AG$4,MEN_DES&MEN_COD,MEN_GMS),0)*$Q22} -> 0 | AH22: {=IFERROR(_xlfn.XLOOKUP($A22&AH$4,MEN_DES&MEN_COD,MEN_GMS),0)*$Q22} -> 0 | AI22: {=IFERROR(_xlfn.XLOOKUP($A22&AI$4,MEN_DES&MEN_COD,MEN_GMS),0)*$Q22} -> 0 | AJ22: {=IFERROR(_xlfn.XLOOKUP($A22&AJ$4,MEN_DES&MEN_COD,MEN_GMS),0)*$Q22} -> 0 | AK22: {=IFERROR(_xlfn.XLOOKUP($A22&AK$4,MEN_DES&MEN_COD,MEN_GMS),0)*$Q22} -> 0 | AL22: {=IFERROR(_xlfn.XLOOKUP($A22&AL$4,MEN_DES&MEN_COD,MEN_GMS),0)*$Q22} -> 0 | AM22: {=IFERROR(_xlfn.XLOOKUP($A22&AM$4,MEN_DES&MEN_COD,MEN_GMS),0)*$Q22} -> 0 | AN22: {=IFERROR(_xlfn.XLOOKUP($A22&AN$4,MEN_DES&MEN_COD,MEN_GMS),0)*$Q22} -> 0 | ... BN22: {=IFERROR(_xlfn.XLOOKUP($A22&BN$4,MEN_DES&MEN_COD,MEN_GMS),0)*$Q22} -> 0 | BO22: =SUM(R22:BN22) -> 0
R23: {=IFERROR(_xlfn.XLOOKUP($A23&R$4,MEN_DES&MEN_COD,MEN_GMS),0)*$Q23} -> 0 | S23: {=IFERROR(_xlfn.XLOOKUP($A23&S$4,MEN_DES&MEN_COD,MEN_GMS),0)*$Q23} -> 0 | T23: {=IFERROR(_xlfn.XLOOKUP($A23&T$4,MEN_DES&MEN_COD,MEN_GMS),0)*$Q23} -> 0 | U23: {=IFERROR(_xlfn.XLOOKUP($A23&U$4,MEN_DES&MEN_COD,MEN_GMS),0)*$Q23} -> 0 | V23: {=IFERROR(_xlfn.XLOOKUP($A23&V$4,MEN_DES&MEN_COD,MEN_GMS),0)*$Q23} -> 0 | W23: {=IFERROR(_xlfn.XLOOKUP($A23&W$4,MEN_DES&MEN_COD,MEN_GMS),0)*$Q23} -> 0 | X23: {=IFERROR(_xlfn.XLOOKUP($A23&X$4,MEN_DES&MEN_COD,MEN_GMS),0)*$Q23} -> 0 | Y23: {=IFERROR(_xlfn.XLOOKUP($A23&Y$4,MEN_DES&MEN_COD,MEN_GMS),0)*$Q23} -> 0 | ... AE23: {=IFERROR(_xlfn.XLOOKUP($A23&AE$4,MEN_DES&MEN_COD,MEN_GMS),0)*$Q23} -> 0 | AG23: {=IFERROR(_xlfn.XLOOKUP($A23&AG$4,MEN_DES&MEN_COD,MEN_GMS),0)*$Q23} -> 0 | AH23: {=IFERROR(_xlfn.XLOOKUP($A23&AH$4,MEN_DES&MEN_COD,MEN_GMS),0)*$Q23} -> 0 | AI23: {=IFERROR(_xlfn.XLOOKUP($A23&AI$4,MEN_DES&MEN_COD,MEN_GMS),0)*$Q23} -> 0 | AJ23: {=IFERROR(_xlfn.XLOOKUP($A23&AJ$4,MEN_DES&MEN_COD,MEN_GMS),0)*$Q23} -> 0 | AK23: {=IFERROR(_xlfn.XLOOKUP($A23&AK$4,MEN_DES&MEN_COD,MEN_GMS),0)*$Q23} -> 0 | AL23: {=IFERROR(_xlfn.XLOOKUP($A23&AL$4,MEN_DES&MEN_COD,MEN_GMS),0)*$Q23} -> 0 | AM23: {=IFERROR(_xlfn.XLOOKUP($A23&AM$4,MEN_DES&MEN_COD,MEN_GMS),0)*$Q23} -> 0 | AN23: {=IFERROR(_xlfn.XLOOKUP($A23&AN$4,MEN_DES&MEN_COD,MEN_GMS),0)*$Q23} -> 0 | ... BN23: {=IFERROR(_xlfn.XLOOKUP($A23&BN$4,MEN_DES&MEN_COD,MEN_GMS),0)*$Q23} -> 0 | BO23: =SUM(R23:BN23) -> 0
R24: {=IFERROR(_xlfn.XLOOKUP($A24&R$4,MEN_DES&MEN_COD,MEN_GMS),0)*$Q24} -> 0 | S24: {=IFERROR(_xlfn.XLOOKUP($A24&S$4,MEN_DES&MEN_COD,MEN_GMS),0)*$Q24} -> 0 | T24: {=IFERROR(_xlfn.XLOOKUP($A24&T$4,MEN_DES&MEN_COD,MEN_GMS),0)*$Q24} -> 0 | U24: {=IFERROR(_xlfn.XLOOKUP($A24&U$4,MEN_DES&MEN_COD,MEN_GMS),0)*$Q24} -> 0 | V24: {=IFERROR(_xlfn.XLOOKUP($A24&V$4,MEN_DES&MEN_COD,MEN_GMS),0)*$Q24} -> 0 | W24: {=IFERROR(_xlfn.XLOOKUP($A24&W$4,MEN_DES&MEN_COD,MEN_GMS),0)*$Q24} -> 0 | X24: {=IFERROR(_xlfn.XLOOKUP($A24&X$4,MEN_DES&MEN_COD,MEN_GMS),0)*$Q24} -> 0 | Y24: {=IFERROR(_xlfn.XLOOKUP($A24&Y$4,MEN_DES&MEN_COD,MEN_GMS),0)*$Q24} -> 0 | ... AE24: {=IFERROR(_xlfn.XLOOKUP($A24&AE$4,MEN_DES&MEN_COD,MEN_GMS),0)*$Q24} -> 0 | AG24: {=IFERROR(_xlfn.XLOOKUP($A24&AG$4,MEN_DES&MEN_COD,MEN_GMS),0)*$Q24} -> 0 | AH24: {=IFERROR(_xlfn.XLOOKUP($A24&AH$4,MEN_DES&MEN_COD,MEN_GMS),0)*$Q24} -> 0 | AI24: {=IFERROR(_xlfn.XLOOKUP($A24&AI$4,MEN_DES&MEN_COD,MEN_GMS),0)*$Q24} -> 0 | AJ24: {=IFERROR(_xlfn.XLOOKUP($A24&AJ$4,MEN_DES&MEN_COD,MEN_GMS),0)*$Q24} -> 0 | AK24: {=IFERROR(_xlfn.XLOOKUP($A24&AK$4,MEN_DES&MEN_COD,MEN_GMS),0)*$Q24} -> 0 | AL24: {=IFERROR(_xlfn.XLOOKUP($A24&AL$4,MEN_DES&MEN_COD,MEN_GMS),0)*$Q24} -> 0 | AM24: {=IFERROR(_xlfn.XLOOKUP($A24&AM$4,MEN_DES&MEN_COD,MEN_GMS),0)*$Q24} -> 0 | AN24: {=IFERROR(_xlfn.XLOOKUP($A24&AN$4,MEN_DES&MEN_COD,MEN_GMS),0)*$Q24} -> 0 | ... BN24: {=IFERROR(_xlfn.XLOOKUP($A24&BN$4,MEN_DES&MEN_COD,MEN_GMS),0)*$Q24} -> 0 | BO24: =SUM(R24:BN24) -> 0
R25: {=IFERROR(_xlfn.XLOOKUP($A25&R$4,MEN_DES&MEN_COD,MEN_GMS),0)*$Q25} -> 0 | S25: {=IFERROR(_xlfn.XLOOKUP($A25&S$4,MEN_DES&MEN_COD,MEN_GMS),0)*$Q25} -> 0 | T25: {=IFERROR(_xlfn.XLOOKUP($A25&T$4,MEN_DES&MEN_COD,MEN_GMS),0)*$Q25} -> 0 | U25: {=IFERROR(_xlfn.XLOOKUP($A25&U$4,MEN_DES&MEN_COD,MEN_GMS),0)*$Q25} -> 0 | V25: {=IFERROR(_xlfn.XLOOKUP($A25&V$4,MEN_DES&MEN_COD,MEN_GMS),0)*$Q25} -> 0 | W25: {=IFERROR(_xlfn.XLOOKUP($A25&W$4,MEN_DES&MEN_COD,MEN_GMS),0)*$Q25} -> 0 | X25: {=IFERROR(_xlfn.XLOOKUP($A25&X$4,MEN_DES&MEN_COD,MEN_GMS),0)*$Q25} -> 0 | Y25: {=IFERROR(_xlfn.XLOOKUP($A25&Y$4,MEN_DES&MEN_COD,MEN_GMS),0)*$Q25} -> 0 | ... AE25: {=IFERROR(_xlfn.XLOOKUP($A25&AE$4,MEN_DES&MEN_COD,MEN_GMS),0)*$Q25} -> 0 | AG25: {=IFERROR(_xlfn.XLOOKUP($A25&AG$4,MEN_DES&MEN_COD,MEN_GMS),0)*$Q25} -> 0 | AH25: {=IFERROR(_xlfn.XLOOKUP($A25&AH$4,MEN_DES&MEN_COD,MEN_GMS),0)*$Q25} -> 0 | AI25: {=IFERROR(_xlfn.XLOOKUP($A25&AI$4,MEN_DES&MEN_COD,MEN_GMS),0)*$Q25} -> 0 | AJ25: {=IFERROR(_xlfn.XLOOKUP($A25&AJ$4,MEN_DES&MEN_COD,MEN_GMS),0)*$Q25} -> 0 | AK25: {=IFERROR(_xlfn.XLOOKUP($A25&AK$4,MEN_DES&MEN_COD,MEN_GMS),0)*$Q25} -> 0 | AL25: {=IFERROR(_xlfn.XLOOKUP($A25&AL$4,MEN_DES&MEN_COD,MEN_GMS),0)*$Q25} -> 0 | AM25: {=IFERROR(_xlfn.XLOOKUP($A25&AM$4,MEN_DES&MEN_COD,MEN_GMS),0)*$Q25} -> 0 | AN25: {=IFERROR(_xlfn.XLOOKUP($A25&AN$4,MEN_DES&MEN_COD,MEN_GMS),0)*$Q25} -> 0 | ... BN25: {=IFERROR(_xlfn.XLOOKUP($A25&BN$4,MEN_DES&MEN_COD,MEN_GMS),0)*$Q25} -> 0 | BO25: =SUM(R25:BN25) -> 0
R26: {=IFERROR(_xlfn.XLOOKUP($A26&R$4,MEN_DES&MEN_COD,MEN_GMS),0)*$Q26} -> 0 | S26: {=IFERROR(_xlfn.XLOOKUP($A26&S$4,MEN_DES&MEN_COD,MEN_GMS),0)*$Q26} -> 0 | T26: {=IFERROR(_xlfn.XLOOKUP($A26&T$4,MEN_DES&MEN_COD,MEN_GMS),0)*$Q26} -> 0 | U26: {=IFERROR(_xlfn.XLOOKUP($A26&U$4,MEN_DES&MEN_COD,MEN_GMS),0)*$Q26} -> 0 | V26: {=IFERROR(_xlfn.XLOOKUP($A26&V$4,MEN_DES&MEN_COD,MEN_GMS),0)*$Q26} -> 0 | W26: {=IFERROR(_xlfn.XLOOKUP($A26&W$4,MEN_DES&MEN_COD,MEN_GMS),0)*$Q26} -> 0 | X26: {=IFERROR(_xlfn.XLOOKUP($A26&X$4,MEN_DES&MEN_COD,MEN_GMS),0)*$Q26} -> 0 | Y26: {=IFERROR(_xlfn.XLOOKUP($A26&Y$4,MEN_DES&MEN_COD,MEN_GMS),0)*$Q26} -> 0 | ... AE26: {=IFERROR(_xlfn.XLOOKUP($A26&AE$4,MEN_DES&MEN_COD,MEN_GMS),0)*$Q26} -> 0 | AG26: {=IFERROR(_xlfn.XLOOKUP($A26&AG$4,MEN_DES&MEN_COD,MEN_GMS),0)*$Q26} -> 0 | AH26: {=IFERROR(_xlfn.XLOOKUP($A26&AH$4,MEN_DES&MEN_COD,MEN_GMS),0)*$Q26} -> 0 | AI26: {=IFERROR(_xlfn.XLOOKUP($A26&AI$4,MEN_DES&MEN_COD,MEN_GMS),0)*$Q26} -> 0 | AJ26: {=IFERROR(_xlfn.XLOOKUP($A26&AJ$4,MEN_DES&MEN_COD,MEN_GMS),0)*$Q26} -> 0 | AK26: {=IFERROR(_xlfn.XLOOKUP($A26&AK$4,MEN_DES&MEN_COD,MEN_GMS),0)*$Q26} -> 0 | AL26: {=IFERROR(_xlfn.XLOOKUP($A26&AL$4,MEN_DES&MEN_COD,MEN_GMS),0)*$Q26} -> 0 | AM26: {=IFERROR(_xlfn.XLOOKUP($A26&AM$4,MEN_DES&MEN_COD,MEN_GMS),0)*$Q26} -> 0 | AN26: {=IFERROR(_xlfn.XLOOKUP($A26&AN$4,MEN_DES&MEN_COD,MEN_GMS),0)*$Q26} -> 0 | ... BN26: {=IFERROR(_xlfn.XLOOKUP($A26&BN$4,MEN_DES&MEN_COD,MEN_GMS),0)*$Q26} -> 0 | BO26: =SUM(R26:BN26) -> 0
R27: {=IFERROR(_xlfn.XLOOKUP($A27&R$4,MEN_DES&MEN_COD,MEN_GMS),0)*$Q27} -> 0 | S27: {=IFERROR(_xlfn.XLOOKUP($A27&S$4,MEN_DES&MEN_COD,MEN_GMS),0)*$Q27} -> 0 | T27: {=IFERROR(_xlfn.XLOOKUP($A27&T$4,MEN_DES&MEN_COD,MEN_GMS),0)*$Q27} -> 0 | U27: {=IFERROR(_xlfn.XLOOKUP($A27&U$4,MEN_DES&MEN_COD,MEN_GMS),0)*$Q27} -> 0 | V27: {=IFERROR(_xlfn.XLOOKUP($A27&V$4,MEN_DES&MEN_COD,MEN_GMS),0)*$Q27} -> 0 | W27: {=IFERROR(_xlfn.XLOOKUP($A27&W$4,MEN_DES&MEN_COD,MEN_GMS),0)*$Q27} -> 0 | X27: {=IFERROR(_xlfn.XLOOKUP($A27&X$4,MEN_DES&MEN_COD,MEN_GMS),0)*$Q27} -> 0 | Y27: {=IFERROR(_xlfn.XLOOKUP($A27&Y$4,MEN_DES&MEN_COD,MEN_GMS),0)*$Q27} -> 0 | ... AE27: {=IFERROR(_xlfn.XLOOKUP($A27&AE$4,MEN_DES&MEN_COD,MEN_GMS),0)*$Q27} -> 0 | AG27: {=IFERROR(_xlfn.XLOOKUP($A27&AG$4,MEN_DES&MEN_COD,MEN_GMS),0)*$Q27} -> 0 | AH27: {=IFERROR(_xlfn.XLOOKUP($A27&AH$4,MEN_DES&MEN_COD,MEN_GMS),0)*$Q27} -> 0 | AI27: {=IFERROR(_xlfn.XLOOKUP($A27&AI$4,MEN_DES&MEN_COD,MEN_GMS),0)*$Q27} -> 0 | AJ27: {=IFERROR(_xlfn.XLOOKUP($A27&AJ$4,MEN_DES&MEN_COD,MEN_GMS),0)*$Q27} -> 0 | AK27: {=IFERROR(_xlfn.XLOOKUP($A27&AK$4,MEN_DES&MEN_COD,MEN_GMS),0)*$Q27} -> 0 | AL27: {=IFERROR(_xlfn.XLOOKUP($A27&AL$4,MEN_DES&MEN_COD,MEN_GMS),0)*$Q27} -> 0 | AM27: {=IFERROR(_xlfn.XLOOKUP($A27&AM$4,MEN_DES&MEN_COD,MEN_GMS),0)*$Q27} -> 0 | AN27: {=IFERROR(_xlfn.XLOOKUP($A27&AN$4,MEN_DES&MEN_COD,MEN_GMS),0)*$Q27} -> 0 | ... BN27: {=IFERROR(_xlfn.XLOOKUP($A27&BN$4,MEN_DES&MEN_COD,MEN_GMS),0)*$Q27} -> 0 | BO27: =SUM(R27:BN27) -> 0
R28: {=IFERROR(_xlfn.XLOOKUP($A28&R$4,MEN_DES&MEN_COD,MEN_GMS),0)*$Q28} -> 0 | S28: {=IFERROR(_xlfn.XLOOKUP($A28&S$4,MEN_DES&MEN_COD,MEN_GMS),0)*$Q28} -> 0 | T28: {=IFERROR(_xlfn.XLOOKUP($A28&T$4,MEN_DES&MEN_COD,MEN_GMS),0)*$Q28} -> 0 | U28: {=IFERROR(_xlfn.XLOOKUP($A28&U$4,MEN_DES&MEN_COD,MEN_GMS),0)*$Q28} -> 0 | V28: {=IFERROR(_xlfn.XLOOKUP($A28&V$4,MEN_DES&MEN_COD,MEN_GMS),0)*$Q28} -> 0 | W28: {=IFERROR(_xlfn.XLOOKUP($A28&W$4,MEN_DES&MEN_COD,MEN_GMS),0)*$Q28} -> 0 | X28: {=IFERROR(_xlfn.XLOOKUP($A28&X$4,MEN_DES&MEN_COD,MEN_GMS),0)*$Q28} -> 0 | Y28: {=IFERROR(_xlfn.XLOOKUP($A28&Y$4,MEN_DES&MEN_COD,MEN_GMS),0)*$Q28} -> 0 | ... AE28: {=IFERROR(_xlfn.XLOOKUP($A28&AE$4,MEN_DES&MEN_COD,MEN_GMS),0)*$Q28} -> 0 | AG28: {=IFERROR(_xlfn.XLOOKUP($A28&AG$4,MEN_DES&MEN_COD,MEN_GMS),0)*$Q28} -> 0 | AH28: {=IFERROR(_xlfn.XLOOKUP($A28&AH$4,MEN_DES&MEN_COD,MEN_GMS),0)*$Q28} -> 0 | AI28: {=IFERROR(_xlfn.XLOOKUP($A28&AI$4,MEN_DES&MEN_COD,MEN_GMS),0)*$Q28} -> 0 | AJ28: {=IFERROR(_xlfn.XLOOKUP($A28&AJ$4,MEN_DES&MEN_COD,MEN_GMS),0)*$Q28} -> 0 | AK28: {=IFERROR(_xlfn.XLOOKUP($A28&AK$4,MEN_DES&MEN_COD,MEN_GMS),0)*$Q28} -> 0 | AL28: {=IFERROR(_xlfn.XLOOKUP($A28&AL$4,MEN_DES&MEN_COD,MEN_GMS),0)*$Q28} -> 0 | AM28: {=IFERROR(_xlfn.XLOOKUP($A28&AM$4,MEN_DES&MEN_COD,MEN_GMS),0)*$Q28} -> 0 | AN28: {=IFERROR(_xlfn.XLOOKUP($A28&AN$4,MEN_DES&MEN_COD,MEN_GMS),0)*$Q28} -> 0 | ... BN28: {=IFERROR(_xlfn.XLOOKUP($A28&BN$4,MEN_DES&MEN_COD,MEN_GMS),0)*$Q28} -> 0 | BO28: =SUM(R28:BN28) -> 0
R29: {=IFERROR(_xlfn.XLOOKUP($A29&R$4,MEN_DES&MEN_COD,MEN_GMS),0)*$Q29} -> 0 | S29: {=IFERROR(_xlfn.XLOOKUP($A29&S$4,MEN_DES&MEN_COD,MEN_GMS),0)*$Q29} -> 0 | T29: {=IFERROR(_xlfn.XLOOKUP($A29&T$4,MEN_DES&MEN_COD,MEN_GMS),0)*$Q29} -> 0 | U29: {=IFERROR(_xlfn.XLOOKUP($A29&U$4,MEN_DES&MEN_COD,MEN_GMS),0)*$Q29} -> 0 | V29: {=IFERROR(_xlfn.XLOOKUP($A29&V$4,MEN_DES&MEN_COD,MEN_GMS),0)*$Q29} -> 0 | W29: {=IFERROR(_xlfn.XLOOKUP($A29&W$4,MEN_DES&MEN_COD,MEN_GMS),0)*$Q29} -> 0 | X29: {=IFERROR(_xlfn.XLOOKUP($A29&X$4,MEN_DES&MEN_COD,MEN_GMS),0)*$Q29} -> 0 | Y29: {=IFERROR(_xlfn.XLOOKUP($A29&Y$4,MEN_DES&MEN_COD,MEN_GMS),0)*$Q29} -> 0 | ... AE29: {=IFERROR(_xlfn.XLOOKUP($A29&AE$4,MEN_DES&MEN_COD,MEN_GMS),0)*$Q29} -> 0 | AG29: {=IFERROR(_xlfn.XLOOKUP($A29&AG$4,MEN_DES&MEN_COD,MEN_GMS),0)*$Q29} -> 0 | AH29: {=IFERROR(_xlfn.XLOOKUP($A29&AH$4,MEN_DES&MEN_COD,MEN_GMS),0)*$Q29} -> 0 | AI29: {=IFERROR(_xlfn.XLOOKUP($A29&AI$4,MEN_DES&MEN_COD,MEN_GMS),0)*$Q29} -> 0 | AJ29: {=IFERROR(_xlfn.XLOOKUP($A29&AJ$4,MEN_DES&MEN_COD,MEN_GMS),0)*$Q29} -> 0 | AK29: {=IFERROR(_xlfn.XLOOKUP($A29&AK$4,MEN_DES&MEN_COD,MEN_GMS),0)*$Q29} -> 0 | AL29: {=IFERROR(_xlfn.XLOOKUP($A29&AL$4,MEN_DES&MEN_COD,MEN_GMS),0)*$Q29} -> 0 | AM29: {=IFERROR(_xlfn.XLOOKUP($A29&AM$4,MEN_DES&MEN_COD,MEN_GMS),0)*$Q29} -> 0 | AN29: {=IFERROR(_xlfn.XLOOKUP($A29&AN$4,MEN_DES&MEN_COD,MEN_GMS),0)*$Q29} -> 0 | ... BN29: {=IFERROR(_xlfn.XLOOKUP($A29&BN$4,MEN_DES&MEN_COD,MEN_GMS),0)*$Q29} -> 0 | BO29: =SUM(R29:BN29) -> 0
R30: {=IFERROR(_xlfn.XLOOKUP($A30&R$4,MEN_DES&MEN_COD,MEN_GMS),0)*$Q30} -> 0 | S30: {=IFERROR(_xlfn.XLOOKUP($A30&S$4,MEN_DES&MEN_COD,MEN_GMS),0)*$Q30} -> 0 | T30: {=IFERROR(_xlfn.XLOOKUP($A30&T$4,MEN_DES&MEN_COD,MEN_GMS),0)*$Q30} -> 0 | U30: {=IFERROR(_xlfn.XLOOKUP($A30&U$4,MEN_DES&MEN_COD,MEN_GMS),0)*$Q30} -> 0 | V30: {=IFERROR(_xlfn.XLOOKUP($A30&V$4,MEN_DES&MEN_COD,MEN_GMS),0)*$Q30} -> 0 | W30: {=IFERROR(_xlfn.XLOOKUP($A30&W$4,MEN_DES&MEN_COD,MEN_GMS),0)*$Q30} -> 0 | X30: {=IFERROR(_xlfn.XLOOKUP($A30&X$4,MEN_DES&MEN_COD,MEN_GMS),0)*$Q30} -> 0 | Y30: {=IFERROR(_xlfn.XLOOKUP($A30&Y$4,MEN_DES&MEN_COD,MEN_GMS),0)*$Q30} -> 0 | ... AE30: {=IFERROR(_xlfn.XLOOKUP($A30&AE$4,MEN_DES&MEN_COD,MEN_GMS),0)*$Q30} -> 0 | AG30: {=IFERROR(_xlfn.XLOOKUP($A30&AG$4,MEN_DES&MEN_COD,MEN_GMS),0)*$Q30} -> 0 | AH30: {=IFERROR(_xlfn.XLOOKUP($A30&AH$4,MEN_DES&MEN_COD,MEN_GMS),0)*$Q30} -> 0 | AI30: {=IFERROR(_xlfn.XLOOKUP($A30&AI$4,MEN_DES&MEN_COD,MEN_GMS),0)*$Q30} -> 0 | AJ30: {=IFERROR(_xlfn.XLOOKUP($A30&AJ$4,MEN_DES&MEN_COD,MEN_GMS),0)*$Q30} -> 0 | AK30: {=IFERROR(_xlfn.XLOOKUP($A30&AK$4,MEN_DES&MEN_COD,MEN_GMS),0)*$Q30} -> 0 | AL30: {=IFERROR(_xlfn.XLOOKUP($A30&AL$4,MEN_DES&MEN_COD,MEN_GMS),0)*$Q30} -> 0 | AM30: {=IFERROR(_xlfn.XLOOKUP($A30&AM$4,MEN_DES&MEN_COD,MEN_GMS),0)*$Q30} -> 0 | AN30: {=IFERROR(_xlfn.XLOOKUP($A30&AN$4,MEN_DES&MEN_COD,MEN_GMS),0)*$Q30} -> 0 | ... BN30: {=IFERROR(_xlfn.XLOOKUP($A30&BN$4,MEN_DES&MEN_COD,MEN_GMS),0)*$Q30} -> 0 | BO30: =SUM(R30:BN30) -> 0
R31: {=IFERROR(_xlfn.XLOOKUP($A31&R$4,MEN_DES&MEN_COD,MEN_GMS),0)*$Q31} -> 0 | S31: {=IFERROR(_xlfn.XLOOKUP($A31&S$4,MEN_DES&MEN_COD,MEN_GMS),0)*$Q31} -> 0 | T31: {=IFERROR(_xlfn.XLOOKUP($A31&T$4,MEN_DES&MEN_COD,MEN_GMS),0)*$Q31} -> 0 | U31: {=IFERROR(_xlfn.XLOOKUP($A31&U$4,MEN_DES&MEN_COD,MEN_GMS),0)*$Q31} -> 0 | V31: {=IFERROR(_xlfn.XLOOKUP($A31&V$4,MEN_DES&MEN_COD,MEN_GMS),0)*$Q31} -> 0 | W31: {=IFERROR(_xlfn.XLOOKUP($A31&W$4,MEN_DES&MEN_COD,MEN_GMS),0)*$Q31} -> 0 | X31: {=IFERROR(_xlfn.XLOOKUP($A31&X$4,MEN_DES&MEN_COD,MEN_GMS),0)*$Q31} -> 0 | Y31: {=IFERROR(_xlfn.XLOOKUP($A31&Y$4,MEN_DES&MEN_COD,MEN_GMS),0)*$Q31} -> 0 | ... AE31: {=IFERROR(_xlfn.XLOOKUP($A31&AE$4,MEN_DES&MEN_COD,MEN_GMS),0)*$Q31} -> 0 | AG31: {=IFERROR(_xlfn.XLOOKUP($A31&AG$4,MEN_DES&MEN_COD,MEN_GMS),0)*$Q31} -> 0 | AH31: {=IFERROR(_xlfn.XLOOKUP($A31&AH$4,MEN_DES&MEN_COD,MEN_GMS),0)*$Q31} -> 0 | AI31: {=IFERROR(_xlfn.XLOOKUP($A31&AI$4,MEN_DES&MEN_COD,MEN_GMS),0)*$Q31} -> 0 | AJ31: {=IFERROR(_xlfn.XLOOKUP($A31&AJ$4,MEN_DES&MEN_COD,MEN_GMS),0)*$Q31} -> 0 | AK31: {=IFERROR(_xlfn.XLOOKUP($A31&AK$4,MEN_DES&MEN_COD,MEN_GMS),0)*$Q31} -> 0 | AL31: {=IFERROR(_xlfn.XLOOKUP($A31&AL$4,MEN_DES&MEN_COD,MEN_GMS),0)*$Q31} -> 0 | AM31: {=IFERROR(_xlfn.XLOOKUP($A31&AM$4,MEN_DES&MEN_COD,MEN_GMS),0)*$Q31} -> 0 | AN31: {=IFERROR(_xlfn.XLOOKUP($A31&AN$4,MEN_DES&MEN_COD,MEN_GMS),0)*$Q31} -> 0 | ... BN31: {=IFERROR(_xlfn.XLOOKUP($A31&BN$4,MEN_DES&MEN_COD,MEN_GMS),0)*$Q31} -> 0 | BO31: =SUM(R31:BN31) -> 0
R32: {=IFERROR(_xlfn.XLOOKUP($A32&R$4,MEN_DES&MEN_COD,MEN_GMS),0)*$Q32} -> 0 | S32: {=IFERROR(_xlfn.XLOOKUP($A32&S$4,MEN_DES&MEN_COD,MEN_GMS),0)*$Q32} -> 0 | T32: {=IFERROR(_xlfn.XLOOKUP($A32&T$4,MEN_DES&MEN_COD,MEN_GMS),0)*$Q32} -> 0 | U32: {=IFERROR(_xlfn.XLOOKUP($A32&U$4,MEN_DES&MEN_COD,MEN_GMS),0)*$Q32} -> 0 | V32: {=IFERROR(_xlfn.XLOOKUP($A32&V$4,MEN_DES&MEN_COD,MEN_GMS),0)*$Q32} -> 0 | W32: {=IFERROR(_xlfn.XLOOKUP($A32&W$4,MEN_DES&MEN_COD,MEN_GMS),0)*$Q32} -> 0 | X32: {=IFERROR(_xlfn.XLOOKUP($A32&X$4,MEN_DES&MEN_COD,MEN_GMS),0)*$Q32} -> 0 | Y32: {=IFERROR(_xlfn.XLOOKUP($A32&Y$4,MEN_DES&MEN_COD,MEN_GMS),0)*$Q32} -> 0 | ... AE32: {=IFERROR(_xlfn.XLOOKUP($A32&AE$4,MEN_DES&MEN_COD,MEN_GMS),0)*$Q32} -> 0 | AG32: {=IFERROR(_xlfn.XLOOKUP($A32&AG$4,MEN_DES&MEN_COD,MEN_GMS),0)*$Q32} -> 0 | AH32: {=IFERROR(_xlfn.XLOOKUP($A32&AH$4,MEN_DES&MEN_COD,MEN_GMS),0)*$Q32} -> 0 | AI32: {=IFERROR(_xlfn.XLOOKUP($A32&AI$4,MEN_DES&MEN_COD,MEN_GMS),0)*$Q32} -> 0 | AJ32: {=IFERROR(_xlfn.XLOOKUP($A32&AJ$4,MEN_DES&MEN_COD,MEN_GMS),0)*$Q32} -> 0 | AK32: {=IFERROR(_xlfn.XLOOKUP($A32&AK$4,MEN_DES&MEN_COD,MEN_GMS),0)*$Q32} -> 0 | AL32: {=IFERROR(_xlfn.XLOOKUP($A32&AL$4,MEN_DES&MEN_COD,MEN_GMS),0)*$Q32} -> 0 | AM32: {=IFERROR(_xlfn.XLOOKUP($A32&AM$4,MEN_DES&MEN_COD,MEN_GMS),0)*$Q32} -> 0 | AN32: {=IFERROR(_xlfn.XLOOKUP($A32&AN$4,MEN_DES&MEN_COD,MEN_GMS),0)*$Q32} -> 0 | ... BN32: {=IFERROR(_xlfn.XLOOKUP($A32&BN$4,MEN_DES&MEN_COD,MEN_GMS),0)*$Q32} -> 0 | BO32: =SUM(R32:BN32) -> 0
... R223: {=IFERROR(_xlfn.XLOOKUP($A223&R$4,MEN_DES&MEN_COD,MEN_GMS),0)*$Q223} -> 0 | S223: {=IFERROR(_xlfn.XLOOKUP($A223&S$4,MEN_DES&MEN_COD,MEN_GMS),0)*$Q223} -> 0 | T223: {=IFERROR(_xlfn.XLOOKUP($A223&T$4,MEN_DES&MEN_COD,MEN_GMS),0)*$Q223} -> 0 | U223: {=IFERROR(_xlfn.XLOOKUP($A223&U$4,MEN_DES&MEN_COD,MEN_GMS),0)*$Q223} -> 0 | V223: {=IFERROR(_xlfn.XLOOKUP($A223&V$4,MEN_DES&MEN_COD,MEN_GMS),0)*$Q223} -> 0 | W223: {=IFERROR(_xlfn.XLOOKUP($A223&W$4,MEN_DES&MEN_COD,MEN_GMS),0)*$Q223} -> 0 | X223: {=IFERROR(_xlfn.XLOOKUP($A223&X$4,MEN_DES&MEN_COD,MEN_GMS),0)*$Q223} -> 0 | Y223: {=IFERROR(_xlfn.XLOOKUP($A223&Y$4,MEN_DES&MEN_COD,MEN_GMS),0)*$Q223} -> 0 | ... AE223: {=IFERROR(_xlfn.XLOOKUP($A223&AE$4,MEN_DES&MEN_COD,MEN_GMS),0)*$Q223} -> 0 | AG223: {=IFERROR(_xlfn.XLOOKUP($A223&AG$4,MEN_DES&MEN_COD,MEN_GMS),0)*$Q223} -> 0 | AH223: {=IFERROR(_xlfn.XLOOKUP($A223&AH$4,MEN_DES&MEN_COD,MEN_GMS),0)*$Q223} -> 0 | AI223: {=IFERROR(_xlfn.XLOOKUP($A223&AI$4,MEN_DES&MEN_COD,MEN_GMS),0)*$Q223} -> 0 | AJ223: {=IFERROR(_xlfn.XLOOKUP($A223&AJ$4,MEN_DES&MEN_COD,MEN_GMS),0)*$Q223} -> 0 | AK223: {=IFERROR(_xlfn.XLOOKUP($A223&AK$4,MEN_DES&MEN_COD,MEN_GMS),0)*$Q223} -> 0 | AL223: {=IFERROR(_xlfn.XLOOKUP($A223&AL$4,MEN_DES&MEN_COD,MEN_GMS),0)*$Q223} -> 0 | AM223: {=IFERROR(_xlfn.XLOOKUP($A223&AM$4,MEN_DES&MEN_COD,MEN_GMS),0)*$Q223} -> 0 | AN223: {=IFERROR(_xlfn.XLOOKUP($A223&AN$4,MEN_DES&MEN_COD,MEN_GMS),0)*$Q223} -> 0 | ... BN223: {=IFERROR(_xlfn.XLOOKUP($A223&BN$4,MEN_DES&MEN_COD,MEN_GMS),0)*$Q223} -> 0 | BO223: =SUM(R223:BN223) -> 0

Sheet SALES'26
A1: Item name | B1: SKU | C1: Category | D1: Items sold | E1: Gross sales | F1: Items refunded | G1: Refunds | H1: Discounts | I1: Net sales | J1: Cost of goods | K1: Gross profit | L1: Margin | M1: Taxes | N1: DATE
A2: [ATF] Beef Teriyaki Noodles (Regular) | B2: 10457 | C2: ALL TIME FAVORITES | D2: 1 | E2: 285 | F2: 0 | G2: 0 | H2: 0 | I2: 285 | J2: 0 | K2: 285 | L2: 1 | M2: 0 | N2: 45992
A3: [ATF] Ebi Tempura (6pcs) | B3: 10450 | C3: ALL TIME FAVORITES | D3: 1 | E3: 470 | F3: 0 | G3: 0 | H3: 5.74 | I3: 464.26 | J3: 0 | K3: 464.26 | L3: 1 | M3: 0 | N3: 45992
A4: [DB] Beef Terriyaki (Set B) | B4: 10158 | C4: DON BURI (BEEF) | D4: 1 | E4: 385 | F4: 0 | G4: 0 | H4: 0 | I4: 385 | J4: 0 | K4: 385 | L4: 1 | M4: 0 | N4: 45992
A5: [DB] Karaagedon (A) | B5: 10665 | C5: GRAB FOOD | D5: 1 | E5: 299 | F5: 0 | G5: 0 | H5: 0 | I5: 299 | J5: 0 | K5: 299 | L5: 1 | M5: 0 | N5: 45992
A6: [DB] Katsudon (Set A) | B6: 10109 | C6: DON BURI (PORK) | D6: 1 | E6: 275 | F6: 0 | G6: 0 | H6: 0 | I6: 275 | J6: 0 | K6: 275 | L6: 1 | M6: 0 | N6: 45992
A7: [DB] Oyakudon (Set B) | B7: 10051 | C7: DON BURI (CHICKEN) | D7: 1 | E7: 315 | F7: 0 | G7: 0 | H7: 0 | I7: 315 | J7: 0 | K7: 315 | L7: 1 | M7: 0 | N7: 45992
A8: [DB] Torikatsu (Set A) | B8: 10055 | C8: DON BURI (CHICKEN) | D8: 1 | E8: 260 | F8: 0 | G8: 0 | H8: 0 | I8: 260 | J8: 0 | K8: 260 | L8: 1 | M8: 0 | N8: 45992
A9: [DB] Torikatsudon (Set A) | B9: 10062 | C9: DON BURI (CHICKEN) | D9: 2 | E9: 550 | F9: 0 | G9: 0 | H9: 0 | I9: 550 | J9: 0 | K9: 550 | L9: 1 | M9: 0 | N9: 45992
A10: [MR] California Maki | B10: 10264 | C10: MAKI ROLLS | D10: 1 | E10: 190 | F10: 0 | G10: 0 | H10: 0 | I10: 190 | J10: 0 | K10: 190 | L10: 1 | M10: 0 | N10: 45992
A11: [MR] Cheesy Cowboy | B11: 10366 | C11: MAKI ROLLS | D11: 1 | E11: 270 | F11: 0 | G11: 0 | H11: 0 | I11: 270 | J11: 0 | K11: 270 | L11: 1 | M11: 0 | N11: 45992
A12: [MR] Salmon Mango Roll | B12: 10007 | C12: MAKI ROLLS | D12: 1 | E12: 275 | F12: 0 | G12: 0 | H12: 0 | I12: 275 | J12: 0 | K12: 275 | L12: 1 | M12: 0 | N12: 45992
A13: [RM] Shoyu Seafood Ramen | B13: 10353 | C13: RAMEN BOWLS | D13: 1 | E13: 350 | F13: 0 | G13: 0 | H13: 4.28 | I13: 345.72 | J13: 0 | K13: 345.72 | L13: 1 | M13: 0 | N13: 45992
... A55: [SM] Yakisoba w/ Yakitori (Chicekn BBQ) & Cali Maki | B55: 10037 | C55: SNACK MEALS | D55: 1 | E55: 395 | F55: 0 | G55: 0 | H55: 0 | I55: 395 | J55: 0 | K55: 395 | L55: 1 | M55: 0 | N55: 45993
A56: Caramel choco bliss | B56: 00 | C56: Dessert | D56: 1 | E56: 150 | F56: 0 | G56: 0 | H56: 0 | I56: 150 | J56: 0 | K56: 150 | L56: 1 | M56: 0 | N56: 45993
A57: Ramen soup | B57: 000000 | C57: Other | D57: 1 | E57: 45 | F57: 0 | G57: 0 | H57: 0 | I57: 45 | J57: 0 | K57: 45 | L57: 1 | M57: 0 | N57: 45993
A58: Torikatsudon | B58: 10632 | C58: ANNIVERSARY PROMO 2025 | D58: 2 | E58: 318 | F58: 0 | G58: 0 | H58: 0 | I58: 318 | J58: 0 | K58: 318 | L58: 1 | M58: 0 | N58: 45993
A59: 4pcs California Maki | B59: 1066 | C59: Other | D59: 1 | E59: 99 | F59: 0 | G59: 0 | H59: 0 | I59: 99 | J59: 0 | K59: 99 | L59: 1 | M59: 0 | N59: 45994
A60: [ATF] Ebi Tempura (6pcs) | B60: 10450 | C60: ALL TIME FAVORITES | D60: 1 | E60: 470 | F60: 0 | G60: 0 | H60: 0 | I60: 470 | J60: 0 | K60: 470 | L60: 1 | M60: 0 | N60: 45994
A61: [Baked Sushi] Cheesy Beef | B61: 10575 | C61: MANAGEMENT | D61: 1 | E61: 0 | F61: 0 | G61: 0 | H61: 0 | I61: 0 | J61: 0 | K61: 0 | L61: 0 | M61: 0 | N61: 45994
A62: [BS] Cheesy Beef | B62: 10397 | C62: BAKED SUSHI | D62: 1 | E62: 575 | F62: 0 | G62: 0 | H62: 115 | I62: 460 | J62: 0 | K62: 460 | L62: 1 | M62: 0 | N62: 45994
A63: [DB] Beef Curry (Set A) | B63: 10152 | C63: DON BURI (BEEF) | D63: 1 | E63: 350 | F63: 0 | G63: 0 | H63: 0 | I63: 350 | J63: 0 | K63: 350 | L63: 1 | M63: 0 | N63: 45994
A64: [DB] Beef Teppanyaki/Misono (Set A) | B64: 10167 | C64: DON BURI (BEEF) | D64: 1 | E64: 350 | F64: 0 | G64: 0 | H64: 0 | I64: 350 | J64: 0 | K64: 350 | L64: 1 | M64: 0 | N64: 45994
A65: [DB] Crispy Chicken w/ Egg (Set A) | B65: 10225 | C65: DON BURI (CHICKEN) | D65: 1 | E65: 255 | F65: 0 | G65: 0 | H65: 0 | I65: 255 | J65: 0 | K65: 255 | L65: 1 | M65: 0 | N65: 45994
A66: [DB] Gyudon (Set A) | B66: 10645 | C66: DON BURI (BEEF) | D66: 4 | E66: 1360 | F66: 0 | G66: 0 | H66: 0 | I66: 1360 | J66: 0 | K66: 1360 | L66: 1 | M66: 0 | N66: 45994
A67: [DB] Gyudon (Set B) | B67: 10145 | C67: DON BURI (BEEF) | D67: 1 | E67: 370 | F67: 0 | G67: 0 | H67: 0 | I67: 370 | J67: 0 | K67: 370 | L67: 1 | M67: 0 | N67: 45994
A68: [DB] Karaagedon (Set B) | B68: 10052 | C68: DON BURI (CHICKEN) | D68: 1 | E68: 340 | F68: 0 | G68: 0 | H68: 0 | I68: 340 | J68: 0 | K68: 340 | L68: 1 | M68: 0 | N68: 45994
A69: [DB] Katsu Curry (Regular) (Set A) | B69: 10125 | C69: DON BURI (PORK) | D69: 1 | E69: 275 | F69: 0 | G69: 0 | H69: 0 | I69: 275 | J69: 0 | K69: 275 | L69: 1 | M69: 0 | N69: 45994
... A177: [TM] Seafood Fried Rice w/ Ebi Tempura | B177: 10403 | C177: TEMPURA MEALS | D177: 1 | E177: 335 | F177: 0 | G177: 0 | H177: 31.07 | I177: 303.93 | J177: 0 | K177: 303.93 | L177: 1 | M177: 0 | N177: 45996
A178: Caramel choco bliss | B178: 00 | C178: Dessert | D178: 1 | E178: 150 | F178: 0 | G178: 0 | H178: 6 | I178: 144 | J178: 0 | K178: 144 | L178: 1 | M178: 0 | N178: 45996
A179: Classic Dark Choco | B179: 10667 | C179: Dessert | D179: 1 | E179: 150 | F179: 0 | G179: 0 | H179: 6 | I179: 144 | J179: 0 | K179: 144 | L179: 1 | M179: 0 | N179: 45996
A180: Katsudon | B180: 10633 | C180: ANNIVERSARY PROMO 2025 | D180: 4 | E180: 636 | F180: 0 | G180: 0 | H180: 0 | I180: 636 | J180: 0 | K180: 636 | L180: 1 | M180: 0 | N180: 45996
A181: Miso Soup (Small) | B181: 10494 | C181: Other | D181: 2 | E181: 76 | F181: 0 | G181: 0 | H181: 0 | I181: 76 | J181: 0 | K181: 76 | L181: 1 | M181: 0 | N181: 45996
A182: Nori Snack Pack | B182: 10489 | C182: Other | D182: 1 | E182: 45 | F182: 0 | G182: 0 | H182: 4.17 | I182: 40.83 | J182: 0 | K182: 40.83 | L182: 1 | M182: 0 | N182: 45996
A183: Oreo Dream Cake | B183: 10666 | C183: Dessert | D183: 1 | E183: 150 | F183: 0 | G183: 0 | H183: 0 | I183: 150 | J183: 0 | K183: 150 | L183: 1 | M183: 0 | N183: 45996
A184: Red Velvet Royale | B184: 10668 | C184: Dessert | D184: 2 | E184: 300 | F184: 0 | G184: 0 | H184: 0 | I184: 300 | J184: 0 | K184: 300 | L184: 1 | M184: 0 | N184: 45996
A185: TONKATSU set A | B185: 10527 | C185: GRAB FOOD | D185: 1 | E185: 299 | F185: 0 | G185: 0 | H185: 0 | I185: 299 | J185: 0 | K185: 299 | L185: 1 | M185: 0 | N185: 45996
A186: Torikatsudon | B186: 10632 | C186: ANNIVERSARY PROMO 2025 | D186: 1 | E186: 159 | F186: 0 | G186: 0 | H186: 0 | I186: 159 | J186: 0 | K186: 159 | L186: 1 | M186: 0 | N186: 45996
A187: [ATF] Ebi Tempura (12pcs ) | B187: 10451 | C187: ALL TIME FAVORITES | D187: 2 | E187: 1790 | F187: 0 | G187: 0 | H187: 43.49 | I187: 1746.51 | J187: 0 | K187: 1746.51 | L187: 1 | M187: 0 | N187: 45997
A188: [ATF] Yakisoba (Regular) | B188: 10461 | C188: ALL TIME FAVORITES | D188: 1 | E188: 275 | F188: 0 | G188: 0 | H188: 23.86 | I188: 251.14 | J188: 0 | K188: 251.14 | L188: 1 | M188: 0 | N188: 45997
A189: [ATF] Yakisoba (Sharing) | B189: 10462 | C189: ALL TIME FAVORITES | D189: 2 | E189: 820 | F189: 0 | G189: 0 | H189: 71.14 | I189: 748.86 | J189: 0 | K189: 748.86 | L189: 1 | M189: 0 | N189: 45997
A190: [BS] California Baked | B190: 10396 | C190: BAKED SUSHI | D190: 1 | E190: 555 | F190: 0 | G190: 0 | H190: 0 | I190: 555 | J190: 0 | K190: 555 | L190: 1 | M190: 0 | N190: 45997
... A742: Kani Burrito | B742: 10528 | C742: MANAGEMENT | D742: 3 | E742: 0 | F742: 0 | G742: 0 | H742: 0 | I742: 0 | J742: 0 | K742: 0 | L742: 0 | M742: 0 | N742: 46015
A743: Super supreme | B743: 0000000 | C743: MANAGEMENT | D743: 1 | E743: 0 | F743: 0 | G743: 0 | H743: 0 | I743: 0 | J743: 0 | K743: 0 | L743: 0 | M743: 0 | N743: 46015
A744: Torikatsu | B744: 10294 | C744: MANAGEMENT | D744: 2 | E744: 0 | F744: 0 | G744: 0 | H744: 0 | I744: 0 | J744: 0 | K744: 0 | L744: 0 | M744: 0 | N744: 46015
A745: Torikatsudon | B745: 10632 | C745: ANNIVERSARY PROMO 2025 | D745: 3 | E745: 477 | F745: 0 | G745: 0 | H745: 0 | I745: 477 | J745: 0 | K745: 477 | L745: 1 | M745: 0 | N745: 46015
A746: [ATF] Yakisoba (Regular) | B746: 10461 | C746: ALL TIME FAVORITES | D746: 1 | E746: 275 | F746: 0 | G746: 0 | H746: 0 | I746: 275 | J746: 0 | K746: 275 | L746: 1 | M746: 0 | N746: 46017
A747: [BS] California Baked | B747: 10396 | C747: BAKED SUSHI | D747: 1 | E747: 555 | F747: 0 | G747: 0 | H747: 0 | I747: 555 | J747: 0 | K747: 555 | L747: 1 | M747: 0 | N747: 46017
A748: [DB] Beef Teppanyaki/Misono (Set B) | B748: 10168 | C748: DON BURI (BEEF) | D748: 2 | E748: 770 | F748: 0 | G748: 0 | H748: 63.41 | I748: 706.59 | J748: 0 | K748: 706.59 | L748: 1 | M748: 0 | N748: 46017
A749: [DB] Beef Terriyaki (Set B) | B749: 10158 | C749: DON BURI (BEEF) | D749: 1 | E749: 385 | F749: 0 | G749: 0 | H749: 0 | I749: 385 | J749: 0 | K749: 385 | L749: 1 | M749: 0 | N749: 46017
A750: [DB] Crispy Chicken w/ Egg (Set B) | B750: 10072 | C750: DON BURI (CHICKEN) | D750: 1 | E750: 315 | F750: 0 | G750: 0 | H750: 0 | I750: 315 | J750: 0 | K750: 315 | L750: 1 | M750: 0 | N750: 46017
A751: [DB] Gyudon (Set B) | B751: 10145 | C751: DON BURI (BEEF) | D751: 2 | E751: 740 | F751: 0 | G751: 0 | H751: 60.94 | I751: 679.06 | J751: 0 | K751: 679.06 | L751: 1 | M751: 0 | N751: 46017
A752: [DB] Sukiyakidon (Set A) | B752: 10135 | C752: DON BURI (BEEF) | D752: 1 | E752: 310 | F752: 0 | G752: 0 | H752: 0 | I752: 310 | J752: 0 | K752: 310 | L752: 1 | M752: 0 | N752: 46017
A753: [DB] Sukiyakidon (Set B) | B753: 10137 | C753: DON BURI (BEEF) | D753: 1 | E753: 350 | F753: 0 | G753: 0 | H753: 0 | I753: 350 | J753: 0 | K753: 350 | L753: 1 | M753: 0 | N753: 46017
A754: [DS] Green Tea | B754: 10443 | C754: DRINKS & SHAKES | D754: 1 | E754: 75 | F754: 0 | G754: 0 | H754: 0 | I754: 75 | J754: 0 | K754: 75 | L754: 1 | M754: 0 | N754: 46017
A755: [DS] Mango Shake | B755: 10445 | C755: DRINKS & SHAKES | D755: 1 | E755: 195 | F755: 0 | G755: 0 | H755: 0 | I755: 195 | J755: 0 | K755: 195 | L755: 1 | M755: 0 | N755: 46017
... A812: Yakisoba for Sharing | B812: 10559 | C812: MANAGEMENT | D812: 1 | E812: 0 | F812: 0 | G812: 0 | H812: 0 | I812: 0 | J812: 0 | K812: 0 | L812: 0 | M812: 0 | N812: 46019
A813: Yakisoba reg | B813: 0000 | C813: MANAGEMENT | D813: 1 | E813: 0 | F813: 0 | G813: 0 | H813: 0 | I813: 0 | J813: 0 | K813: 0 | L813: 0 | M813: 0 | N813: 46019
A814: [ATF] Beef Teriyaki Noodles (Regular) | B814: 10457 | C814: ALL TIME FAVORITES | D814: 1 | E814: 285 | F814: 0 | G814: 0 | H814: 0 | I814: 285 | J814: 0 | K814: 285 | L814: 1 | M814: 0 | N814: 46020
A815: [ATF] Ebi Tempura (3pcs ) | B815: 10449 | C815: ALL TIME FAVORITES | D815: 1 | E815: 260 | F815: 0 | G815: 0 | H815: 0 | I815: 260 | J815: 0 | K815: 260 | L815: 1 | M815: 0 | N815: 46020
A816: [BS] Creamy Salmon | B816: 10398 | C816: BAKED SUSHI | D816: 2 | E816: 1250 | F816: 0 | G816: 0 | H816: 79.62 | I816: 1170.38 | J816: 0 | K816: 1170.38 | L816: 1 | M816: 0 | N816: 46020
A817: [D] Vanilla Ice Cream | B817: 10039 | C817: DESSERTS | D817: 2 | E817: 150 | F817: 0 | G817: 0 | H817: 19.11 | I817: 130.89 | J817: 0 | K817: 130.89 | L817: 1 | M817: 0 | N817: 46020
A818: [DB] Beef Teppanyaki/Misono (Set A) | B818: 10167 | C818: DON BURI (BEEF) | D818: 1 | E818: 350 | F818: 0 | G818: 0 | H818: 0 | I818: 350 | J818: 0 | K818: 350 | L818: 1 | M818: 0 | N818: 46020
A819: [DB] Chicken Teppanyaki/Misono (Set A) | B819: 10070 | C819: DON BURI (CHICKEN) | D819: 1 | E819: 275 | F819: 0 | G819: 0 | H819: 35.03 | I819: 239.97 | J819: 0 | K819: 239.97 | L819: 1 | M819: 0 | N819: 46020
A820: [DB] Katsu Curry (Regular) (Set A) | B820: 10125 | C820: DON BURI (PORK) | D820: 1 | E820: 275 | F820: 0 | G820: 0 | H820: 0 | I820: 275 | J820: 0 | K820: 275 | L820: 1 | M820: 0 | N820: 46020
A821: [DB] Katsudon (Set A) | B821: 10109 | C821: DON BURI (PORK) | D821: 1 | E821: 275 | F821: 0 | G821: 0 | H821: 0 | I821: 275 | J821: 0 | K821: 275 | L821: 1 | M821: 0 | N821: 46020
A822: [DB] Oyakudon (Set B) | B822: 10051 | C822: DON BURI (CHICKEN) | D822: 1 | E822: 315 | F822: 0 | G822: 0 | H822: 0 | I822: 315 | J822: 0 | K822: 315 | L822: 1 | M822: 0 | N822: 46020
A823: [DB] Torikatsu (Set A) | B823: 10055 | C823: DON BURI (CHICKEN) | D823: 2 | E823: 520 | F823: 0 | G823: 0 | H823: 66.24 | I823: 453.76 | J823: 0 | K823: 453.76 | L823: 1 | M823: 0 | N823: 46020
A824: [DS] Coke/Sprite/Royal/Rootbeer | B824: 10442 | C824: DRINKS & SHAKES | D824: 2 | E824: 166 | F824: 0 | G824: 0 | H824: 0 | I824: 166 | J824: 0 | K824: 166 | L824: 1 | M824: 0 | N824: 46020
A825: [MM] JR w/ Beef Misono & Kani Tempura | B825: 10212 | C825: MIX & MATCH | D825: 1 | E825: 245 | F825: 0 | G825: 0 | H825: 0 | I825: 245 | J825: 0 | K825: 245 | L825: 1 | M825: 0 | N825: 46020
... A2317: Miso Soup (Small) | B2317: 10494 | C2317: Other | D2317: 2 | E2317: 76 | F2317: 0 | G2317: 0 | H2317: 0 | I2317: 76 | J2317: 0 | K2317: 76 | L2317: 1 | M2317: 0 | N2317: 46071
A2318: Mixed sushi and sashimi | B2318: 00000 | C2318: MANAGEMENT | D2318: 1 | E2318: 0 | F2318: 0 | G2318: 0 | H2318: 0 | I2318: 0 | J2318: 0 | K2318: 0 | L2318: 0 | M2318: 0 | N2318: 46071
A2319: Nori Snack Pack | B2319: 10489 | C2319: Other | D2319: 1 | E2319: 45 | F2319: 0 | G2319: 0 | H2319: 0 | I2319: 45 | J2319: 0 | K2319: 45 | L2319: 1 | M2319: 0 | N2319: 46071
A2320: Torikatsudon | B2320: 10495 | C2320: MANAGEMENT | D2320: 1 | E2320: 0 | F2320: 0 | G2320: 0 | H2320: 0 | I2320: 0 | J2320: 0 | K2320: 0 | L2320: 0 | M2320: 0 | N2320: 46071
A2321: Torikatsudon | B2321: 10632 | C2321: ANNIVERSARY PROMO 2025 | D2321: 2 | E2321: 318 | F2321: 0 | G2321: 0 | H2321: 0 | I2321: 318 | J2321: 0 | K2321: 318 | L2321: 1 | M2321: 0 | N2321: 46071
A2322: Yakisoba for Sharing | B2322: 10559 | C2322: MANAGEMENT | D2322: 1 | E2322: 0 | F2322: 0 | G2322: 0 | H2322: 0 | I2322: 0 | J2322: 0 | K2322: 0 | L2322: 0 | M2322: 0 | N2322: 46071
A2323: [BS] Cheesy Beef | B2323: 10397 | C2323: BAKED SUSHI | D2323: 1 | E2323: 575 | F2323: 0 | G2323: 0 | H2323: 0 | I2323: 575 | J2323: 0 | K2323: 575 | L2323: 1 | M2323: 0 | N2323: 46072
A2324: [DB] Karaagedon (Set A) | B2324: 10044 | C2324: DON BURI (CHICKEN) | D2324: 1 | E2324: 260 | F2324: 0 | G2324: 0 | H2324: 0 | I2324: 260 | J2324: 0 | K2324: 260 | L2324: 1 | M2324: 0 | N2324: 46072
A2325: [DB] Katsu Curry (Regular) (Set A) | B2325: 10125 | C2325: DON BURI (PORK) | D2325: 1 | E2325: 275 | F2325: 0 | G2325: 0 | H2325: 0 | I2325: 275 | J2325: 0 | K2325: 275 | L2325: 1 | M2325: 0 | N2325: 46072
A2326: [DS] Coke/Sprite/Royal/Rootbeer | B2326: 10442 | C2326: DRINKS & SHAKES | D2326: 1 | E2326: 83 | F2326: 0 | G2326: 0 | H2326: 0 | I2326: 83 | J2326: 0 | K2326: 83 | L2326: 1 | M2326: 0 | N2326: 46072
A2327: [MM] SF w/ Tonkatsu & Ebi Tempura | B2327: 10221 | C2327: MIX & MATCH | D2327: 1 | E2327: 255 | F2327: 0 | G2327: 0 | H2327: 14.54 | I2327: 240.46 | J2327: 0 | K2327: 240.46 | L2327: 1 | M2327: 0 | N2327: 46072
A2328: [MM] SF w/ Torikatsu & Ebi Tempura | B2328: 10218 | C2328: MIX & MATCH | D2328: 3 | E2328: 735 | F2328: 0 | G2328: 0 | H2328: 21.4 | I2328: 713.6 | J2328: 0 | K2328: 713.6 | L2328: 1 | M2328: 0 | N2328: 46072
A2329: [MM] SF w/ Tuna & Salmon Sashimi & Ebi Tempura | B2329: 10223 | C2329: MIX & MATCH | D2329: 1 | E2329: 275 | F2329: 0 | G2329: 0 | H2329: 0 | I2329: 275 | J2329: 0 | K2329: 275 | L2329: 1 | M2329: 0 | N2329: 46072
A2330: [MM] SF w/ Yakitori & Ebi Tempura | B2330: 10216 | C2330: MIX & MATCH | D2330: 2 | E2330: 490 | F2330: 0 | G2330: 0 | H2330: 0 | I2330: 490 | J2330: 0 | K2330: 490 | L2330: 1 | M2330: 0 | N2330: 46072
... A2593: Torikatsudon 60 grams | B2593: 10522 | C2593: MANAGEMENT | D2593: 5 | E2593: 0 | F2593: 0 | G2593: 0 | H2593: 0 | I2593: 0 | J2593: 0 | K2593: 0 | L2593: 0 | M2593: 0 | N2593: 46080
A2594: Yakisoba reg | B2594: 0000 | C2594: MANAGEMENT | D2594: 1 | E2594: 0 | F2594: 0 | G2594: 0 | H2594: 0 | I2594: 0 | J2594: 0 | K2594: 0 | L2594: 0 | M2594: 0 | N2594: 46080
A2595: 4 in 1 baked | B2595: 10716 | C2595: MANAGEMENT | D2595: 1 | E2595: 0 | F2595: 0 | G2595: 0 | H2595: 0 | I2595: 0 | J2595: 0 | K2595: 0 | L2595: 0 | M2595: 0 | N2595: 46081
A2596: [ MR] Tonkatsu Roll | B2596: 10660 | C2596: MAKI ROLLS | D2596: 1 | E2596: 265 | F2596: 0 | G2596: 0 | H2596: 0 | I2596: 265 | J2596: 0 | K2596: 265 | L2596: 1 | M2596: 0 | N2596: 46081
A2597: [BS] Creamy Salmon | B2597: 10398 | C2597: BAKED SUSHI | D2597: 1 | E2597: 625 | F2597: 0 | G2597: 0 | H2597: 0 | I2597: 625 | J2597: 0 | K2597: 625 | L2597: 1 | M2597: 0 | N2597: 46081
A2598: [DB] Crispy Chicken w/ Egg (Set A) | B2598: 10225 | C2598: DON BURI (CHICKEN) | D2598: 1 | E2598: 255 | F2598: 0 | G2598: 0 | H2598: 0 | I2598: 255 | J2598: 0 | K2598: 255 | L2598: 1 | M2598: 0 | N2598: 46081
A2599: [DB] Gyudon (Set B) | B2599: 10145 | C2599: DON BURI (BEEF) | D2599: 2 | E2599: 740 | F2599: 0 | G2599: 0 | H2599: 0 | I2599: 740 | J2599: 0 | K2599: 740 | L2599: 1 | M2599: 0 | N2599: 46081
A2600: [DB] Katsudon (Set B) | B2600: 10111 | C2600: DON BURI (PORK) | D2600: 4 | E2600: 1420 | F2600: 0 | G2600: 0 | H2600: 0 | I2600: 1420 | J2600: 0 | K2600: 1420 | L2600: 1 | M2600: 0 | N2600: 46081
A2601: [DB] Torikatsudon (Set A) | B2601: 10062 | C2601: DON BURI (CHICKEN) | D2601: 1 | E2601: 275 | F2601: 0 | G2601: 0 | H2601: 0 | I2601: 275 | J2601: 0 | K2601: 275 | L2601: 1 | M2601: 0 | N2601: 46081
A2602: [DS] Coke/Sprite/Royal/Rootbeer | B2602: 10442 | C2602: DRINKS & SHAKES | D2602: 1 | E2602: 83 | F2602: 0 | G2602: 0 | H2602: 0 | I2602: 83 | J2602: 0 | K2602: 83 | L2602: 1 | M2602: 0 | N2602: 46081
A2603: [DS] Iced coffee | B2603: 10488 | C2603: DRINKS & SHAKES | D2603: 1 | E2603: 135 | F2603: 0 | G2603: 0 | H2603: 0 | I2603: 135 | J2603: 0 | K2603: 135 | L2603: 1 | M2603: 0 | N2603: 46081
A2604: [DS] Iced Tea (Regular) | B2604: 10440 | C2604: DRINKS & SHAKES | D2604: 1 | E2604: 88 | F2604: 0 | G2604: 0 | H2604: 0 | I2604: 88 | J2604: 0 | K2604: 88 | L2604: 1 | M2604: 0 | N2604: 46081
A2605: [HS] Mixed Maki Rolls | B2605: 10470 | C2605: HOUSE SPECIALTY | D2605: 2 | E2605: 550 | F2605: 0 | G2605: 0 | H2605: 0 | I2605: 550 | J2605: 0 | K2605: 550 | L2605: 1 | M2605: 0 | N2605: 46081
A2606: [MM] SF w/ Tonkatsu & Ebi Tempura | B2606: 10221 | C2606: MIX & MATCH | D2606: 1 | E2606: 255 | F2606: 0 | G2606: 0 | H2606: 0 | I2606: 255 | J2606: 0 | K2606: 255 | L2606: 1 | M2606: 0 | N2606: 46081
... A2768: Miso Soup (Small) | B2768: 10494 | C2768: Other | D2768: 1 | E2768: 38 | F2768: 0 | G2768: 0 | H2768: 0 | I2768: 38 | J2768: 0 | K2768: 38 | L2768: 1 | M2768: 0 | N2768: 46086
A2769: Yakisoba reg | B2769: 0000 | C2769: MANAGEMENT | D2769: 1 | E2769: 0 | F2769: 0 | G2769: 0 | H2769: 0 | I2769: 0 | J2769: 0 | K2769: 0 | L2769: 0 | M2769: 0 | N2769: 46086
...

Sheet PMTT SUM
A1: DATE | B1: Cash | C1: GCash | D1: GrabFood | E1: Bank Transfer | F1: Maya | G1: GoTyme | H1: TOTAL | I1: SALES | K1: DATE | L1: Cash | M1: GCash | N1: GrabFood | O1: Bank Transfer | P1: Maya | Q1: GoTyme | R1: TOTAL | T1: CHECKING
A4: 46198 | B4: =SUMIFS('PMT TYPE'!$F:$F,'PMT TYPE'!$A:$A,'PMTT SUM'!B$1,'PMT TYPE'!$G:$G,'PMTT SUM'!$A4) -> 0 | C4: =SUMIFS('PMT TYPE'!$F:$F,'PMT TYPE'!$A:$A,'PMTT SUM'!C$1,'PMT TYPE'!$G:$G,'PMTT SUM'!$A4) -> 0 | D4: =SUMIFS('PMT TYPE'!$F:$F,'PMT TYPE'!$A:$A,'PMTT SUM'!D$1,'PMT TYPE'!$G:$G,'PMTT SUM'!$A4) -> 0 | E4: =SUMIFS('PMT TYPE'!$F:$F,'PMT TYPE'!$A:$A,'PMTT SUM'!E$1,'PMT TYPE'!$G:$G,'PMTT SUM'!$A4) -> 0 | F4: =SUMIFS('PMT TYPE'!$F:$F,'PMT TYPE'!$A:$A,'PMTT SUM'!F$1,'PMT TYPE'!$G:$G,'PMTT SUM'!$A4) -> 0 | G4: =SUMIFS('PMT TYPE'!$F:$F,'PMT TYPE'!$A:$A,'PMTT SUM'!G$1,'PMT TYPE'!$G:$G,'PMTT SUM'!$A4) -> 0 | H4: =SUM(B4:G4) -> 0 | I4: =SUMIFS(SUM_NET,SUM_PER,">="&'PMTT SUM'!A4,SUM_PER,"<"&'PMTT SUM'!A5) -> 12559
A5: 46199 | B5: =SUMIFS('PMT TYPE'!$F:$F,'PMT TYPE'!$A:$A,'PMTT SUM'!B$1,'PMT TYPE'!$G:$G,'PMTT SUM'!$A5) -> 0 | C5: =SUMIFS('PMT TYPE'!$F:$F,'PMT TYPE'!$A:$A,'PMTT SUM'!C$1,'PMT TYPE'!$G:$G,'PMTT SUM'!$A5) -> 0 | D5: =SUMIFS('PMT TYPE'!$F:$F,'PMT TYPE'!$A:$A,'PMTT SUM'!D$1,'PMT TYPE'!$G:$G,'PMTT SUM'!$A5) -> 0 | E5: =SUMIFS('PMT TYPE'!$F:$F,'PMT TYPE'!$A:$A,'PMTT SUM'!E$1,'PMT TYPE'!$G:$G,'PMTT SUM'!$A5) -> 0 | F5: =SUMIFS('PMT TYPE'!$F:$F,'PMT TYPE'!$A:$A,'PMTT SUM'!F$1,'PMT TYPE'!$G:$G,'PMTT SUM'!$A5) -> 0 | G5: =SUMIFS('PMT TYPE'!$F:$F,'PMT TYPE'!$A:$A,'PMTT SUM'!G$1,'PMT TYPE'!$G:$G,'PMTT SUM'!$A5) -> 0 | H5: =SUM(B5:G5) -> 0 | I5: =SUMIFS(SUM_NET,SUM_PER,">="&'PMTT SUM'!A5,SUM_PER,"<"&'PMTT SUM'!A6) -> 10143
A6: 46200 | B6: =SUMIFS('PMT TYPE'!$F:$F,'PMT TYPE'!$A:$A,'PMTT SUM'!B$1,'PMT TYPE'!$G:$G,'PMTT SUM'!$A6) -> 0 | C6: =SUMIFS('PMT TYPE'!$F:$F,'PMT TYPE'!$A:$A,'PMTT SUM'!C$1,'PMT TYPE'!$G:$G,'PMTT SUM'!$A6) -> 0 | D6: =SUMIFS('PMT TYPE'!$F:$F,'PMT TYPE'!$A:$A,'PMTT SUM'!D$1,'PMT TYPE'!$G:$G,'PMTT SUM'!$A6) -> 0 | E6: =SUMIFS('PMT TYPE'!$F:$F,'PMT TYPE'!$A:$A,'PMTT SUM'!E$1,'PMT TYPE'!$G:$G,'PMTT SUM'!$A6) -> 0 | F6: =SUMIFS('PMT TYPE'!$F:$F,'PMT TYPE'!$A:$A,'PMTT SUM'!F$1,'PMT TYPE'!$G:$G,'PMTT SUM'!$A6) -> 0 | G6: =SUMIFS('PMT TYPE'!$F:$F,'PMT TYPE'!$A:$A,'PMTT SUM'!G$1,'PMT TYPE'!$G:$G,'PMTT SUM'!$A6) -> 0 | H6: =SUM(B6:G6) -> 0 | I6: =SUMIFS(SUM_NET,SUM_PER,">="&'PMTT SUM'!A6,SUM_PER,"<"&'PMTT SUM'!A7) -> 13752
A7: 46201 | B7: =SUMIFS('PMT TYPE'!$F:$F,'PMT TYPE'!$A:$A,'PMTT SUM'!B$1,'PMT TYPE'!$G:$G,'PMTT SUM'!$A7) -> 0 | C7: =SUMIFS('PMT TYPE'!$F:$F,'PMT TYPE'!$A:$A,'PMTT SUM'!C$1,'PMT TYPE'!$G:$G,'PMTT SUM'!$A7) -> 0 | D7: =SUMIFS('PMT TYPE'!$F:$F,'PMT TYPE'!$A:$A,'PMTT SUM'!D$1,'PMT TYPE'!$G:$G,'PMTT SUM'!$A7) -> 0 | E7: =SUMIFS('PMT TYPE'!$F:$F,'PMT TYPE'!$A:$A,'PMTT SUM'!E$1,'PMT TYPE'!$G:$G,'PMTT SUM'!$A7) -> 0 | F7: =SUMIFS('PMT TYPE'!$F:$F,'PMT TYPE'!$A:$A,'PMTT SUM'!F$1,'PMT TYPE'!$G:$G,'PMTT SUM'!$A7) -> 0 | G7: =SUMIFS('PMT TYPE'!$F:$F,'PMT TYPE'!$A:$A,'PMTT SUM'!G$1,'PMT TYPE'!$G:$G,'PMTT SUM'!$A7) -> 0 | H7: =SUM(B7:G7) -> 0 | I7: =SUMIFS(SUM_NET,SUM_PER,">="&'PMTT SUM'!A7,SUM_PER,"<"&'PMTT SUM'!A8) -> 11157
A8: 46202 | B8: =SUMIFS('PMT TYPE'!$F:$F,'PMT TYPE'!$A:$A,'PMTT SUM'!B$1,'PMT TYPE'!$G:$G,'PMTT SUM'!$A8) -> 0 | C8: =SUMIFS('PMT TYPE'!$F:$F,'PMT TYPE'!$A:$A,'PMTT SUM'!C$1,'PMT TYPE'!$G:$G,'PMTT SUM'!$A8) -> 0 | D8: =SUMIFS('PMT TYPE'!$F:$F,'PMT TYPE'!$A:$A,'PMTT SUM'!D$1,'PMT TYPE'!$G:$G,'PMTT SUM'!$A8) -> 0 | E8: =SUMIFS('PMT TYPE'!$F:$F,'PMT TYPE'!$A:$A,'PMTT SUM'!E$1,'PMT TYPE'!$G:$G,'PMTT SUM'!$A8) -> 0 | F8: =SUMIFS('PMT TYPE'!$F:$F,'PMT TYPE'!$A:$A,'PMTT SUM'!F$1,'PMT TYPE'!$G:$G,'PMTT SUM'!$A8) -> 0 | G8: =SUMIFS('PMT TYPE'!$F:$F,'PMT TYPE'!$A:$A,'PMTT SUM'!G$1,'PMT TYPE'!$G:$G,'PMTT SUM'!$A8) -> 0 | H8: =SUM(B8:G8) -> 0 | I8: =SUMIFS(SUM_NET,SUM_PER,">="&'PMTT SUM'!A8,SUM_PER,"<"&'PMTT SUM'!A9) -> 10386
A9: 46203 | B9: =SUMIFS('PMT TYPE'!$F:$F,'PMT TYPE'!$A:$A,'PMTT SUM'!B$1,'PMT TYPE'!$G:$G,'PMTT SUM'!$A9) -> 0 | C9: =SUMIFS('PMT TYPE'!$F:$F,'PMT TYPE'!$A:$A,'PMTT SUM'!C$1,'PMT TYPE'!$G:$G,'PMTT SUM'!$A9) -> 0 | D9: =SUMIFS('PMT TYPE'!$F:$F,'PMT TYPE'!$A:$A,'PMTT SUM'!D$1,'PMT TYPE'!$G:$G,'PMTT SUM'!$A9) -> 0 | E9: =SUMIFS('PMT TYPE'!$F:$F,'PMT TYPE'!$A:$A,'PMTT SUM'!E$1,'PMT TYPE'!$G:$G,'PMTT SUM'!$A9) -> 0 | F9: =SUMIFS('PMT TYPE'!$F:$F,'PMT TYPE'!$A:$A,'PMTT SUM'!F$1,'PMT TYPE'!$G:$G,'PMTT SUM'!$A9) -> 0 | G9: =SUMIFS('PMT TYPE'!$F:$F,'PMT TYPE'!$A:$A,'PMTT SUM'!G$1,'PMT TYPE'!$G:$G,'PMTT SUM'!$A9) -> 0 | H9: =SUM(B9:G9) -> 0 | I9: =SUMIFS(SUM_NET,SUM_PER,">="&'PMTT SUM'!A9,SUM_PER,"<"&'PMTT SUM'!A10) -> 9556
A10: 46204 | B10: =SUMIFS('PMT TYPE'!$F:$F,'PMT TYPE'!$A:$A,'PMTT SUM'!B$1,'PMT TYPE'!$G:$G,'PMTT SUM'!$A10) -> 3302 | C10: =SUMIFS('PMT TYPE'!$F:$F,'PMT TYPE'!$A:$A,'PMTT SUM'!C$1,'PMT TYPE'!$G:$G,'PMTT SUM'!$A10) -> 4152 | D10: =SUMIFS('PMT TYPE'!$F:$F,'PMT TYPE'!$A:$A,'PMTT SUM'!D$1,'PMT TYPE'!$G:$G,'PMTT SUM'!$A10) -> 629 | E10: =SUMIFS('PMT TYPE'!$F:$F,'PMT TYPE'!$A:$A,'PMTT SUM'!E$1,'PMT TYPE'!$G:$G,'PMTT SUM'!$A10) -> 4692 | F10: =SUMIFS('PMT TYPE'!$F:$F,'PMT TYPE'!$A:$A,'PMTT SUM'!F$1,'PMT TYPE'!$G:$G,'PMTT SUM'!$A10) -> 550 | G10: =SUMIFS('PMT TYPE'!$F:$F,'PMT TYPE'!$A:$A,'PMTT SUM'!G$1,'PMT TYPE'!$G:$G,'PMTT SUM'!$A10) -> 0 | H10: =SUM(B10:G10) -> 13325 | I10: =SUMIFS(SUM_NET,SUM_PER,">="&'PMTT SUM'!A10,SUM_PER,"<"&'PMTT SUM'!A11) -> 13325
A11: 46205 | B11: =SUMIFS('PMT TYPE'!$F:$F,'PMT TYPE'!$A:$A,'PMTT SUM'!B$1,'PMT TYPE'!$G:$G,'PMTT SUM'!$A11) -> 5505 | C11: =SUMIFS('PMT TYPE'!$F:$F,'PMT TYPE'!$A:$A,'PMTT SUM'!C$1,'PMT TYPE'!$G:$G,'PMTT SUM'!$A11) -> 3159 | D11: =SUMIFS('PMT TYPE'!$F:$F,'PMT TYPE'!$A:$A,'PMTT SUM'!D$1,'PMT TYPE'!$G:$G,'PMTT SUM'!$A11) -> 0 | E11: =SUMIFS('PMT TYPE'!$F:$F,'PMT TYPE'!$A:$A,'PMTT SUM'!E$1,'PMT TYPE'!$G:$G,'PMTT SUM'!$A11) -> 726 | F11: =SUMIFS('PMT TYPE'!$F:$F,'PMT TYPE'!$A:$A,'PMTT SUM'!F$1,'PMT TYPE'!$G:$G,'PMTT SUM'!$A11) -> 0 | G11: =SUMIFS('PMT TYPE'!$F:$F,'PMT TYPE'!$A:$A,'PMTT SUM'!G$1,'PMT TYPE'!$G:$G,'PMTT SUM'!$A11) -> 0 | H11: =SUM(B11:G11) -> 9390 | I11: =SUMIFS(SUM_NET,SUM_PER,">="&'PMTT SUM'!A11,SUM_PER,"<"&'PMTT SUM'!A12) -> 9390
A12: 46206 | B12: =SUMIFS('PMT TYPE'!$F:$F,'PMT TYPE'!$A:$A,'PMTT SUM'!B$1,'PMT TYPE'!$G:$G,'PMTT SUM'!$A12) -> 8734 | C12: =SUMIFS('PMT TYPE'!$F:$F,'PMT TYPE'!$A:$A,'PMTT SUM'!C$1,'PMT TYPE'!$G:$G,'PMTT SUM'!$A12) -> 1529 | D12: =SUMIFS('PMT TYPE'!$F:$F,'PMT TYPE'!$A:$A,'PMTT SUM'!D$1,'PMT TYPE'!$G:$G,'PMTT SUM'!$A12) -> 330 | E12: =SUMIFS('PMT TYPE'!$F:$F,'PMT TYPE'!$A:$A,'PMTT SUM'!E$1,'PMT TYPE'!$G:$G,'PMTT SUM'!$A12) -> 2525 | F12: =SUMIFS('PMT TYPE'!$F:$F,'PMT TYPE'!$A:$A,'PMTT SUM'!F$1,'PMT TYPE'!$G:$G,'PMTT SUM'!$A12) -> 0 | G12: =SUMIFS('PMT TYPE'!$F:$F,'PMT TYPE'!$A:$A,'PMTT SUM'!G$1,'PMT TYPE'!$G:$G,'PMTT SUM'!$A12) -> 0 | H12: =SUM(B12:G12) -> 13118 | I12: =SUMIFS(SUM_NET,SUM_PER,">="&'PMTT SUM'!A12,SUM_PER,"<"&'PMTT SUM'!A13) -> 13118
A13: 46207 | B13: =SUMIFS('PMT TYPE'!$F:$F,'PMT TYPE'!$A:$A,'PMTT SUM'!B$1,'PMT TYPE'!$G:$G,'PMTT SUM'!$A13) -> 14956 | C13: =SUMIFS('PMT TYPE'!$F:$F,'PMT TYPE'!$A:$A,'PMTT SUM'!C$1,'PMT TYPE'!$G:$G,'PMTT SUM'!$A13) -> 4472 | D13: =SUMIFS('PMT TYPE'!$F:$F,'PMT TYPE'!$A:$A,'PMTT SUM'!D$1,'PMT TYPE'!$G:$G,'PMTT SUM'!$A13) -> 0 | E13: =SUMIFS('PMT TYPE'!$F:$F,'PMT TYPE'!$A:$A,'PMTT SUM'!E$1,'PMT TYPE'!$G:$G,'PMTT SUM'!$A13) -> 1374 | F13: =SUMIFS('PMT TYPE'!$F:$F,'PMT TYPE'!$A:$A,'PMTT SUM'!F$1,'PMT TYPE'!$G:$G,'PMTT SUM'!$A13) -> 0 | G13: =SUMIFS('PMT TYPE'!$F:$F,'PMT TYPE'!$A:$A,'PMTT SUM'!G$1,'PMT TYPE'!$G:$G,'PMTT SUM'!$A13) -> 1516 | H13: =SUM(B13:G13) -> 22318 | I13: =SUMIFS(SUM_NET,SUM_PER,">="&'PMTT SUM'!A13,SUM_PER,"<"&'PMTT SUM'!A14) -> 22318
A14: 46208 | B14: =SUMIFS('PMT TYPE'!$F:$F,'PMT TYPE'!$A:$A,'PMTT SUM'!B$1,'PMT TYPE'!$G:$G,'PMTT SUM'!$A14) -> 2713 | C14: =SUMIFS('PMT TYPE'!$F:$F,'PMT TYPE'!$A:$A,'PMTT SUM'!C$1,'PMT TYPE'!$G:$G,'PMTT SUM'!$A14) -> 670 | D14: =SUMIFS('PMT TYPE'!$F:$F,'PMT TYPE'!$A:$A,'PMTT SUM'!D$1,'PMT TYPE'!$G:$G,'PMTT SUM'!$A14) -> 0 | E14: =SUMIFS('PMT TYPE'!$F:$F,'PMT TYPE'!$A:$A,'PMTT SUM'!E$1,'PMT TYPE'!$G:$G,'PMTT SUM'!$A14) -> 275 | F14: =SUMIFS('PMT TYPE'!$F:$F,'PMT TYPE'!$A:$A,'PMTT SUM'!F$1,'PMT TYPE'!$G:$G,'PMTT SUM'!$A14) -> 0 | G14: =SUMIFS('PMT TYPE'!$F:$F,'PMT TYPE'!$A:$A,'PMTT SUM'!G$1,'PMT TYPE'!$G:$G,'PMTT SUM'!$A14) -> 0 | H14: =SUM(B14:G14) -> 3658 | I14: =SUMIFS(SUM_NET,SUM_PER,">="&'PMTT SUM'!A14,SUM_PER,"<"&'PMTT SUM'!A15) -> 3658
A15: 46209 | B15: =SUMIFS('PMT TYPE'!$F:$F,'PMT TYPE'!$A:$A,'PMTT SUM'!B$1,'PMT TYPE'!$G:$G,'PMTT SUM'!$A15) -> 1653 | C15: =SUMIFS('PMT TYPE'!$F:$F,'PMT TYPE'!$A:$A,'PMTT SUM'!C$1,'PMT TYPE'!$G:$G,'PMTT SUM'!$A15) -> 1865 | D15: =SUMIFS('PMT TYPE'!$F:$F,'PMT TYPE'!$A:$A,'PMTT SUM'!D$1,'PMT TYPE'!$G:$G,'PMTT SUM'!$A15) -> 580 | E15: =SUMIFS('PMT TYPE'!$F:$F,'PMT TYPE'!$A:$A,'PMTT SUM'!E$1,'PMT TYPE'!$G:$G,'PMTT SUM'!$A15) -> 225 | F15: =SUMIFS('PMT TYPE'!$F:$F,'PMT TYPE'!$A:$A,'PMTT SUM'!F$1,'PMT TYPE'!$G:$G,'PMTT SUM'!$A15) -> 0 | G15: =SUMIFS('PMT TYPE'!$F:$F,'PMT TYPE'!$A:$A,'PMTT SUM'!G$1,'PMT TYPE'!$G:$G,'PMTT SUM'!$A15) -> 510 | H15: =SUM(B15:G15) -> 4833 | I15: =SUMIFS(SUM_NET,SUM_PER,">="&'PMTT SUM'!A15,SUM_PER,"<"&'PMTT SUM'!A16) -> 4568
... A33: 46227 | B33: =SUMIFS('PMT TYPE'!$F:$F,'PMT TYPE'!$A:$A,'PMTT SUM'!B$1,'PMT TYPE'!$G:$G,'PMTT SUM'!$A33) -> 8831 | C33: =SUMIFS('PMT TYPE'!$F:$F,'PMT TYPE'!$A:$A,'PMTT SUM'!C$1,'PMT TYPE'!$G:$G,'PMTT SUM'!$A33) -> 2049 | D33: =SUMIFS('PMT TYPE'!$F:$F,'PMT TYPE'!$A:$A,'PMTT SUM'!D$1,'PMT TYPE'!$G:$G,'PMTT SUM'!$A33) -> 550 | E33: =SUMIFS('PMT TYPE'!$F:$F,'PMT TYPE'!$A:$A,'PMTT SUM'!E$1,'PMT TYPE'!$G:$G,'PMTT SUM'!$A33) -> 0 | F33: =SUMIFS('PMT TYPE'!$F:$F,'PMT TYPE'!$A:$A,'PMTT SUM'!F$1,'PMT TYPE'!$G:$G,'PMTT SUM'!$A33) -> 0 | G33: =SUMIFS('PMT TYPE'!$F:$F,'PMT TYPE'!$A:$A,'PMTT SUM'!G$1,'PMT TYPE'!$G:$G,'PMTT SUM'!$A33) -> 190 | H33: =SUM(B33:G33) -> 11620 | I33: =SUMIFS(SUM_NET,SUM_PER,">="&'PMTT SUM'!A33,SUM_PER,"<"&'PMTT SUM'!A34) -> 11620
A34: 46228 | B34: =SUMIFS('PMT TYPE'!$F:$F,'PMT TYPE'!$A:$A,'PMTT SUM'!B$1,'PMT TYPE'!$G:$G,'PMTT SUM'!$A34) -> 4574 | C34: =SUMIFS('PMT TYPE'!$F:$F,'PMT TYPE'!$A:$A,'PMTT SUM'!C$1,'PMT TYPE'!$G:$G,'PMTT SUM'!$A34) -> 2660 | D34: =SUMIFS('PMT TYPE'!$F:$F,'PMT TYPE'!$A:$A,'PMTT SUM'!D$1,'PMT TYPE'!$G:$G,'PMTT SUM'!$A34) -> 0 | E34: =SUMIFS('PMT TYPE'!$F:$F,'PMT TYPE'!$A:$A,'PMTT SUM'!E$1,'PMT TYPE'!$G:$G,'PMTT SUM'!$A34) -> 924 | F34: =SUMIFS('PMT TYPE'!$F:$F,'PMT TYPE'!$A:$A,'PMTT SUM'!F$1,'PMT TYPE'!$G:$G,'PMTT SUM'!$A34) -> 0 | G34: =SUMIFS('PMT TYPE'!$F:$F,'PMT TYPE'!$A:$A,'PMTT SUM'!G$1,'PMT TYPE'!$G:$G,'PMTT SUM'!$A34) -> 0 | H34: =SUM(B34:G34) -> 8158 | I34: =SUMIFS(SUM_NET,SUM_PER,">="&'PMTT SUM'!A34,SUM_PER,"<"&'PMTT SUM'!A35) -> 8158 | K34: 46023 | L34: =SUMIFS('PMT TYPE'!$F:$F,'PMT TYPE'!$A:$A,'PMTT SUM'!L$1,'PMT TYPE'!$G:$G,">="&'PMTT SUM'!$K34,'PMT TYPE'!$G:$G,"<"&'PMTT SUM'!$K35) -> 0 | M34: =SUMIFS('PMT TYPE'!$F:$F,'PMT TYPE'!$A:$A,'PMTT SUM'!M$1,'PMT TYPE'!$G:$G,">="&'PMTT SUM'!$K34,'PMT TYPE'!$G:$G,"<"&'PMTT SUM'!$K35) -> 0 | N34: =SUMIFS('PMT TYPE'!$F:$F,'PMT TYPE'!$A:$A,'PMTT SUM'!N$1,'PMT TYPE'!$G:$G,">="&'PMTT SUM'!$K34,'PMT TYPE'!$G:$G,"<"&'PMTT SUM'!$K35) -> 0 | O34: =SUMIFS('PMT TYPE'!$F:$F,'PMT TYPE'!$A:$A,'PMTT SUM'!O$1,'PMT TYPE'!$G:$G,">="&'PMTT SUM'!$K34,'PMT TYPE'!$G:$G,"<"&'PMTT SUM'!$K35) -> 0 | P34: =SUMIFS('PMT TYPE'!$F:$F,'PMT TYPE'!$A:$A,'PMTT SUM'!P$1,'PMT TYPE'!$G:$G,">="&'PMTT SUM'!$K34,'PMT TYPE'!$G:$G,"<"&'PMTT SUM'!$K35) -> 0 | Q34: =SUMIFS('PMT TYPE'!$F:$F,'PMT TYPE'!$A:$A,'PMTT SUM'!Q$1,'PMT TYPE'!$G:$G,">="&'PMTT SUM'!$K34,'PMT TYPE'!$G:$G,"<"&'PMTT SUM'!$K35) -> 0 | R34: =SUM(L34:Q34) -> 0 | T34: =SUMIFS(H:H,A:A,">="&K34,A:A,"<"&K35) -> 0 | U34: =T34-R34 -> 0
A35: 46229 | B35: =SUMIFS('PMT TYPE'!$F:$F,'PMT TYPE'!$A:$A,'PMTT SUM'!B$1,'PMT TYPE'!$G:$G,'PMTT SUM'!$A35) -> 10107 | C35: =SUMIFS('PMT TYPE'!$F:$F,'PMT TYPE'!$A:$A,'PMTT SUM'!C$1,'PMT TYPE'!$G:$G,'PMTT SUM'!$A35) -> 500 | D35: =SUMIFS('PMT TYPE'!$F:$F,'PMT TYPE'!$A:$A,'PMTT SUM'!D$1,'PMT TYPE'!$G:$G,'PMTT SUM'!$A35) -> 695 | E35: =SUMIFS('PMT TYPE'!$F:$F,'PMT TYPE'!$A:$A,'PMTT SUM'!E$1,'PMT TYPE'!$G:$G,'PMTT SUM'!$A35) -> 0 | F35: =SUMIFS('PMT TYPE'!$F:$F,'PMT TYPE'!$A:$A,'PMTT SUM'!F$1,'PMT TYPE'!$G:$G,'PMTT SUM'!$A35) -> 0 | G35: =SUMIFS('PMT TYPE'!$F:$F,'PMT TYPE'!$A:$A,'PMTT SUM'!G$1,'PMT TYPE'!$G:$G,'PMTT SUM'!$A35) -> 0 | H35: =SUM(B35:G35) -> 11302 | I35: =SUMIFS(SUM_NET,SUM_PER,">="&'PMTT SUM'!A35,SUM_PER,"<"&'PMTT SUM'!A36) -> 11302 | K35: 46054 | L35: =SUMIFS('PMT TYPE'!$F:$F,'PMT TYPE'!$A:$A,'PMTT SUM'!L$1,'PMT TYPE'!$G:$G,">="&'PMTT SUM'!$K35,'PMT TYPE'!$G:$G,"<"&'PMTT SUM'!$K36) -> 0 | M35: =SUMIFS('PMT TYPE'!$F:$F,'PMT TYPE'!$A:$A,'PMTT SUM'!M$1,'PMT TYPE'!$G:$G,">="&'PMTT SUM'!$K35,'PMT TYPE'!$G:$G,"<"&'PMTT SUM'!$K36) -> 0 | N35: =SUMIFS('PMT TYPE'!$F:$F,'PMT TYPE'!$A:$A,'PMTT SUM'!N$1,'PMT TYPE'!$G:$G,">="&'PMTT SUM'!$K35,'PMT TYPE'!$G:$G,"<"&'PMTT SUM'!$K36) -> 0 | O35: =SUMIFS('PMT TYPE'!$F:$F,'PMT TYPE'!$A:$A,'PMTT SUM'!O$1,'PMT TYPE'!$G:$G,">="&'PMTT SUM'!$K35,'PMT TYPE'!$G:$G,"<"&'PMTT SUM'!$K36) -> 0 | P35: =SUMIFS('PMT TYPE'!$F:$F,'PMT TYPE'!$A:$A,'PMTT SUM'!P$1,'PMT TYPE'!$G:$G,">="&'PMTT SUM'!$K35,'PMT TYPE'!$G:$G,"<"&'PMTT SUM'!$K36) -> 0 | Q35: =SUMIFS('PMT TYPE'!$F:$F,'PMT TYPE'!$A:$A,'PMTT SUM'!Q$1,'PMT TYPE'!$G:$G,">="&'PMTT SUM'!$K35,'PMT TYPE'!$G:$G,"<"&'PMTT SUM'!$K36) -> 0 | R35: =SUM(L35:Q35) -> 0 | T35: =SUMIFS(H:H,A:A,">="&K35,A:A,"<"&K36) -> 0 | U35: =T35-R35 -> 0
A36: 46230 | B36: =SUMIFS('PMT TYPE'!$F:$F,'PMT TYPE'!$A:$A,'PMTT SUM'!B$1,'PMT TYPE'!$G:$G,'PMTT SUM'!$A36) -> 2540 | C36: =SUMIFS('PMT TYPE'!$F:$F,'PMT TYPE'!$A:$A,'PMTT SUM'!C$1,'PMT TYPE'!$G:$G,'PMTT SUM'!$A36) -> 2059 | D36: =SUMIFS('PMT TYPE'!$F:$F,'PMT TYPE'!$A:$A,'PMTT SUM'!D$1,'PMT TYPE'!$G:$G,'PMTT SUM'!$A36) -> 0 | E36: =SUMIFS('PMT TYPE'!$F:$F,'PMT TYPE'!$A:$A,'PMTT SUM'!E$1,'PMT TYPE'!$G:$G,'PMTT SUM'!$A36) -> 793 | F36: =SUMIFS('PMT TYPE'!$F:$F,'PMT TYPE'!$A:$A,'PMTT SUM'!F$1,'PMT TYPE'!$G:$G,'PMTT SUM'!$A36) -> 0 | G36: =SUMIFS('PMT TYPE'!$F:$F,'PMT TYPE'!$A:$A,'PMTT SUM'!G$1,'PMT TYPE'!$G:$G,'PMTT SUM'!$A36) -> 0 | H36: =SUM(B36:G36) -> 5392 | I36: =SUMIFS(SUM_NET,SUM_PER,">="&'PMTT SUM'!A36,SUM_PER,"<"&'PMTT SUM'!A37) -> 5392 | K36: 46082 | L36: =SUMIFS('PMT TYPE'!$F:$F,'PMT TYPE'!$A:$A,'PMTT SUM'!L$1,'PMT TYPE'!$G:$G,">="&'PMTT SUM'!$K36,'PMT TYPE'!$G:$G,"<"&'PMTT SUM'!$K37) -> 0 | M36: =SUMIFS('PMT TYPE'!$F:$F,'PMT TYPE'!$A:$A,'PMTT SUM'!M$1,'PMT TYPE'!$G:$G,">="&'PMTT SUM'!$K36,'PMT TYPE'!$G:$G,"<"&'PMTT SUM'!$K37) -> 0 | N36: =SUMIFS('PMT TYPE'!$F:$F,'PMT TYPE'!$A:$A,'PMTT SUM'!N$1,'PMT TYPE'!$G:$G,">="&'PMTT SUM'!$K36,'PMT TYPE'!$G:$G,"<"&'PMTT SUM'!$K37) -> 0 | O36: =SUMIFS('PMT TYPE'!$F:$F,'PMT TYPE'!$A:$A,'PMTT SUM'!O$1,'PMT TYPE'!$G:$G,">="&'PMTT SUM'!$K36,'PMT TYPE'!$G:$G,"<"&'PMTT SUM'!$K37) -> 0 | P36: =SUMIFS('PMT TYPE'!$F:$F,'PMT TYPE'!$A:$A,'PMTT SUM'!P$1,'PMT TYPE'!$G:$G,">="&'PMTT SUM'!$K36,'PMT TYPE'!$G:$G,"<"&'PMTT SUM'!$K37) -> 0 | Q36: =SUMIFS('PMT TYPE'!$F:$F,'PMT TYPE'!$A:$A,'PMTT SUM'!Q$1,'PMT TYPE'!$G:$G,">="&'PMTT SUM'!$K36,'PMT TYPE'!$G:$G,"<"&'PMTT SUM'!$K37) -> 0 | R36: =SUM(L36:Q36) -> 0 | T36: =SUMIFS(H:H,A:A,">="&K36,A:A,"<"&K37) -> 0 | U36: =T36-R36 -> 0
A37: 46231 | B37: =SUMIFS('PMT TYPE'!$F:$F,'PMT TYPE'!$A:$A,'PMTT SUM'!B$1,'PMT TYPE'!$G:$G,'PMTT SUM'!$A37) -> 3822 | C37: =SUMIFS('PMT TYPE'!$F:$F,'PMT TYPE'!$A:$A,'PMTT SUM'!C$1,'PMT TYPE'!$G:$G,'PMTT SUM'!$A37) -> 3021 | D37: =SUMIFS('PMT TYPE'!$F:$F,'PMT TYPE'!$A:$A,'PMTT SUM'!D$1,'PMT TYPE'!$G:$G,'PMTT SUM'!$A37) -> 0 | E37: =SUMIFS('PMT TYPE'!$F:$F,'PMT TYPE'!$A:$A,'PMTT SUM'!E$1,'PMT TYPE'!$G:$G,'PMTT SUM'!$A37) -> 2130 | F37: =SUMIFS('PMT TYPE'!$F:$F,'PMT TYPE'!$A:$A,'PMTT SUM'!F$1,'PMT TYPE'!$G:$G,'PMTT SUM'!$A37) -> 1394 | G37: =SUMIFS('PMT TYPE'!$F:$F,'PMT TYPE'!$A:$A,'PMTT SUM'!G$1,'PMT TYPE'!$G:$G,'PMTT SUM'!$A37) -> 0 | H37: =SUM(B37:G37) -> 10367 | I37: =SUMIFS(SUM_NET,SUM_PER,">="&'PMTT SUM'!A37,SUM_PER,"<"&'PMTT SUM'!A38) -> 10367 | K37: 46113 | L37: =SUMIFS('PMT TYPE'!$F:$F,'PMT TYPE'!$A:$A,'PMTT SUM'!L$1,'PMT TYPE'!$G:$G,">="&'PMTT SUM'!$K37,'PMT TYPE'!$G:$G,"<"&'PMTT SUM'!$K38) -> 0 | M37: =SUMIFS('PMT TYPE'!$F:$F,'PMT TYPE'!$A:$A,'PMTT SUM'!M$1,'PMT TYPE'!$G:$G,">="&'PMTT SUM'!$K37,'PMT TYPE'!$G:$G,"<"&'PMTT SUM'!$K38) -> 0 | N37: =SUMIFS('PMT TYPE'!$F:$F,'PMT TYPE'!$A:$A,'PMTT SUM'!N$1,'PMT TYPE'!$G:$G,">="&'PMTT SUM'!$K37,'PMT TYPE'!$G:$G,"<"&'PMTT SUM'!$K38) -> 0 | O37: =SUMIFS('PMT TYPE'!$F:$F,'PMT TYPE'!$A:$A,'PMTT SUM'!O$1,'PMT TYPE'!$G:$G,">="&'PMTT SUM'!$K37,'PMT TYPE'!$G:$G,"<"&'PMTT SUM'!$K38) -> 0 | P37: =SUMIFS('PMT TYPE'!$F:$F,'PMT TYPE'!$A:$A,'PMTT SUM'!P$1,'PMT TYPE'!$G:$G,">="&'PMTT SUM'!$K37,'PMT TYPE'!$G:$G,"<"&'PMTT SUM'!$K38) -> 0 | Q37: =SUMIFS('PMT TYPE'!$F:$F,'PMT TYPE'!$A:$A,'PMTT SUM'!Q$1,'PMT TYPE'!$G:$G,">="&'PMTT SUM'!$K37,'PMT TYPE'!$G:$G,"<"&'PMTT SUM'!$K38) -> 0 | R37: =SUM(L37:Q37) -> 0 | T37: =SUMIFS(H:H,A:A,">="&K37,A:A,"<"&K38) -> 0 | U37: =T37-R37 -> 0
A38: 46232 | B38: =SUMIFS('PMT TYPE'!$F:$F,'PMT TYPE'!$A:$A,'PMTT SUM'!B$1,'PMT TYPE'!$G:$G,'PMTT SUM'!$A38) -> 6209 | C38: =SUMIFS('PMT TYPE'!$F:$F,'PMT TYPE'!$A:$A,'PMTT SUM'!C$1,'PMT TYPE'!$G:$G,'PMTT SUM'!$A38) -> 1443 | D38: =SUMIFS('PMT TYPE'!$F:$F,'PMT TYPE'!$A:$A,'PMTT SUM'!D$1,'PMT TYPE'!$G:$G,'PMTT SUM'!$A38) -> 2605 | E38: =SUMIFS('PMT TYPE'!$F:$F,'PMT TYPE'!$A:$A,'PMTT SUM'!E$1,'PMT TYPE'!$G:$G,'PMTT SUM'!$A38) -> 810 | F38: =SUMIFS('PMT TYPE'!$F:$F,'PMT TYPE'!$A:$A,'PMTT SUM'!F$1,'PMT TYPE'!$G:$G,'PMTT SUM'!$A38) -> 0 | G38: =SUMIFS('PMT TYPE'!$F:$F,'PMT TYPE'!$A:$A,'PMTT SUM'!G$1,'PMT TYPE'!$G:$G,'PMTT SUM'!$A38) -> 197 | H38: =SUM(B38:G38) -> 11264 | I38: =SUMIFS(SUM_NET,SUM_PER,">="&'PMTT SUM'!A38,SUM_PER,"<"&'PMTT SUM'!A39) -> 11264 | K38: 46143 | L38: =SUMIFS('PMT TYPE'!$F:$F,'PMT TYPE'!$A:$A,'PMTT SUM'!L$1,'PMT TYPE'!$G:$G,">="&'PMTT SUM'!$K38,'PMT TYPE'!$G:$G,"<"&'PMTT SUM'!$K39) -> 0 | M38: =SUMIFS('PMT TYPE'!$F:$F,'PMT TYPE'!$A:$A,'PMTT SUM'!M$1,'PMT TYPE'!$G:$G,">="&'PMTT SUM'!$K38,'PMT TYPE'!$G:$G,"<"&'PMTT SUM'!$K39) -> 0 | N38: =SUMIFS('PMT TYPE'!$F:$F,'PMT TYPE'!$A:$A,'PMTT SUM'!N$1,'PMT TYPE'!$G:$G,">="&'PMTT SUM'!$K38,'PMT TYPE'!$G:$G,"<"&'PMTT SUM'!$K39) -> 0 | O38: =SUMIFS('PMT TYPE'!$F:$F,'PMT TYPE'!$A:$A,'PMTT SUM'!O$1,'PMT TYPE'!$G:$G,">="&'PMTT SUM'!$K38,'PMT TYPE'!$G:$G,"<"&'PMTT SUM'!$K39) -> 0 | P38: =SUMIFS('PMT TYPE'!$F:$F,'PMT TYPE'!$A:$A,'PMTT SUM'!P$1,'PMT TYPE'!$G:$G,">="&'PMTT SUM'!$K38,'PMT TYPE'!$G:$G,"<"&'PMTT SUM'!$K39) -> 0 | Q38: =SUMIFS('PMT TYPE'!$F:$F,'PMT TYPE'!$A:$A,'PMTT SUM'!Q$1,'PMT TYPE'!$G:$G,">="&'PMTT SUM'!$K38,'PMT TYPE'!$G:$G,"<"&'PMTT SUM'!$K39) -> 0 | R38: =SUM(L38:Q38) -> 0 | T38: =SUMIFS(H:H,A:A,">="&K38,A:A,"<"&K39) -> 0 | U38: =T38-R38 -> 0
A39: 46233 | B39: =SUMIFS('PMT TYPE'!$F:$F,'PMT TYPE'!$A:$A,'PMTT SUM'!B$1,'PMT TYPE'!$G:$G,'PMTT SUM'!$A39) -> 4755 | C39: =SUMIFS('PMT TYPE'!$F:$F,'PMT TYPE'!$A:$A,'PMTT SUM'!C$1,'PMT TYPE'!$G:$G,'PMTT SUM'!$A39) -> 190 | D39: =SUMIFS('PMT TYPE'!$F:$F,'PMT TYPE'!$A:$A,'PMTT SUM'!D$1,'PMT TYPE'!$G:$G,'PMTT SUM'!$A39) -> 0 | E39: =SUMIFS('PMT TYPE'!$F:$F,'PMT TYPE'!$A:$A,'PMTT SUM'!E$1,'PMT TYPE'!$G:$G,'PMTT SUM'!$A39) -> 4706 | F39: =SUMIFS('PMT TYPE'!$F:$F,'PMT TYPE'!$A:$A,'PMTT SUM'!F$1,'PMT TYPE'!$G:$G,'PMTT SUM'!$A39) -> 780 | G39: =SUMIFS('PMT TYPE'!$F:$F,'PMT TYPE'!$A:$A,'PMTT SUM'!G$1,'PMT TYPE'!$G:$G,'PMTT SUM'!$A39) -> 761 | H39: =SUM(B39:G39) -> 11192 | I39: =SUMIFS(SUM_NET,SUM_PER,">="&'PMTT SUM'!A39,SUM_PER,"<"&'PMTT SUM'!A40) -> 11192 | K39: 46174 | L39: =SUMIFS('PMT TYPE'!$F:$F,'PMT TYPE'!$A:$A,'PMTT SUM'!L$1,'PMT TYPE'!$G:$G,">="&'PMTT SUM'!$K39,'PMT TYPE'!$G:$G,"<"&'PMTT SUM'!$K40) -> 0 | M39: =SUMIFS('PMT TYPE'!$F:$F,'PMT TYPE'!$A:$A,'PMTT SUM'!M$1,'PMT TYPE'!$G:$G,">="&'PMTT SUM'!$K39,'PMT TYPE'!$G:$G,"<"&'PMTT SUM'!$K40) -> 0 | N39: =SUMIFS('PMT TYPE'!$F:$F,'PMT TYPE'!$A:$A,'PMTT SUM'!N$1,'PMT TYPE'!$G:$G,">="&'PMTT SUM'!$K39,'PMT TYPE'!$G:$G,"<"&'PMTT SUM'!$K40) -> 0 | O39: =SUMIFS('PMT TYPE'!$F:$F,'PMT TYPE'!$A:$A,'PMTT SUM'!O$1,'PMT TYPE'!$G:$G,">="&'PMTT SUM'!$K39,'PMT TYPE'!$G:$G,"<"&'PMTT SUM'!$K40) -> 0 | P39: =SUMIFS('PMT TYPE'!$F:$F,'PMT TYPE'!$A:$A,'PMTT SUM'!P$1,'PMT TYPE'!$G:$G,">="&'PMTT SUM'!$K39,'PMT TYPE'!$G:$G,"<"&'PMTT SUM'!$K40) -> 0 | Q39: =SUMIFS('PMT TYPE'!$F:$F,'PMT TYPE'!$A:$A,'PMTT SUM'!Q$1,'PMT TYPE'!$G:$G,">="&'PMTT SUM'!$K39,'PMT TYPE'!$G:$G,"<"&'PMTT SUM'!$K40) -> 0 | R39: =SUM(L39:Q39) -> 0 | T39: =SUMIFS(H:H,A:A,">="&K39,A:A,"<"&K40) -> 0 | U39: =T39-R39 -> 0
A40: 46234 | B40: =SUMIFS('PMT TYPE'!$F:$F,'PMT TYPE'!$A:$A,'PMTT SUM'!B$1,'PMT TYPE'!$G:$G,'PMTT SUM'!$A40) -> 5798 | C40: =SUMIFS('PMT TYPE'!$F:$F,'PMT TYPE'!$A:$A,'PMTT SUM'!C$1,'PMT TYPE'!$G:$G,'PMTT SUM'!$A40) -> 1614 | D40: =SUMIFS('PMT TYPE'!$F:$F,'PMT TYPE'!$A:$A,'PMTT SUM'!D$1,'PMT TYPE'!$G:$G,'PMTT SUM'!$A40) -> 0 | E40: =SUMIFS('PMT TYPE'!$F:$F,'PMT TYPE'!$A:$A,'PMTT SUM'!E$1,'PMT TYPE'!$G:$G,'PMTT SUM'!$A40) -> 0 | F40: =SUMIFS('PMT TYPE'!$F:$F,'PMT TYPE'!$A:$A,'PMTT SUM'!F$1,'PMT TYPE'!$G:$G,'PMTT SUM'!$A40) -> 0 | G40: =SUMIFS('PMT TYPE'!$F:$F,'PMT TYPE'!$A:$A,'PMTT SUM'!G$1,'PMT TYPE'!$G:$G,'PMTT SUM'!$A40) -> 791 | H40: =SUM(B40:G40) -> 8203 | I40: =SUMIFS(SUM_NET,SUM_PER,">="&'PMTT SUM'!A40,SUM_PER,"<"&'PMTT SUM'!A41) -> 8203 | K40: 46204 | L40: =SUMIFS('PMT TYPE'!$F:$F,'PMT TYPE'!$A:$A,'PMTT SUM'!L$1,'PMT TYPE'!$G:$G,">="&'PMTT SUM'!$K40,'PMT TYPE'!$G:$G,"<"&'PMTT SUM'!$K41) -> 193539.79 | M40: =SUMIFS('PMT TYPE'!$F:$F,'PMT TYPE'!$A:$A,'PMTT SUM'!M$1,'PMT TYPE'!$G:$G,">="&'PMTT SUM'!$K40,'PMT TYPE'!$G:$G,"<"&'PMTT SUM'!$K41) -> 80329 | N40: =SUMIFS('PMT TYPE'!$F:$F,'PMT TYPE'!$A:$A,'PMTT SUM'!N$1,'PMT TYPE'!$G:$G,">="&'PMTT SUM'!$K40,'PMT TYPE'!$G:$G,"<"&'PMTT SUM'!$K41) -> 11474 | O40: =SUMIFS('PMT TYPE'!$F:$F,'PMT TYPE'!$A:$A,'PMTT SUM'!O$1,'PMT TYPE'!$G:$G,">="&'PMTT SUM'!$K40,'PMT TYPE'!$G:$G,"<"&'PMTT SUM'!$K41) -> 34485.5 | P40: =SUMIFS('PMT TYPE'!$F:$F,'PMT TYPE'!$A:$A,'PMTT SUM'!P$1,'PMT TYPE'!$G:$G,">="&'PMTT SUM'!$K40,'PMT TYPE'!$G:$G,"<"&'PMTT SUM'!$K41) -> 6224 | Q40: =SUMIFS('PMT TYPE'!$F:$F,'PMT TYPE'!$A:$A,'PMTT SUM'!Q$1,'PMT TYPE'!$G:$G,">="&'PMTT SUM'!$K40,'PMT TYPE'!$G:$G,"<"&'PMTT SUM'!$K41) -> 9488 | R40: =SUM(L40:Q40) -> 335540.29 | T40: =SUMIFS(H:H,A:A,">="&K40,A:A,"<"&K41) -> 335540.29 | U40: =T40-R40 -> 0
A41: 46235 | B41: =SUMIFS('PMT TYPE'!$F:$F,'PMT TYPE'!$A:$A,'PMTT SUM'!B$1,'PMT TYPE'!$G:$G,'PMTT SUM'!$A41) -> 14018 | C41: =SUMIFS('PMT TYPE'!$F:$F,'PMT TYPE'!$A:$A,'PMTT SUM'!C$1,'PMT TYPE'!$G:$G,'PMTT SUM'!$A41) -> 0 | D41: =SUMIFS('PMT TYPE'!$F:$F,'PMT TYPE'!$A:$A,'PMTT SUM'!D$1,'PMT TYPE'!$G:$G,'PMTT SUM'!$A41) -> 1005 | E41: =SUMIFS('PMT TYPE'!$F:$F,'PMT TYPE'!$A:$A,'PMTT SUM'!E$1,'PMT TYPE'!$G:$G,'PMTT SUM'!$A41) -> 0 | F41: =SUMIFS('PMT TYPE'!$F:$F,'PMT TYPE'!$A:$A,'PMTT SUM'!F$1,'PMT TYPE'!$G:$G,'PMTT SUM'!$A41) -> 0 | G41: =SUMIFS('PMT TYPE'!$F:$F,'PMT TYPE'!$A:$A,'PMTT SUM'!G$1,'PMT TYPE'!$G:$G,'PMTT SUM'!$A41) -> 0 | H41: =SUM(B41:G41) -> 15023 | I41: =SUMIFS(SUM_NET,SUM_PER,">="&'PMTT SUM'!A41,SUM_PER,"<"&'PMTT SUM'!A42) -> 15023 | K41: 46235 | L41: =SUMIFS('PMT TYPE'!$F:$F,'PMT TYPE'!$A:$A,'PMTT SUM'!L$1,'PMT TYPE'!$G:$G,">="&'PMTT SUM'!$K41,'PMT TYPE'!$G:$G,"<"&'PMTT SUM'!$K42) -> 170511.71 | M41: =SUMIFS('PMT TYPE'!$F:$F,'PMT TYPE'!$A:$A,'PMTT SUM'!M$1,'PMT TYPE'!$G:$G,">="&'PMTT SUM'!$K41,'PMT TYPE'!$G:$G,"<"&'PMTT SUM'!$K42) -> 58084 | N41: =SUMIFS('PMT TYPE'!$F:$F,'PMT TYPE'!$A:$A,'PMTT SUM'!N$1,'PMT TYPE'!$G:$G,">="&'PMTT SUM'!$K41,'PMT TYPE'!$G:$G,"<"&'PMTT SUM'!$K42) -> 7390 | O41: =SUMIFS('PMT TYPE'!$F:$F,'PMT TYPE'!$A:$A,'PMTT SUM'!O$1,'PMT TYPE'!$G:$G,">="&'PMTT SUM'!$K41,'PMT TYPE'!$G:$G,"<"&'PMTT SUM'!$K42) -> 29108 | P41: =SUMIFS('PMT TYPE'!$F:$F,'PMT TYPE'!$A:$A,'PMTT SUM'!P$1,'PMT TYPE'!$G:$G,">="&'PMTT SUM'!$K41,'PMT TYPE'!$G:$G,"<"&'PMTT SUM'!$K42) -> 4776 | Q41: =SUMIFS('PMT TYPE'!$F:$F,'PMT TYPE'!$A:$A,'PMTT SUM'!Q$1,'PMT TYPE'!$G:$G,">="&'PMTT SUM'!$K41,'PMT TYPE'!$G:$G,"<"&'PMTT SUM'!$K42) -> 13516 | R41: =SUM(L41:Q41) -> 283385.71 | T41: =SUMIFS(H:H,A:A,">="&K41,A:A,"<"&K42) -> 283385.71 | U41: =T41-R41 -> 0
A42: 46236 | B42: =SUMIFS('PMT TYPE'!$F:$F,'PMT TYPE'!$A:$A,'PMTT SUM'!B$1,'PMT TYPE'!$G:$G,'PMTT SUM'!$A42) -> 3888 | C42: =SUMIFS('PMT TYPE'!$F:$F,'PMT TYPE'!$A:$A,'PMTT SUM'!C$1,'PMT TYPE'!$G:$G,'PMTT SUM'!$A42) -> 1420 | D42: =SUMIFS('PMT TYPE'!$F:$F,'PMT TYPE'!$A:$A,'PMTT SUM'!D$1,'PMT TYPE'!$G:$G,'PMTT SUM'!$A42) -> 740 | E42: =SUMIFS('PMT TYPE'!$F:$F,'PMT TYPE'!$A:$A,'PMTT SUM'!E$1,'PMT TYPE'!$G:$G,'PMTT SUM'!$A42) -> 3496 | F42: =SUMIFS('PMT TYPE'!$F:$F,'PMT TYPE'!$A:$A,'PMTT SUM'!F$1,'PMT TYPE'!$G:$G,'PMTT SUM'!$A42) -> 0 | G42: =SUMIFS('PMT TYPE'!$F:$F,'PMT TYPE'!$A:$A,'PMTT SUM'!G$1,'PMT TYPE'!$G:$G,'PMTT SUM'!$A42) -> 612 | H42: =SUM(B42:G42) -> 10156 | I42: =SUMIFS(SUM_NET,SUM_PER,">="&'PMTT SUM'!A42,SUM_PER,"<"&'PMTT SUM'!A43) -> 10156 | K42: 46266 | L42: =SUMIFS('PMT TYPE'!$F:$F,'PMT TYPE'!$A:$A,'PMTT SUM'!L$1,'PMT TYPE'!$G:$G,">="&'PMTT SUM'!$K42,'PMT TYPE'!$G:$G,"<"&'PMTT SUM'!$K43) -> 11526 | M42: =SUMIFS('PMT TYPE'!$F:$F,'PMT TYPE'!$A:$A,'PMTT SUM'!M$1,'PMT TYPE'!$G:$G,">="&'PMTT SUM'!$K42,'PMT TYPE'!$G:$G,"<"&'PMTT SUM'!$K43) -> 3997 | N42: =SUMIFS('PMT TYPE'!$F:$F,'PMT TYPE'!$A:$A,'PMTT SUM'!N$1,'PMT TYPE'!$G:$G,">="&'PMTT SUM'!$K42,'PMT TYPE'!$G:$G,"<"&'PMTT SUM'!$K43) -> 0 | O42: =SUMIFS('PMT TYPE'!$F:$F,'PMT TYPE'!$A:$A,'PMTT SUM'!O$1,'PMT TYPE'!$G:$G,">="&'PMTT SUM'!$K42,'PMT TYPE'!$G:$G,"<"&'PMTT SUM'!$K43) -> 3691 | P42: =SUMIFS('PMT TYPE'!$F:$F,'PMT TYPE'!$A:$A,'PMTT SUM'!P$1,'PMT TYPE'!$G:$G,">="&'PMTT SUM'!$K42,'PMT TYPE'!$G:$G,"<"&'PMTT SUM'!$K43) -> 1720 | Q42: =SUMIFS('PMT TYPE'!$F:$F,'PMT TYPE'!$A:$A,'PMTT SUM'!Q$1,'PMT TYPE'!$G:$G,">="&'PMTT SUM'!$K42,'PMT TYPE'!$G:$G,"<"&'PMTT SUM'!$K43) -> 1121 | R42: =SUM(L42:Q42) -> 22055 | T42: =SUMIFS(H:H,A:A,">="&K42,A:A,"<"&K43) -> 22055 | U42: =T42-R42 -> 0
A43: 46237 | B43: =SUMIFS('PMT TYPE'!$F:$F,'PMT TYPE'!$A:$A,'PMTT SUM'!B$1,'PMT TYPE'!$G:$G,'PMTT SUM'!$A43) -> 2680 | C43: =SUMIFS('PMT TYPE'!$F:$F,'PMT TYPE'!$A:$A,'PMTT SUM'!C$1,'PMT TYPE'!$G:$G,'PMTT SUM'!$A43) -> 1895 | D43: =SUMIFS('PMT TYPE'!$F:$F,'PMT TYPE'!$A:$A,'PMTT SUM'!D$1,'PMT TYPE'!$G:$G,'PMTT SUM'!$A43) -> 0 | E43: =SUMIFS('PMT TYPE'!$F:$F,'PMT TYPE'!$A:$A,'PMTT SUM'!E$1,'PMT TYPE'!$G:$G,'PMTT SUM'!$A43) -> 0 | F43: =SUMIFS('PMT TYPE'!$F:$F,'PMT TYPE'!$A:$A,'PMTT SUM'!F$1,'PMT TYPE'!$G:$G,'PMTT SUM'!$A43) -> 0 | G43: =SUMIFS('PMT TYPE'!$F:$F,'PMT TYPE'!$A:$A,'PMTT SUM'!G$1,'PMT TYPE'!$G:$G,'PMTT SUM'!$A43) -> 0 | H43: =SUM(B43:G43) -> 4575 | I43: =SUMIFS(SUM_NET,SUM_PER,">="&'PMTT SUM'!A43,SUM_PER,"<"&'PMTT SUM'!A44) -> 4575 | K43: 46296 | L43: =SUMIFS('PMT TYPE'!$F:$F,'PMT TYPE'!$A:$A,'PMTT SUM'!L$1,'PMT TYPE'!$G:$G,">="&'PMTT SUM'!$K43,'PMT TYPE'!$G:$G,"<"&'PMTT SUM'!$K44) -> 0 | M43: =SUMIFS('PMT TYPE'!$F:$F,'PMT TYPE'!$A:$A,'PMTT SUM'!M$1,'PMT TYPE'!$G:$G,">="&'PMTT SUM'!$K43,'PMT TYPE'!$G:$G,"<"&'PMTT SUM'!$K44) -> 0 | N43: =SUMIFS('PMT TYPE'!$F:$F,'PMT TYPE'!$A:$A,'PMTT SUM'!N$1,'PMT TYPE'!$G:$G,">="&'PMTT SUM'!$K43,'PMT TYPE'!$G:$G,"<"&'PMTT SUM'!$K44) -> 0 | O43: =SUMIFS('PMT TYPE'!$F:$F,'PMT TYPE'!$A:$A,'PMTT SUM'!O$1,'PMT TYPE'!$G:$G,">="&'PMTT SUM'!$K43,'PMT TYPE'!$G:$G,"<"&'PMTT SUM'!$K44) -> 0 | P43: =SUMIFS('PMT TYPE'!$F:$F,'PMT TYPE'!$A:$A,'PMTT SUM'!P$1,'PMT TYPE'!$G:$G,">="&'PMTT SUM'!$K43,'PMT TYPE'!$G:$G,"<"&'PMTT SUM'!$K44) -> 0 | Q43: =SUMIFS('PMT TYPE'!$F:$F,'PMT TYPE'!$A:$A,'PMTT SUM'!Q$1,'PMT TYPE'!$G:$G,">="&'PMTT SUM'!$K43,'PMT TYPE'!$G:$G,"<"&'PMTT SUM'!$K44) -> 0 | R43: =SUM(L43:Q43) -> 0 | T43: =SUMIFS(H:H,A:A,">="&K43,A:A,"<"&K44) -> 0 | U43: =T43-R43 -> 0
A44: 46238 | B44: =SUMIFS('PMT TYPE'!$F:$F,'PMT TYPE'!$A:$A,'PMTT SUM'!B$1,'PMT TYPE'!$G:$G,'PMTT SUM'!$A44) -> 2680 | C44: =SUMIFS('PMT TYPE'!$F:$F,'PMT TYPE'!$A:$A,'PMTT SUM'!C$1,'PMT TYPE'!$G:$G,'PMTT SUM'!$A44) -> 1895 | D44: =SUMIFS('PMT TYPE'!$F:$F,'PMT TYPE'!$A:$A,'PMTT SUM'!D$1,'PMT TYPE'!$G:$G,'PMTT SUM'!$A44) -> 0 | E44: =SUMIFS('PMT TYPE'!$F:$F,'PMT TYPE'!$A:$A,'PMTT SUM'!E$1,'PMT TYPE'!$G:$G,'PMTT SUM'!$A44) -> 0 | F44: =SUMIFS('PMT TYPE'!$F:$F,'PMT TYPE'!$A:$A,'PMTT SUM'!F$1,'PMT TYPE'!$G:$G,'PMTT SUM'!$A44) -> 0 | G44: =SUMIFS('PMT TYPE'!$F:$F,'PMT TYPE'!$A:$A,'PMTT SUM'!G$1,'PMT TYPE'!$G:$G,'PMTT SUM'!$A44) -> 0 | H44: =SUM(B44:G44) -> 4575 | I44: =SUMIFS(SUM_NET,SUM_PER,">="&'PMTT SUM'!A44,SUM_PER,"<"&'PMTT SUM'!A45) -> 8091 | K44: 46327 | L44: =SUMIFS('PMT TYPE'!$F:$F,'PMT TYPE'!$A:$A,'PMTT SUM'!L$1,'PMT TYPE'!$G:$G,">="&'PMTT SUM'!$K44,'PMT TYPE'!$G:$G,"<"&'PMTT SUM'!$K45) -> 0 | M44: =SUMIFS('PMT TYPE'!$F:$F,'PMT TYPE'!$A:$A,'PMTT SUM'!M$1,'PMT TYPE'!$G:$G,">="&'PMTT SUM'!$K44,'PMT TYPE'!$G:$G,"<"&'PMTT SUM'!$K45) -> 0 | N44: =SUMIFS('PMT TYPE'!$F:$F,'PMT TYPE'!$A:$A,'PMTT SUM'!N$1,'PMT TYPE'!$G:$G,">="&'PMTT SUM'!$K44,'PMT TYPE'!$G:$G,"<"&'PMTT SUM'!$K45) -> 0 | O44: =SUMIFS('PMT TYPE'!$F:$F,'PMT TYPE'!$A:$A,'PMTT SUM'!O$1,'PMT TYPE'!$G:$G,">="&'PMTT SUM'!$K44,'PMT TYPE'!$G:$G,"<"&'PMTT SUM'!$K45) -> 0 | P44: =SUMIFS('PMT TYPE'!$F:$F,'PMT TYPE'!$A:$A,'PMTT SUM'!P$1,'PMT TYPE'!$G:$G,">="&'PMTT SUM'!$K44,'PMT TYPE'!$G:$G,"<"&'PMTT SUM'!$K45) -> 0 | Q44: =SUMIFS('PMT TYPE'!$F:$F,'PMT TYPE'!$A:$A,'PMTT SUM'!Q$1,'PMT TYPE'!$G:$G,">="&'PMTT SUM'!$K44,'PMT TYPE'!$G:$G,"<"&'PMTT SUM'!$K45) -> 0 | R44: =SUM(L44:Q44) -> 0 | T44: =SUMIFS(H:H,A:A,">="&K44,A:A,"<"&K45) -> 0 | U44: =T44-R44 -> 0
A45: 46239 | B45: =SUMIFS('PMT TYPE'!$F:$F,'PMT TYPE'!$A:$A,'PMTT SUM'!B$1,'PMT TYPE'!$G:$G,'PMTT SUM'!$A45) -> 12079.71 | C45: =SUMIFS('PMT TYPE'!$F:$F,'PMT TYPE'!$A:$A,'PMTT SUM'!C$1,'PMT TYPE'!$G:$G,'PMTT SUM'!$A45) -> 4348 | D45: =SUMIFS('PMT TYPE'!$F:$F,'PMT TYPE'!$A:$A,'PMTT SUM'!D$1,'PMT TYPE'!$G:$G,'PMTT SUM'!$A45) -> 655 | E45: =SUMIFS('PMT TYPE'!$F:$F,'PMT TYPE'!$A:$A,'PMTT SUM'!E$1,'PMT TYPE'!$G:$G,'PMTT SUM'!$A45) -> 689 | F45: =SUMIFS('PMT TYPE'!$F:$F,'PMT TYPE'!$A:$A,'PMTT SUM'!F$1,'PMT TYPE'!$G:$G,'PMTT SUM'!$A45) -> 0 | G45: =SUMIFS('PMT TYPE'!$F:$F,'PMT TYPE'!$A:$A,'PMTT SUM'!G$1,'PMT TYPE'!$G:$G,'PMTT SUM'!$A45) -> 0 | H45: =SUM(B45:G45) -> 17771.71 | I45: =SUMIFS(SUM_NET,SUM_PER,">="&'PMTT SUM'!A45,SUM_PER,"<"&'PMTT SUM'!A46) -> 17554 | K45: 46357 | L45: =SUMIFS('PMT TYPE'!$F:$F,'PMT TYPE'!$A:$A,'PMTT SUM'!L$1,'PMT TYPE'!$G:$G,">="&'PMTT SUM'!$K45,'PMT TYPE'!$G:$G,"<"&'PMTT SUM'!$K46) -> 0 | M45: =SUMIFS('PMT TYPE'!$F:$F,'PMT TYPE'!$A:$A,'PMTT SUM'!M$1,'PMT TYPE'!$G:$G,">="&'PMTT SUM'!$K45,'PMT TYPE'!$G:$G,"<"&'PMTT SUM'!$K46) -> 0 | N45: =SUMIFS('PMT TYPE'!$F:$F,'PMT TYPE'!$A:$A,'PMTT SUM'!N$1,'PMT TYPE'!$G:$G,">="&'PMTT SUM'!$K45,'PMT TYPE'!$G:$G,"<"&'PMTT SUM'!$K46) -> 0 | O45: =SUMIFS('PMT TYPE'!$F:$F,'PMT TYPE'!$A:$A,'PMTT SUM'!O$1,'PMT TYPE'!$G:$G,">="&'PMTT SUM'!$K45,'PMT TYPE'!$G:$G,"<"&'PMTT SUM'!$K46) -> 0 | P45: =SUMIFS('PMT TYPE'!$F:$F,'PMT TYPE'!$A:$A,'PMTT SUM'!P$1,'PMT TYPE'!$G:$G,">="&'PMTT SUM'!$K45,'PMT TYPE'!$G:$G,"<"&'PMTT SUM'!$K46) -> 0 | Q45: =SUMIFS('PMT TYPE'!$F:$F,'PMT TYPE'!$A:$A,'PMTT SUM'!Q$1,'PMT TYPE'!$G:$G,">="&'PMTT SUM'!$K45,'PMT TYPE'!$G:$G,"<"&'PMTT SUM'!$K46) -> 0 | R45: =SUM(L45:Q45) -> 0 | T45: =SUMIFS(H:H,A:A,">="&K45,A:A,"<"&K46) -> 0 | U45: =T45-R45 -> 0
... A47: 46241 | B47: =SUMIFS('PMT TYPE'!$F:$F,'PMT TYPE'!$A:$A,'PMTT SUM'!B$1,'PMT TYPE'!$G:$G,'PMTT SUM'!$A47) -> 5749 | C47: =SUMIFS('PMT TYPE'!$F:$F,'PMT TYPE'!$A:$A,'PMTT SUM'!C$1,'PMT TYPE'!$G:$G,'PMTT SUM'!$A47) -> 2962 | D47: =SUMIFS('PMT TYPE'!$F:$F,'PMT TYPE'!$A:$A,'PMTT SUM'!D$1,'PMT TYPE'!$G:$G,'PMTT SUM'!$A47) -> 0 | E47: =SUMIFS('PMT TYPE'!$F:$F,'PMT TYPE'!$A:$A,'PMTT SUM'!E$1,'PMT TYPE'!$G:$G,'PMTT SUM'!$A47) -> 1545 | F47: =SUMIFS('PMT TYPE'!$F:$F,'PMT TYPE'!$A:$A,'PMTT SUM'!F$1,'PMT TYPE'!$G:$G,'PMTT SUM'!$A47) -> 350 | G47: =SUMIFS('PMT TYPE'!$F:$F,'PMT TYPE'!$A:$A,'PMTT SUM'!G$1,'PMT TYPE'!$G:$G,'PMTT SUM'!$A47) -> 0 | H47: =SUM(B47:G47) -> 10606 | I47: =SUMIFS(SUM_NET,SUM_PER,">="&'PMTT SUM'!A47,SUM_PER,"<"&'PMTT SUM'!A48) -> 10606 | K47: 46419 | L47: =SUMIFS('PMT TYPE'!$F:$F,'PMT TYPE'!$A:$A,'PMTT SUM'!L$1,'PMT TYPE'!$G:$G,">="&'PMTT SUM'!$K47,'PMT TYPE'!$G:$G,"<"&'PMTT SUM'!$K48) -> 0 | M47: =SUMIFS('PMT TYPE'!$F:$F,'PMT TYPE'!$A:$A,'PMTT SUM'!M$1,'PMT TYPE'!$G:$G,">="&'PMTT SUM'!$K47,'PMT TYPE'!$G:$G,"<"&'PMTT SUM'!$K48) -> 0 | N47: =SUMIFS('PMT TYPE'!$F:$F,'PMT TYPE'!$A:$A,'PMTT SUM'!N$1,'PMT TYPE'!$G:$G,">="&'PMTT SUM'!$K47,'PMT TYPE'!$G:$G,"<"&'PMTT SUM'!$K48) -> 0 | O47: =SUMIFS('PMT TYPE'!$F:$F,'PMT TYPE'!$A:$A,'PMTT SUM'!O$1,'PMT TYPE'!$G:$G,">="&'PMTT SUM'!$K47,'PMT TYPE'!$G:$G,"<"&'PMTT SUM'!$K48) -> 0 | P47: =SUMIFS('PMT TYPE'!$F:$F,'PMT TYPE'!$A:$A,'PMTT SUM'!P$1,'PMT TYPE'!$G:$G,">="&'PMTT SUM'!$K47,'PMT TYPE'!$G:$G,"<"&'PMTT SUM'!$K48) -> 0 | Q47: =SUMIFS('PMT TYPE'!$F:$F,'PMT TYPE'!$A:$A,'PMTT SUM'!Q$1,'PMT TYPE'!$G:$G,">="&'PMTT SUM'!$K47,'PMT TYPE'!$G:$G,"<"&'PMTT SUM'!$K48) -> 0 | R47: =SUM(L47:Q47) -> 0 | T47: =SUMIFS(H:H,A:A,">="&K47,A:A,"<"&K48) -> 0 | U47: =T47-R47 -> 0
A48: 46242 | B48: =SUMIFS('PMT TYPE'!$F:$F,'PMT TYPE'!$A:$A,'PMTT SUM'!B$1,'PMT TYPE'!$G:$G,'PMTT SUM'!$A48) -> 847 | C48: =SUMIFS('PMT TYPE'!$F:$F,'PMT TYPE'!$A:$A,'PMTT SUM'!C$1,'PMT TYPE'!$G:$G,'PMTT SUM'!$A48) -> 0 | D48: =SUMIFS('PMT TYPE'!$F:$F,'PMT TYPE'!$A:$A,'PMTT SUM'!D$1,'PMT TYPE'!$G:$G,'PMTT SUM'!$A48) -> 0 | E48: =SUMIFS('PMT TYPE'!$F:$F,'PMT TYPE'!$A:$A,'PMTT SUM'!E$1,'PMT TYPE'!$G:$G,'PMTT SUM'!$A48) -> 0 | F48: =SUMIFS('PMT TYPE'!$F:$F,'PMT TYPE'!$A:$A,'PMTT SUM'!F$1,'PMT TYPE'!$G:$G,'PMTT SUM'!$A48) -> 0 | G48: =SUMIFS('PMT TYPE'!$F:$F,'PMT TYPE'!$A:$A,'PMTT SUM'!G$1,'PMT TYPE'!$G:$G,'PMTT SUM'!$A48) -> 625 | H48: =SUM(B48:G48) -> 1472 | I48: =SUMIFS(SUM_NET,SUM_PER,">="&'PMTT SUM'!A48,SUM_PER,"<"&'PMTT SUM'!A49) -> 1472 | K48: 46447
A49: 46243 | B49: =SUMIFS('PMT TYPE'!$F:$F,'PMT TYPE'!$A:$A,'PMTT SUM'!B$1,'PMT TYPE'!$G:$G,'PMTT SUM'!$A49) -> 819 | C49: =SUMIFS('PMT TYPE'!$F:$F,'PMT TYPE'!$A:$A,'PMTT SUM'!C$1,'PMT TYPE'!$G:$G,'PMTT SUM'!$A49) -> 1339 | D49: =SUMIFS('PMT TYPE'!$F:$F,'PMT TYPE'!$A:$A,'PMTT SUM'!D$1,'PMT TYPE'!$G:$G,'PMTT SUM'!$A49) -> 0 | E49: =SUMIFS('PMT TYPE'!$F:$F,'PMT TYPE'!$A:$A,'PMTT SUM'!E$1,'PMT TYPE'!$G:$G,'PMTT SUM'!$A49) -> 1100 | F49: =SUMIFS('PMT TYPE'!$F:$F,'PMT TYPE'!$A:$A,'PMTT SUM'!F$1,'PMT TYPE'!$G:$G,'PMTT SUM'!$A49) -> 0 | G49: =SUMIFS('PMT TYPE'!$F:$F,'PMT TYPE'!$A:$A,'PMTT SUM'!G$1,'PMT TYPE'!$G:$G,'PMTT SUM'!$A49) -> 0 | H49: =SUM(B49:G49) -> 3258 | I49: =SUMIFS(SUM_NET,SUM_PER,">="&'PMTT SUM'!A49,SUM_PER,"<"&'PMTT SUM'!A50) -> 3258
A50: 46244 | B50: =SUMIFS('PMT TYPE'!$F:$F,'PMT TYPE'!$A:$A,'PMTT SUM'!B$1,'PMT TYPE'!$G:$G,'PMTT SUM'!$A50) -> 4269 | C50: =SUMIFS('PMT TYPE'!$F:$F,'PMT TYPE'!$A:$A,'PMTT SUM'!C$1,'PMT TYPE'!$G:$G,'PMTT SUM'!$A50) -> 1290 | D50: =SUMIFS('PMT TYPE'!$F:$F,'PMT TYPE'!$A:$A,'PMTT SUM'!D$1,'PMT TYPE'!$G:$G,'PMTT SUM'!$A50) -> 310 | E50: =SUMIFS('PMT TYPE'!$F:$F,'PMT TYPE'!$A:$A,'PMTT SUM'!E$1,'PMT TYPE'!$G:$G,'PMTT SUM'!$A50) -> 0 | F50: =SUMIFS('PMT TYPE'!$F:$F,'PMT TYPE'!$A:$A,'PMTT SUM'!F$1,'PMT TYPE'!$G:$G,'PMTT SUM'!$A50) -> 0 | G50: =SUMIFS('PMT TYPE'!$F:$F,'PMT TYPE'!$A:$A,'PMTT SUM'!G$1,'PMT TYPE'!$G:$G,'PMTT SUM'!$A50) -> 0 | H50: =SUM(B50:G50) -> 5869 | I50: =SUMIFS(SUM_NET,SUM_PER,">="&'PMTT SUM'!A50,SUM_PER,"<"&'PMTT SUM'!A51) -> 5869
A51: 46245 | B51: =SUMIFS('PMT TYPE'!$F:$F,'PMT TYPE'!$A:$A,'PMTT SUM'!B$1,'PMT TYPE'!$G:$G,'PMTT SUM'!$A51) -> 5615 | C51: =SUMIFS('PMT TYPE'!$F:$F,'PMT TYPE'!$A:$A,'PMTT SUM'!C$1,'PMT TYPE'!$G:$G,'PMTT SUM'!$A51) -> 1268 | D51: =SUMIFS('PMT TYPE'!$F:$F,'PMT TYPE'!$A:$A,'PMTT SUM'!D$1,'PMT TYPE'!$G:$G,'PMTT SUM'!$A51) -> 0 | E51: =SUMIFS('PMT TYPE'!$F:$F,'PMT TYPE'!$A:$A,'PMTT SUM'!E$1,'PMT TYPE'!$G:$G,'PMTT SUM'!$A51) -> 0 | F51: =SUMIFS('PMT TYPE'!$F:$F,'PMT TYPE'!$A:$A,'PMTT SUM'!F$1,'PMT TYPE'!$G:$G,'PMTT SUM'!$A51) -> 0 | G51: =SUMIFS('PMT TYPE'!$F:$F,'PMT TYPE'!$A:$A,'PMTT SUM'!G$1,'PMT TYPE'!$G:$G,'PMTT SUM'!$A51) -> 0 | H51: =SUM(B51:G51) -> 6883 | I51: =SUMIFS(SUM_NET,SUM_PER,">="&'PMTT SUM'!A51,SUM_PER,"<"&'PMTT SUM'!A52) -> 6883
A52: 46246 | B52: =SUMIFS('PMT TYPE'!$F:$F,'PMT TYPE'!$A:$A,'PMTT SUM'!B$1,'PMT TYPE'!$G:$G,'PMTT SUM'!$A52) -> 7109 | C52: =SUMIFS('PMT TYPE'!$F:$F,'PMT TYPE'!$A:$A,'PMTT SUM'!C$1,'PMT TYPE'!$G:$G,'PMTT SUM'!$A52) -> 254 | D52: =SUMIFS('PMT TYPE'!$F:$F,'PMT TYPE'!$A:$A,'PMTT SUM'!D$1,'PMT TYPE'!$G:$G,'PMTT SUM'!$A52) -> 740 | E52: =SUMIFS('PMT TYPE'!$F:$F,'PMT TYPE'!$A:$A,'PMTT SUM'!E$1,'PMT TYPE'!$G:$G,'PMTT SUM'!$A52) -> 1425 | F52: =SUMIFS('PMT TYPE'!$F:$F,'PMT TYPE'!$A:$A,'PMTT SUM'!F$1,'PMT TYPE'!$G:$G,'PMTT SUM'!$A52) -> 1528 | G52: =SUMIFS('PMT TYPE'!$F:$F,'PMT TYPE'!$A:$A,'PMTT SUM'!G$1,'PMT TYPE'!$G:$G,'PMTT SUM'!$A52) -> 700 | H52: =SUM(B52:G52) -> 11756 | I52: =SUMIFS(SUM_NET,SUM_PER,">="&'PMTT SUM'!A52,SUM_PER,"<"&'PMTT SUM'!A53) -> 11756
A53: 46247 | B53: =SUMIFS('PMT TYPE'!$F:$F,'PMT TYPE'!$A:$A,'PMTT SUM'!B$1,'PMT TYPE'!$G:$G,'PMTT SUM'!$A53) -> 7647 | C53: =SUMIFS('PMT TYPE'!$F:$F,'PMT TYPE'!$A:$A,'PMTT SUM'!C$1,'PMT TYPE'!$G:$G,'PMTT SUM'!$A53) -> 2223 | D53: =SUMIFS('PMT TYPE'!$F:$F,'PMT TYPE'!$A:$A,'PMTT SUM'!D$1,'PMT TYPE'!$G:$G,'PMTT SUM'!$A53) -> 0 | E53: =SUMIFS('PMT TYPE'!$F:$F,'PMT TYPE'!$A:$A,'PMTT SUM'!E$1,'PMT TYPE'!$G:$G,'PMTT SUM'!$A53) -> 159 | F53: =SUMIFS('PMT TYPE'!$F:$F,'PMT TYPE'!$A:$A,'PMTT SUM'!F$1,'PMT TYPE'!$G:$G,'PMTT SUM'!$A53) -> 350 | G53: =SUMIFS('PMT TYPE'!$F:$F,'PMT TYPE'!$A:$A,'PMTT SUM'!G$1,'PMT TYPE'!$G:$G,'PMTT SUM'!$A53) -> 689 | H53: =SUM(B53:G53) -> 11068 | I53: =SUMIFS(SUM_NET,SUM_PER,">="&'PMTT SUM'!A53,SUM_PER,"<"&'PMTT SUM'!A54) -> 11068
A54: 46248 | B54: =SUMIFS('PMT TYPE'!$F:$F,'PMT TYPE'!$A:$A,'PMTT SUM'!B$1,'PMT TYPE'!$G:$G,'PMTT SUM'!$A54) -> 8034 | C54: =SUMIFS('PMT TYPE'!$F:$F,'PMT TYPE'!$A:$A,'PMTT SUM'!C$1,'PMT TYPE'!$G:$G,'PMTT SUM'!$A54) -> 520 | D54: =SUMIFS('PMT TYPE'!$F:$F,'PMT TYPE'!$A:$A,'PMTT SUM'!D$1,'PMT TYPE'!$G:$G,'PMTT SUM'!$A54) -> 2045 | E54: =SUMIFS('PMT TYPE'!$F:$F,'PMT TYPE'!$A:$A,'PMTT SUM'!E$1,'PMT TYPE'!$G:$G,'PMTT SUM'!$A54) -> 4833 | F54: =SUMIFS('PMT TYPE'!$F:$F,'PMT TYPE'!$A:$A,'PMTT SUM'!F$1,'PMT TYPE'!$G:$G,'PMTT SUM'!$A54) -> 0 | G54: =SUMIFS('PMT TYPE'!$F:$F,'PMT TYPE'!$A:$A,'PMTT SUM'!G$1,'PMT TYPE'!$G:$G,'PMTT SUM'!$A54) -> 1053 | H54: =SUM(B54:G54) -> 16485 | I54: =SUMIFS(SUM_NET,SUM_PER,">="&'PMTT SUM'!A54,SUM_PER,"<"&'PMTT SUM'!A55) -> 16485 | K54: 0.02 | M54: =SUM(M34:M48)*0.02 -> 2848.2 | P54: =SUM(P34:P48)*0.02 -> 254.4 | Q54: =SUM(Q34:Q48)*0.02 -> 482.5
A55: 46249 | B55: =SUMIFS('PMT TYPE'!$F:$F,'PMT TYPE'!$A:$A,'PMTT SUM'!B$1,'PMT TYPE'!$G:$G,'PMTT SUM'!$A55) -> 6178 | C55: =SUMIFS('PMT TYPE'!$F:$F,'PMT TYPE'!$A:$A,'PMTT SUM'!C$1,'PMT TYPE'!$G:$G,'PMTT SUM'!$A55) -> 0 | D55: =SUMIFS('PMT TYPE'!$F:$F,'PMT TYPE'!$A:$A,'PMTT SUM'!D$1,'PMT TYPE'!$G:$G,'PMTT SUM'!$A55) -> 0 | E55: =SUMIFS('PMT TYPE'!$F:$F,'PMT TYPE'!$A:$A,'PMTT SUM'!E$1,'PMT TYPE'!$G:$G,'PMTT SUM'!$A55) -> 0 | F55: =SUMIFS('PMT TYPE'!$F:$F,'PMT TYPE'!$A:$A,'PMTT SUM'!F$1,'PMT TYPE'!$G:$G,'PMTT SUM'!$A55) -> 0 | G55: =SUMIFS('PMT TYPE'!$F:$F,'PMT TYPE'!$A:$A,'PMTT SUM'!G$1,'PMT TYPE'!$G:$G,'PMTT SUM'!$A55) -> 0 | H55: =SUM(B55:G55) -> 6178 | I55: =SUMIFS(SUM_NET,SUM_PER,">="&'PMTT SUM'!A55,SUM_PER,"<"&'PMTT SUM'!A56) -> 6178
A56: 46250 | B56: =SUMIFS('PMT TYPE'!$F:$F,'PMT TYPE'!$A:$A,'PMTT SUM'!B$1,'PMT TYPE'!$G:$G,'PMTT SUM'!$A56) -> 5188 | C56: =SUMIFS('PMT TYPE'!$F:$F,'PMT TYPE'!$A:$A,'PMTT SUM'!C$1,'PMT TYPE'!$G:$G,'PMTT SUM'!$A56) -> 1643 | D56: =SUMIFS('PMT TYPE'!$F:$F,'PMT TYPE'!$A:$A,'PMTT SUM'!D$1,'PMT TYPE'!$G:$G,'PMTT SUM'!$A56) -> 0 | E56: =SUMIFS('PMT TYPE'!$F:$F,'PMT TYPE'!$A:$A,'PMTT SUM'!E$1,'PMT TYPE'!$G:$G,'PMTT SUM'!$A56) -> 190 | F56: =SUMIFS('PMT TYPE'!$F:$F,'PMT TYPE'!$A:$A,'PMTT SUM'!F$1,'PMT TYPE'!$G:$G,'PMTT SUM'!$A56) -> 0 | G56: =SUMIFS('PMT TYPE'!$F:$F,'PMT TYPE'!$A:$A,'PMTT SUM'!G$1,'PMT TYPE'!$G:$G,'PMTT SUM'!$A56) -> 0 | H56: =SUM(B56:G56) -> 7021 | I56: =SUMIFS(SUM_NET,SUM_PER,">="&'PMTT SUM'!A56,SUM_PER,"<"&'PMTT SUM'!A57) -> 7021
A57: 46251 | B57: =SUMIFS('PMT TYPE'!$F:$F,'PMT TYPE'!$A:$A,'PMTT SUM'!B$1,'PMT TYPE'!$G:$G,'PMTT SUM'!$A57) -> 3391 | C57: =SUMIFS('PMT TYPE'!$F:$F,'PMT TYPE'!$A:$A,'PMTT SUM'!C$1,'PMT TYPE'!$G:$G,'PMTT SUM'!$A57) -> 4292 | D57: =SUMIFS('PMT TYPE'!$F:$F,'PMT TYPE'!$A:$A,'PMTT SUM'!D$1,'PMT TYPE'!$G:$G,'PMTT SUM'!$A57) -> 0 | E57: =SUMIFS('PMT TYPE'!$F:$F,'PMT TYPE'!$A:$A,'PMTT SUM'!E$1,'PMT TYPE'!$G:$G,'PMTT SUM'!$A57) -> 2105 | F57: =SUMIFS('PMT TYPE'!$F:$F,'PMT TYPE'!$A:$A,'PMTT SUM'!F$1,'PMT TYPE'!$G:$G,'PMTT SUM'!$A57) -> 369 | G57: =SUMIFS('PMT TYPE'!$F:$F,'PMT TYPE'!$A:$A,'PMTT SUM'!G$1,'PMT TYPE'!$G:$G,'PMTT SUM'!$A57) -> 0 | H57: =SUM(B57:G57) -> 10157 | I57: =SUMIFS(SUM_NET,SUM_PER,">="&'PMTT SUM'!A57,SUM_PER,"<"&'PMTT SUM'!A58) -> 10157
A58: 46252 | B58: =SUMIFS('PMT TYPE'!$F:$F,'PMT TYPE'!$A:$A,'PMTT SUM'!B$1,'PMT TYPE'!$G:$G,'PMTT SUM'!$A58) -> 5265 | C58: =SUMIFS('PMT TYPE'!$F:$F,'PMT TYPE'!$A:$A,'PMTT SUM'!C$1,'PMT TYPE'!$G:$G,'PMTT SUM'!$A58) -> 2312 | D58: =SUMIFS('PMT TYPE'!$F:$F,'PMT TYPE'!$A:$A,'PMTT SUM'!D$1,'PMT TYPE'!$G:$G,'PMTT SUM'!$A58) -> 0 | E58: =SUMIFS('PMT TYPE'!$F:$F,'PMT TYPE'!$A:$A,'PMTT SUM'!E$1,'PMT TYPE'!$G:$G,'PMTT SUM'!$A58) -> 0 | F58: =SUMIFS('PMT TYPE'!$F:$F,'PMT TYPE'!$A:$A,'PMTT SUM'!F$1,'PMT TYPE'!$G:$G,'PMTT SUM'!$A58) -> 0 | G58: =SUMIFS('PMT TYPE'!$F:$F,'PMT TYPE'!$A:$A,'PMTT SUM'!G$1,'PMT TYPE'!$G:$G,'PMTT SUM'!$A58) -> 545 | H58: =SUM(B58:G58) -> 8122 | I58: =SUMIFS(SUM_NET,SUM_PER,">="&'PMTT SUM'!A58,SUM_PER,"<"&'PMTT SUM'!A59) -> 8122
A59: 46253 | B59: =SUMIFS('PMT TYPE'!$F:$F,'PMT TYPE'!$A:$A,'PMTT SUM'!B$1,'PMT TYPE'!$G:$G,'PMTT SUM'!$A59) -> 4704 | C59: =SUMIFS('PMT TYPE'!$F:$F,'PMT TYPE'!$A:$A,'PMTT SUM'!C$1,'PMT TYPE'!$G:$G,'PMTT SUM'!$A59) -> 5775 | D59: =SUMIFS('PMT TYPE'!$F:$F,'PMT TYPE'!$A:$A,'PMTT SUM'!D$1,'PMT TYPE'!$G:$G,'PMTT SUM'!$A59) -> 0 | E59: =SUMIFS('PMT TYPE'!$F:$F,'PMT TYPE'!$A:$A,'PMTT SUM'!E$1,'PMT TYPE'!$G:$G,'PMTT SUM'!$A59) -> 0 | F59: =SUMIFS('PMT TYPE'!$F:$F,'PMT TYPE'!$A:$A,'PMTT SUM'!F$1,'PMT TYPE'!$G:$G,'PMTT SUM'!$A59) -> 0 | G59: =SUMIFS('PMT TYPE'!$F:$F,'PMT TYPE'!$A:$A,'PMTT SUM'!G$1,'PMT TYPE'!$G:$G,'PMTT SUM'!$A59) -> 850 | H59: =SUM(B59:G59) -> 11329 | I59: =SUMIFS(SUM_NET,SUM_PER,">="&'PMTT SUM'!A59,SUM_PER,"<"&'PMTT SUM'!A60) -> 11329
A60: 46254 | B60: =SUMIFS('PMT TYPE'!$F:$F,'PMT TYPE'!$A:$A,'PMTT SUM'!B$1,'PMT TYPE'!$G:$G,'PMTT SUM'!$A60) -> 4337 | C60: =SUMIFS('PMT TYPE'!$F:$F,'PMT TYPE'!$A:$A,'PMTT SUM'!C$1,'PMT TYPE'!$G:$G,'PMTT SUM'!$A60) -> 5764 | D60: =SUMIFS('PMT TYPE'!$F:$F,'PMT TYPE'!$A:$A,'PMTT SUM'!D$1,'PMT TYPE'!$G:$G,'PMTT SUM'!$A60) -> 0 | E60: =SUMIFS('PMT TYPE'!$F:$F,'PMT TYPE'!$A:$A,'PMTT SUM'!E$1,'PMT TYPE'!$G:$G,'PMTT SUM'!$A60) -> 3874 | F60: =SUMIFS('PMT TYPE'!$F:$F,'PMT TYPE'!$A:$A,'PMTT SUM'!F$1,'PMT TYPE'!$G:$G,'PMTT SUM'!$A60) -> 1130 | G60: =SUMIFS('PMT TYPE'!$F:$F,'PMT TYPE'!$A:$A,'PMTT SUM'!G$1,'PMT TYPE'!$G:$G,'PMTT SUM'!$A60) -> 2337 | H60: =SUM(B60:G60) -> 17442 | I60: =SUMIFS(SUM_NET,SUM_PER,">="&'PMTT SUM'!A60,SUM_PER,"<"&'PMTT SUM'!A61) -> 17442
A61: 46255 | B61: =SUMIFS('PMT TYPE'!$F:$F,'PMT TYPE'!$A:$A,'PMTT SUM'!B$1,'PMT TYPE'!$G:$G,'PMTT SUM'!$A61) -> 3143 | C61: =SUMIFS('PMT TYPE'!$F:$F,'PMT TYPE'!$A:$A,'PMTT SUM'!C$1,'PMT TYPE'!$G:$G,'PMTT SUM'!$A61) -> 0 | D61: =SUMIFS('PMT TYPE'!$F:$F,'PMT TYPE'!$A:$A,'PMTT SUM'!D$1,'PMT TYPE'!$G:$G,'PMTT SUM'!$A61) -> 0 | E61: =SUMIFS('PMT TYPE'!$F:$F,'PMT TYPE'!$A:$A,'PMTT SUM'!E$1,'PMT TYPE'!$G:$G,'PMTT SUM'!$A61) -> 1789 | F61: =SUMIFS('PMT TYPE'!$F:$F,'PMT TYPE'!$A:$A,'PMTT SUM'!F$1,'PMT TYPE'!$G:$G,'PMTT SUM'!$A61) -> 0 | G61: =SUMIFS('PMT TYPE'!$F:$F,'PMT TYPE'!$A:$A,'PMTT SUM'!G$1,'PMT TYPE'!$G:$G,'PMTT SUM'!$A61) -> 765 | H61: =SUM(B61:G61) -> 5697 | I61: =SUMIFS(SUM_NET,SUM_PER,">="&'PMTT SUM'!A61,SUM_PER,"<"&'PMTT SUM'!A62) -> 5697
A62: 46256 | B62: =SUMIFS('PMT TYPE'!$F:$F,'PMT TYPE'!$A:$A,'PMTT SUM'!B$1,'PMT TYPE'!$G:$G,'PMTT SUM'!$A62) -> 11415 | C62: =SUMIFS('PMT TYPE'!$F:$F,'PMT TYPE'!$A:$A,'PMTT SUM'!C$1,'PMT TYPE'!$G:$G,'PMTT SUM'!$A62) -> 3329 | D62: =SUMIFS('PMT TYPE'!$F:$F,'PMT TYPE'!$A:$A,'PMTT SUM'!D$1,'PMT TYPE'!$G:$G,'PMTT SUM'!$A62) -> 600 | E62: =SUMIFS('PMT TYPE'!$F:$F,'PMT TYPE'!$A:$A,'PMTT SUM'!E$1,'PMT TYPE'!$G:$G,'PMTT SUM'!$A62) -> 1601 | F62: =SUMIFS('PMT TYPE'!$F:$F,'PMT TYPE'!$A:$A,'PMTT SUM'!F$1,'PMT TYPE'!$G:$G,'PMTT SUM'!$A62) -> 0 | G62: =SUMIFS('PMT TYPE'!$F:$F,'PMT TYPE'!$A:$A,'PMTT SUM'!G$1,'PMT TYPE'!$G:$G,'PMTT SUM'!$A62) -> 0 | H62: =SUM(B62:G62) -> 16945 | I62: =SUMIFS(SUM_NET,SUM_PER,">="&'PMTT SUM'!A62,SUM_PER,"<"&'PMTT SUM'!A63) -> 16945
A63: 46257 | B63: =SUMIFS('PMT TYPE'!$F:$F,'PMT TYPE'!$A:$A,'PMTT SUM'!B$1,'PMT TYPE'!$G:$G,'PMTT SUM'!$A63) -> 5442 | C63: =SUMIFS('PMT TYPE'!$F:$F,'PMT TYPE'!$A:$A,'PMTT SUM'!C$1,'PMT TYPE'!$G:$G,'PMTT SUM'!$A63) -> 474 | D63: =SUMIFS('PMT TYPE'!$F:$F,'PMT TYPE'!$A:$A,'PMTT SUM'!D$1,'PMT TYPE'!$G:$G,'PMTT SUM'!$A63) -> 0 | E63: =SUMIFS('PMT TYPE'!$F:$F,'PMT TYPE'!$A:$A,'PMTT SUM'!E$1,'PMT TYPE'!$G:$G,'PMTT SUM'!$A63) -> 0 | F63: =SUMIFS('PMT TYPE'!$F:$F,'PMT TYPE'!$A:$A,'PMTT SUM'!F$1,'PMT TYPE'!$G:$G,'PMTT SUM'!$A63) -> 0 | G63: =SUMIFS('PMT TYPE'!$F:$F,'PMT TYPE'!$A:$A,'PMTT SUM'!G$1,'PMT TYPE'!$G:$G,'PMTT SUM'!$A63) -> 265 | H63: =SUM(B63:G63) -> 6181 | I63: =SUMIFS(SUM_NET,SUM_PER,">="&'PMTT SUM'!A63,SUM_PER,"<"&'PMTT SUM'!A64) -> 6181
A64: 46258 | B64: =SUMIFS('PMT TYPE'!$F:$F,'PMT TYPE'!$A:$A,'PMTT SUM'!B$1,'PMT TYPE'!$G:$G,'PMTT SUM'!$A64) -> 6703 | C64: =SUMIFS('PMT TYPE'!$F:$F,'PMT TYPE'!$A:$A,'PMTT SUM'!C$1,'PMT TYPE'!$G:$G,'PMTT SUM'!$A64) -> 6344 | D64: =SUMIFS('PMT TYPE'!$F:$F,'PMT TYPE'!$A:$A,'PMTT SUM'!D$1,'PMT TYPE'!$G:$G,'PMTT SUM'!$A64) -> 380 | E64: =SUMIFS('PMT TYPE'!$F:$F,'PMT TYPE'!$A:$A,'PMTT SUM'!E$1,'PMT TYPE'!$G:$G,'PMTT SUM'!$A64) -> 612 | F64: =SUMIFS('PMT TYPE'!$F:$F,'PMT TYPE'!$A:$A,'PMTT SUM'!F$1,'PMT TYPE'!$G:$G,'PMTT SUM'!$A64) -> 0 | G64: =SUMIFS('PMT TYPE'!$F:$F,'PMT TYPE'!$A:$A,'PMTT SUM'!G$1,'PMT TYPE'!$G:$G,'PMTT SUM'!$A64) -> 0 | H64: =SUM(B64:G64) -> 14039 | I64: =SUMIFS(SUM_NET,SUM_PER,">="&'PMTT SUM'!A64,SUM_PER,"<"&'PMTT SUM'!A65) -> 14039
A65: 46259 | B65: =SUMIFS('PMT TYPE'!$F:$F,'PMT TYPE'!$A:$A,'PMTT SUM'!B$1,'PMT TYPE'!$G:$G,'PMTT SUM'!$A65) -> 5790 | C65: =SUMIFS('PMT TYPE'!$F:$F,'PMT TYPE'!$A:$A,'PMTT SUM'!C$1,'PMT TYPE'!$G:$G,'PMTT SUM'!$A65) -> 1631 | D65: =SUMIFS('PMT TYPE'!$F:$F,'PMT TYPE'!$A:$A,'PMTT SUM'!D$1,'PMT TYPE'!$G:$G,'PMTT SUM'!$A65) -> 915 | E65: =SUMIFS('PMT TYPE'!$F:$F,'PMT TYPE'!$A:$A,'PMTT SUM'!E$1,'PMT TYPE'!$G:$G,'PMTT SUM'!$A65) -> 718 | F65: =SUMIFS('PMT TYPE'!$F:$F,'PMT TYPE'!$A:$A,'PMTT SUM'!F$1,'PMT TYPE'!$G:$G,'PMTT SUM'!$A65) -> 0 | G65: =SUMIFS('PMT TYPE'!$F:$F,'PMT TYPE'!$A:$A,'PMTT SUM'!G$1,'PMT TYPE'!$G:$G,'PMTT SUM'!$A65) -> 385 | H65: =SUM(B65:G65) -> 9439 | I65: =SUMIFS(SUM_NET,SUM_PER,">="&'PMTT SUM'!A65,SUM_PER,"<"&'PMTT SUM'!A66) -> 9439
A66: 46260 | B66: =SUMIFS('PMT TYPE'!$F:$F,'PMT TYPE'!$A:$A,'PMTT SUM'!B$1,'PMT TYPE'!$G:$G,'PMTT SUM'!$A66) -> 5585 | C66: =SUMIFS('PMT TYPE'!$F:$F,'PMT TYPE'!$A:$A,'PMTT SUM'!C$1,'PMT TYPE'!$G:$G,'PMTT SUM'!$A66) -> 564 | D66: =SUMIFS('PMT TYPE'!$F:$F,'PMT TYPE'!$A:$A,'PMTT SUM'!D$1,'PMT TYPE'!$G:$G,'PMTT SUM'!$A66) -> 0 | E66: =SUMIFS('PMT TYPE'!$F:$F,'PMT TYPE'!$A:$A,'PMTT SUM'!E$1,'PMT TYPE'!$G:$G,'PMTT SUM'!$A66) -> 538 | F66: =SUMIFS('PMT TYPE'!$F:$F,'PMT TYPE'!$A:$A,'PMTT SUM'!F$1,'PMT TYPE'!$G:$G,'PMTT SUM'!$A66) -> 0 | G66: =SUMIFS('PMT TYPE'!$F:$F,'PMT TYPE'!$A:$A,'PMTT SUM'!G$1,'PMT TYPE'!$G:$G,'PMTT SUM'!$A66) -> 0 | H66: =SUM(B66:G66) -> 6687 | I66: =SUMIFS(SUM_NET,SUM_PER,">="&'PMTT SUM'!A66,SUM_PER,"<"&'PMTT SUM'!A67) -> 6687
... A86: 46280 | B86: =SUMIFS('PMT TYPE'!$F:$F,'PMT TYPE'!$A:$A,'PMTT SUM'!B$1,'PMT TYPE'!$G:$G,'PMTT SUM'!$A86) -> 0 | C86: =SUMIFS('PMT TYPE'!$F:$F,'PMT TYPE'!$A:$A,'PMTT SUM'!C$1,'PMT TYPE'!$G:$G,'PMTT SUM'!$A86) -> 0 | D86: =SUMIFS('PMT TYPE'!$F:$F,'PMT TYPE'!$A:$A,'PMTT SUM'!D$1,'PMT TYPE'!$G:$G,'PMTT SUM'!$A86) -> 0 | E86: =SUMIFS('PMT TYPE'!$F:$F,'PMT TYPE'!$A:$A,'PMTT SUM'!E$1,'PMT TYPE'!$G:$G,'PMTT SUM'!$A86) -> 0 | F86: =SUMIFS('PMT TYPE'!$F:$F,'PMT TYPE'!$A:$A,'PMTT SUM'!F$1,'PMT TYPE'!$G:$G,'PMTT SUM'!$A86) -> 0 | G86: =SUMIFS('PMT TYPE'!$F:$F,'PMT TYPE'!$A:$A,'PMTT SUM'!G$1,'PMT TYPE'!$G:$G,'PMTT SUM'!$A86) -> 0 | H86: =SUM(B86:G86) -> 0 | I86: =SUMIFS(SUM_NET,SUM_PER,">="&'PMTT SUM'!A86,SUM_PER,"<"&'PMTT SUM'!A87) -> 0

Sheet PMT TYPE
A1: Payment type | B1: Payment transactions | C1: Payments amount | D1: Refund transactions | E1: Refunds amount | F1: Net amount | G1: DATE
A2: Cash | B2: 12 | C2: 3302 | D2: 0 | E2: 0 | F2: 3302 | G2: 46204
A3: GCash | B3: 4 | C3: 4152 | D3: 0 | E3: 0 | F3: 4152 | G3: 46204
A4: Bank Transfer | B4: 7 | C4: 4692 | D4: 0 | E4: 0 | F4: 4692 | G4: 46204
A5: GrabFood | B5: 1 | C5: 629 | D5: 0 | E5: 0 | F5: 629 | G5: 46204
A6: Maya | B6: 1 | C6: 550 | D6: 0 | E6: 0 | F6: 550 | G6: 46204
A7: Cash | B7: 14 | C7: 5505 | D7: 0 | E7: 0 | F7: 5505 | G7: 46205
A8: GCash | B8: 3 | C8: 3159 | D8: 0 | E8: 0 | F8: 3159 | G8: 46205
A9: Bank Transfer | B9: 2 | C9: 726 | D9: 0 | E9: 0 | F9: 726 | G9: 46205
A10: GCash | B10: 2 | C10: 1529 | D10: 0 | E10: 0 | F10: 1529 | G10: 46206
A11: Cash | B11: 13 | C11: 8734 | D11: 0 | E11: 0 | F11: 8734 | G11: 46206
A12: Bank Transfer | B12: 4 | C12: 2525 | D12: 0 | E12: 0 | F12: 2525 | G12: 46206
A13: GrabFood | B13: 1 | C13: 330 | D13: 0 | E13: 0 | F13: 330 | G13: 46206
... A226: GoTyme | B226: 1 | C226: 486 | D226: 0 | E226: 0 | F226: 486 | G226: 46267

Sheet EGG+VEG
B2: QUANTITY | C2: Cabbage | D2: Carrots | E2: Togue | F2: WOnion | G2: Bell Pepper
A3: VMM | D3: 30 | F3: 15 | G3: 10
A4: VDB | C4: 150 | D4: 30 | E4: 40 | F4: 15 | G4: 5
A5: VRG | C5: 150 | D5: 30 | E5: 40 | F5: 15 | G5: 10
A6: VOK | C6: 300 | F6: 15
A9: VMM | B9: =_xlfn.XLOOKUP(A9,'SUM-SALES25'!$AG$4:$BN$4,'SUM-SALES25'!$AG$5:$BN$5) -> 0 | C9: =$B9*C3 -> 0 | D9: =$B9*D3 -> 0 | E9: =$B9*E3 -> 0 | F9: =$B9*F3 -> 0 | G9: =$B9*G3 -> 0
A10: VDB | B10: =_xlfn.XLOOKUP(A10,'SUM-SALES25'!$AG$4:$BN$4,'SUM-SALES25'!$AG$5:$BN$5) -> 0 | C10: =$B10*C4 -> 0 | D10: =$B10*D4 -> 0 | E10: =$B10*E4 -> 0 | F10: =$B10*F4 -> 0 | G10: =$B10*G4 -> 0
A11: VRG | B11: =_xlfn.XLOOKUP(A11,'SUM-SALES25'!$AG$4:$BN$4,'SUM-SALES25'!$AG$5:$BN$5) -> 1 | C11: =$B11*C5 -> 150 | D11: =$B11*D5 -> 30 | E11: =$B11*E5 -> 40 | F11: =$B11*F5 -> 15 | G11: =$B11*G5 -> 10
A12: VOK | B12: =_xlfn.XLOOKUP(A12,'SUM-SALES25'!$AG$4:$BN$4,'SUM-SALES25'!$AG$5:$BN$5) -> 0 | C12: =$B12*C6 -> 0 | D12: =$B12*D6 -> 0 | E12: =$B12*E6 -> 0 | F12: =$B12*F6 -> 0 | G12: =$B12*G6 -> 0
C13: =SUM(C9:C11) -> 150 | D13: =SUM(D9:D11) -> 30 | E13: =SUM(E9:E11) -> 40 | F13: =SUM(F9:F11) -> 15 | G13: =SUM(G9:G11) -> 10

Sheet COSTING
A1: 1 | B1: 2 | C1: 3 | D1: 4 | F1: 5 | G1: 6
D2: QUANTITY | E2: UNIT RATE | F2: AMOUNT
A3: main ingredients | J3: =5*700*30/K4 -> 0.35 | K3: GROSS
B4: chicken | C4: 270 | D4: 120 | F4: =C4*1.2/1000*D4 -> 38.88 | G4: kg | I4: Overhead | J4: 0.35 | K4: 300000 | L4: SB_050 | M4: Sukiyaki Beef
B5: pangko orange | C5: 280 | D5: 50 | F5: =C5*1/1000*D5 -> 14 | I5: Utilities | J5: =K23/K4 -> 0.255 | L5: GB_050 | M5: Ground Beef
B6: Egg | C6: 250 | D6: 1 | F6: =CEILING(C6*D6/30,1) -> 9 | I6: Profit | J6: 0.5 | L6: SB_030 | M6: Sukiyaki Beef
B7: Cooking oil | C7: 1670 | D7: 30 | F7: =C7/17000*D7 -> 2.9470588 | G7: 17kg | L7: GB_060 | M7: Ground Beef
B8: Rice | F8: 7 | I8: Overhead 1 | J8: 0.4 | K8: 250000 | L8: PL_050 | M8: Porkloin
B9: Flour | C9: 65 | D9: 50 | F9: =C9*1.2/1000*D9 -> 3.9 | I9: Utilities 1 | J9: 0.35 | L9: PL_060 | M9: Porkloin
B10: hondashi | F10: 0.5 | I10: Profit Promo | J10: 0.35 | L10: PL_020 | M10: Porkloin
B11: salt | F11: 0.25 | L11: PB_060 | M11: Pork Belly
B12: pamienta | F12: 0.5 | I12: Overhead 2 | J12: 0.45 | K12: 200000 | L12: PB_120 | M12: Pork Belly
F13: =SUM(F4:F12) -> 76.977059 | I13: Utilities 2 | J13: 0.45 | L13: CF_040 | M13: Yakitori
I14: Profit 2 | J14: 0.5 | L14: CF_050 | M14: Chicken Fillet
A15: TERIYAKI SAUCE | L15: CF_060 | M15: Chicken Fillet
B16: tanduay | C16: 230 | D16: 1 | F16: =C16*D16 -> 230 | G16: sety | L16: CT_120 | M16: Chicken Thigh
B17: sugar | C17: 90 | D17: 1 | F17: =C17/1*D17 -> 90 | G17: kg | L17: CT_150 | M17: Chicken Thigh
B18: kikkoman | C18: 2700 | D18: 0.5 | F18: =C18/18*D18 -> 75 | G18: 18kg | K18: UTILITIES
B19: oyster | C19: 234 | D19: 50 | F19: =C19/1000*D19 -> 11.7 | G19: liter | J19: WATER | K19: 2500
B20: vinegar | C20: 120 | D20: 30 | F20: =C20/250*D20 -> 14.4 | G20: 250ml | J20: ELECTRIC | K20: 24000
B21: lea perins | C21: 139 | D21: 60 | F21: =C21/150*D21 -> 55.6 | G21: 150ml | J21: RENTAL | K21: 35000
B22: hondashi | C22: 430 | D22: 40 | F22: =C22/1000*D22 -> 17.2 | G22: kg | J22: MISC., GAS | K22: 15000
B23: onion | C23: 83 | D23: 200 | F23: =C23/1000*D23 -> 16.6 | G23: kg | K23: =SUM(K19:K22) -> 76500
B24: Carrots | C24: 130 | D24: 20 | F24: =C24/1000*D24 -> 2.6 | G24: kg
B25: Baguio pechay | C25: 155 | D25: 50 | F25: =C25/1000*D25 -> 7.75 | G25: kg
B26: bell pepper | C26: 50 | D26: 1 | F26: =C26/2*D26 -> 25 | G26: each
B27: ginger | C27: 50 | D27: 10 | F27: =C27/250*D27 -> 2 | G27: kg
B28: corn starch | C28: 112 | D28: 60 | F28: =C28/1000*D28 -> 6.72 | G28: kg
B29: chicken bones | C29: 50 | D29: 3 | F29: =C29/1*D29 -> 150 | G29: kg
B30: gas | F30: 5 | G30: pesos
F31: =SUM(F16:F30) -> 709.57
F32: 45 | G32: servings
B33: Teriyaki Sauce | F33: =F31/F32 -> 15.768222
A35: TEPPANYAKI SAUCE
B36: Knorr Seasoning | C36: 325 | D36: 1 | F36: =C36/1*D36 -> 325 | G36: liter
B37: Sugar | C37: 90 | D37: 0.5 | F37: =C37/1*D37 -> 45 | G37: kg
B38: hondashi | C38: 430 | D38: 40 | F38: =C38/1000*D38 -> 17.2 | G38: kg
B39: Sesame Oil | C39: 636 | D39: 5 | F39: =C39/3000*D39 -> 1.06 | G39: liter
B40: Lea perins | C40: 139 | D40: 60 | F40: =C40/150*D40 -> 55.6 | G40: 150ml
F41: =SUM(F36:F40) -> 443.86
F42: 45 | G42: servings
B43: Teppanyaki Sauce | F43: =F41/F42 -> 9.8635556
B44: Teppanyaki Sauce - Grams | F44: =F43/F42 -> 0.21919012
A46: Tempura Batter | C46: Unit Price | D46: Qty | F46: 8 | G46: no. per mix
B47: Egg | C47: 250 | D47: 1 | F47: =CEILING(C47*D47/30/$F$46,1) -> 2
B48: Pangko Orange
B49: Flour | C49: 65 | D49: =55/$F$46 -> 6.875 | F49: =C49*1/1000*D49 -> 0.446875 | G49: 55grams
B50: corn starch | C50: 112 | D50: =55/$F$46 -> 6.875 | F50: =C50*1/1000*D50 -> 0.77 | G50: 55grams
B51: cooking oil | C51: 1670 | D51: 20 | F51: =C51/17000*D51 -> 1.9647059
D52: Tempura Bater | F52: =SUM(F47:F51) -> 5.1815809
A55: Batter | C55: Unit Price | D55: Qty | F55: 4 | G55: no. per mix
B56: Egg | C56: 250 | D56: 1 | F56: =CEILING(C56*D56/30/$F$55,1) -> 3
B57: Pangko Orange
B58: Flour | C58: 65 | D58: =55/$F$55 -> 13.75 | F58: =C58*1/1000*D58 -> 0.89375 | G58: 55grams
B59: corn starch | C59: 112 | D59: =55/$F$55 -> 13.75 | F59: =C59*1/1000*D59 -> 1.54 | G59: 55grams
B60: cooking oil | C60: 1670 | D60: 20 | F60: =C60/17000*D60 -> 1.9647059
D61: Batter | F61: =SUM(F56:F60) -> 7.3984559
A63: Seafood Fried Rice
B64: Rice | F64: 7
B65: Egg | F65: 8
B66: hondashi | F66: 0.1
B67: cooking oil | C67: 1670 | D67: 5 | F67: =C67/17000*D67 -> 0.49117647
B68: carrots | C68: 130 | D68: 5 | F68: =C68/1000*D68 -> 0.65
B69: baguio beans | C69: 120 | D69: 5 | F69: =C69/1000*D69 -> 0.6
B70: onion | C70: 83 | D70: 5 | F70: =C70/1000*D70 -> 0.415
B71: squid tube | D71: 5 | F71: =_xlfn.XLOOKUP(B71,'SUPPLY-UR'!C:C,CUM_URG)*D71 -> 1.9333333
B72: kikkoman | C72: 2700 | D72: =5/1000 -> 0.005 | F72: =C72/18*D72 -> 0.75
B73: Fried Rice | F73: =SUM(F64:F72) -> 19.93951
A76: Mix&Match - 2Kani
B77: Kani | D77: 2 | F77: =_xlfn.XLOOKUP(B77,'SUPPLY-UR'!C:C,CUM_URG)*D77 -> 19.607843
B78: Egg | C78: 250 | D78: 1 | F78: =CEILING(C78*D78/30/6,1) -> 2
B79: Flour | C79: 65 | D79: =55/6 -> 9.1666667 | F79: =C79*1.2/1000*D79 -> 0.715 | G79: 55grams
B80: corn starch | C80: 112 | D80: =55/6 -> 9.1666667 | F80: =C80*1.2/1000*D80 -> 1.232 | G80: 55grams
B81: cooking oil | C81: 1670 | D81: 15 | F81: =C81/17000*D81 -> 1.4735294
A82: Mix&Match - 2Kani | D82: KANI | F82: =SUM(F77:F81) -> 25.028373
A84: Mix&Match - 2Ebi
B85: Nobashi | D85: 2 | F85: =_xlfn.XLOOKUP(B85,'SUPPLY-UR'!C:C,CUM_URG)*D85 -> 27.368421
B86: Egg | C86: 250 | D86: 1 | F86: =CEILING(C86*D86/30/6,1) -> 2
B87: Flour | C87: 65 | D87: =55/6 -> 9.1666667 | F87: =C87*1.2/1000*D87 -> 0.715 | G87: 55grams
B88: corn starch | C88: 112 | D88: =55/6 -> 9.1666667 | F88: =C88*1.2/1000*D88 -> 1.232 | G88: 55grams
B89: cooking oil | C89: 1670 | D89: 15 | F89: =C89/17000*D89 -> 1.4735294
A90: Mix&Match - 2Ebi | D90: EBI | F90: =SUM(F85:F89) -> 32.78895
A93: Mix&Match - Yakitori + Kani | F93: =F104 -> 183
B94: Yakitori | C94: 270 | D94: 80 | F94: =C94*1.2/1000*D94 -> 25.92
B95: Fried Rice | F95: =_xlfn.XLOOKUP(B95,$B$73,$F$73) -> 19.93951
B96: Teriyaki Sauce | F96: =_xlfn.XLOOKUP(B96,$B$33,$F$33) -> 15.768222
B97: Stick | F97: 0.1
F98: =SUM(F94:F97) -> 61.727732
D99: KANI | F99: =_xlfn.XLOOKUP(D99,$D$77:$D$90,$F$77:$F$90) -> 25.028373
F100: =SUM(F98:F99) -> 86.756105
D101: =_xlfn.XLOOKUP(G101,$I$4:$I$16,$J$4:$J$16) -> 0.35 | F101: =D101*F100 -> 30.364637 | G101: Overhead
D102: =_xlfn.XLOOKUP(G102,$I$4:$I$16,$J$4:$J$16) -> 0.255 | F102: =D102*F100 -> 22.122807 | G102: Utilities
D103: =_xlfn.XLOOKUP(G103,$I$4:$I$16,$J$4:$J$16) -> 0.5 | F103: =D103*F100 -> 43.378052 | G103: Profit
A104: Mix&Match - Yakitori + Kani | D104: =F104/F100 -> 2.1093617 | F104: =CEILING(SUM(F100:F103),1) -> 183
A106: Mix&Match - Yakitori + Ebi | F106: =F117 -> 199
B107: Yakitori | C107: 270 | D107: 80 | F107: =C107*1.2/1000*D107 -> 25.92
B108: Fried Rice | F108: =_xlfn.XLOOKUP(B108,$B$73,$F$73) -> 19.93951
B109: Teriyaki Sauce | F109: =_xlfn.XLOOKUP(B109,$B$33,$F$33) -> 15.768222
B110: Stick | F110: 0.1
F111: =SUM(F107:F110) -> 61.727732
...

Sheet LINKS
A3: NEW MENU | B3: https://www.canva.com/design/DAGiQWXWUKw/GuqMsIFjagHMekOyMFp4AA/edit?utm_content=DAGiQWXWUKw&utm_campaign=designshare&utm_medium=link2&utm_source=sharebutton
A4: OLD MENU | B4: https://www.canva.com/design/DAFU-3OpoOU/rApmRRbMQNsUzfr2QAVi6A/edit
H16: PANLUTO | I16: 0 | J16: 0
H17: SASHIMI | I17: 1800 | J17: 1500
H18: BAKED SUSHI | I18: 724 | J18: 724
H19: MAKIROLLS | I19: 0 | J19: 0
I21: =SUM(I16:I20) -> 2524 | J21: =SUM(J16:J20) -> 2224 | K21: =SUM(K16:K20) -> 0 | L21: =SUM(L16:L20) -> 0

Sheet REFERENCES
A1: PORK BELLY
H2: BUTTER | I2: GRAMS
A3: 2.65 | B3: KG | C3: FROZEN | H3: FLOUR | I3: 60
A4: 2.63 | B4: KG | C4: DEFROZED | H4: CORNSTARCH | I4: 30
A5: =A3-A4 -> 0.02 | H5: EGG | I5: 1
A6: 2.01 | B6: KG | C6: COOKED | D6: 1.5hrs
A8: =A6/A3 -> 0.75849057 | B8: =A8 -> 0.75849057
A9: =A3*A8 -> 2.01
A11: 30 pcs @ 60gms = 1800
A12: 201 grams = scrap
A14: 1.8
A15: =A14/A3 -> 0.67924528 | B15: =A15 -> 0.67924528
A19: GYOZA
B20: Cabbage | C20: 3 | D20: kgs
B21: Baguio Pechay | C21: 3 | D21: kgs
B22: White Onion | C22: 0.5 | D22: kgs
B23: Carrots | C23: 1 | D23: kgs
B24: Ginger | C24: 300 | D24: gms | E24: ???
B25: Garlic | C25: 0.5 | D25: kgs
B26: Ground Pork | C26: 0.74 | D26: kgs
B27: Oyster Sauce | D27: 1 bot
B28: Kikkoman
B29: Sesame
B30: Hondashi
B31: Salt

Sheet PMNTS BRKDWN
A1: PAYMENTS
B2: Cash | C2: GCash | D2: Bank | E2: Grab | J2: Cash | K2: GCash | L2: Bank | M2: Others
A3: 45658 | F3: =SUM(B3:E3) -> 0 | I3: 45658 | J3: =SUMIFS(B:B,$A:$A,">="&$I3,$A:$A,"<"&$I4) -> 0 | K3: =SUMIFS(C:C,$A:$A,">="&$I3,$A:$A,"<"&$I4) -> 0 | L3: =SUMIFS(D:D,$A:$A,">="&$I3,$A:$A,"<"&$I4) -> 0 | M3: =SUMIFS(E:E,$A:$A,">="&$I3,$A:$A,"<"&$I4) -> 0 | N3: =SUM(J3:M3) -> 0
A4: 45659 | F4: =SUM(B4:E4) -> 0 | I4: 45689 | J4: =SUMIFS(B:B,$A:$A,">="&$I4,$A:$A,"<"&$I5) -> 12444 | K4: =SUMIFS(C:C,$A:$A,">="&$I4,$A:$A,"<"&$I5) -> 7315 | L4: =SUMIFS(D:D,$A:$A,">="&$I4,$A:$A,"<"&$I5) -> 5475 | M4: =SUMIFS(E:E,$A:$A,">="&$I4,$A:$A,"<"&$I5) -> 0 | N4: =SUM(J4:M4) -> 25234
A5: 45660 | F5: =SUM(B5:E5) -> 0 | I5: 45717 | J5: =SUMIFS(B:B,$A:$A,">="&$I5,$A:$A,"<"&$I6) -> 23590 | K5: =SUMIFS(C:C,$A:$A,">="&$I5,$A:$A,"<"&$I6) -> 9936 | L5: =SUMIFS(D:D,$A:$A,">="&$I5,$A:$A,"<"&$I6) -> 1370 | M5: =SUMIFS(E:E,$A:$A,">="&$I5,$A:$A,"<"&$I6) -> 0 | N5: =SUM(J5:M5) -> 34896
A6: 45661 | F6: =SUM(B6:E6) -> 0 | I6: 45748 | J6: =SUMIFS(B:B,$A:$A,">="&$I6,$A:$A,"<"&$I7) -> 0 | K6: =SUMIFS(C:C,$A:$A,">="&$I6,$A:$A,"<"&$I7) -> 0 | L6: =SUMIFS(D:D,$A:$A,">="&$I6,$A:$A,"<"&$I7) -> 0 | M6: =SUMIFS(E:E,$A:$A,">="&$I6,$A:$A,"<"&$I7) -> 0 | N6: =SUM(J6:M6) -> 0
A7: 45662 | F7: =SUM(B7:E7) -> 0 | I7: 45778 | J7: =SUMIFS(B:B,$A:$A,">="&$I7,$A:$A,"<"&$I8) -> 25789 | K7: =SUMIFS(C:C,$A:$A,">="&$I7,$A:$A,"<"&$I8) -> 12657 | L7: =SUMIFS(D:D,$A:$A,">="&$I7,$A:$A,"<"&$I8) -> 2020 | M7: =SUMIFS(E:E,$A:$A,">="&$I7,$A:$A,"<"&$I8) -> 690 | N7: =SUM(J7:M7) -> 41156
A8: 45663 | F8: =SUM(B8:E8) -> 0 | I8: 45809 | J8: =SUMIFS(B:B,$A:$A,">="&$I8,$A:$A,"<"&$I9) -> 74352.4 | K8: =SUMIFS(C:C,$A:$A,">="&$I8,$A:$A,"<"&$I9) -> 31011 | L8: =SUMIFS(D:D,$A:$A,">="&$I8,$A:$A,"<"&$I9) -> 8648 | M8: =SUMIFS(E:E,$A:$A,">="&$I8,$A:$A,"<"&$I9) -> 2306 | N8: =SUM(J8:M8) -> 116317.4
A9: 45664 | F9: =SUM(B9:E9) -> 0 | I9: 45839 | J9: =SUMIFS(B:B,$A:$A,">="&$I9,$A:$A,"<"&$I10) -> 0 | K9: =SUMIFS(C:C,$A:$A,">="&$I9,$A:$A,"<"&$I10) -> 0 | L9: =SUMIFS(D:D,$A:$A,">="&$I9,$A:$A,"<"&$I10) -> 0 | M9: =SUMIFS(E:E,$A:$A,">="&$I9,$A:$A,"<"&$I10) -> 0 | N9: =SUM(J9:M9) -> 0
A10: 45665 | F10: =SUM(B10:E10) -> 0
A11: 45666 | F11: =SUM(B11:E11) -> 0
A12: 45667 | F12: =SUM(B12:E12) -> 0
A13: 45668 | F13: =SUM(B13:E13) -> 0
A14: 45669 | F14: =SUM(B14:E14) -> 0
A15: 45670 | F15: =SUM(B15:E15) -> 0
A16: 45671 | F16: =SUM(B16:E16) -> 0
A17: 45672 | F17: =SUM(B17:E17) -> 0
A18: 45673 | F18: =SUM(B18:E18) -> 0
A19: 45674 | F19: =SUM(B19:E19) -> 0
A20: 45675 | F20: =SUM(B20:E20) -> 0
A21: 45676 | F21: =SUM(B21:E21) -> 0
... A46: 45701 | F46: =SUM(B46:E46) -> 0
A47: 45702 | B47: 7543 | C47: 2930 | D47: 290 | F47: =SUM(B47:E47) -> 10763
A48: 45703 | B48: 3636 | C48: 1460 | D48: 1575 | F48: =SUM(B48:E48) -> 6671
A49: 45704 | B49: 1265 | C49: 2925 | D49: 3610 | F49: =SUM(B49:E49) -> 7800
A50: 45705 | F50: =SUM(B50:E50) -> 0
A51: 45706 | F51: =SUM(B51:E51) -> 0
A52: 45707 | F52: =SUM(B52:E52) -> 0
A53: 45708 | F53: =SUM(B53:E53) -> 0
A54: 45709 | F54: =SUM(B54:E54) -> 0
A55: 45710 | F55: =SUM(B55:E55) -> 0
A56: 45711 | F56: =SUM(B56:E56) -> 0
A57: 45712 | F57: =SUM(B57:E57) -> 0
A58: 45713 | F58: =SUM(B58:E58) -> 0
A59: 45714 | F59: =SUM(B59:E59) -> 0
A60: 45715 | F60: =SUM(B60:E60) -> 0
A61: 45716 | F61: =SUM(B61:E61) -> 0
... A80: 45735 | F80: =SUM(B80:E80) -> 0
A81: 45736 | B81: 5686 | C81: 5421 | F81: =SUM(B81:E81) -> 11107
A82: 45737 | B82: 3910 | C82: 2780 | D82: 820 | F82: =SUM(B82:E82) -> 7510
A83: 45738 | B83: 3836 | C83: 1735 | F83: =SUM(B83:E83) -> 5571
A84: 45739 | B84: 6797 | F84: =SUM(B84:E84) -> 6797
A85: 45740 | B85: 3361 | D85: 550 | F85: =SUM(B85:E85) -> 3911
A86: 45741 | F86: =SUM(B86:E86) -> 0
A87: 45742 | F87: =SUM(B87:E87) -> 0
A88: 45743 | F88: =SUM(B88:E88) -> 0
A89: 45744 | F89: =SUM(B89:E89) -> 0
A90: 45745 | F90: =SUM(B90:E90) -> 0
A91: 45746 | F91: =SUM(B91:E91) -> 0
A92: 45747 | F92: =SUM(B92:E92) -> 0
A93: 45748 | F93: =SUM(B93:E93) -> 0
A94: 45749 | F94: =SUM(B94:E94) -> 0
A95: 45750 | F95: =SUM(B95:E95) -> 0
A96: 45751 | F96: =SUM(B96:E96) -> 0
A97: 45752 | F97: =SUM(B97:E97) -> 0
... A149: 45804 | F149: =SUM(B149:E149) -> 0
A150: 45805 | B150: 3662 | C150: 3165 | D150: 2020 | E150: 690 | F150: =SUM(B150:E150) -> 9537
A151: 45806 | B151: 3008 | C151: 663 | F151: =SUM(B151:E151) -> 3671
A152: 45807 | B152: 10099 | C152: 4287 | F152: =SUM(B152:E152) -> 14386
A153: 45808 | B153: 9020 | C153: 4542 | F153: =SUM(B153:E153) -> 13562
A154: 45809 | B154: 3142 | C154: 705 | F154: =SUM(B154:E154) -> 3847
A155: 45810 | B155: 5114.4 | C155: 2949 | F155: =SUM(B155:E155) -> 8063.4
A156: 45811 | B156: 4546 | C156: 1073 | D156: 2703 | F156: =SUM(B156:E156) -> 8322
A157: 45812 | B157: 9822 | C157: 2154 | D157: 265 | F157: =SUM(B157:E157) -> 12241
A158: 45813 | B158: 10304 | F158: =SUM(B158:E158) -> 10304 | J158: 3662 | K158: 3165
A159: 45814 | B159: 11763 | C159: 4810 | F159: =SUM(B159:E159) -> 16573 | K159: 690
A160: 45815 | B160: 4391 | C160: 335 | D160: 2750 | E160: 2306 | F160: =SUM(B160:E160) -> 9782 | K160: =SUM(K158:K159) -> 3855
A161: 45816 | B161: 3241 | C161: 540 | F161: =SUM(B161:E161) -> 3781
A162: 45817 | B162: 6352 | C162: 7039 | F162: =SUM(B162:E162) -> 13391
A163: 45818 | B163: 7674 | C163: 2317 | D163: 1230 | F163: =SUM(B163:E163) -> 11221
A164: 45819 | B164: 8003 | C164: =8030+1059 -> 9089 | D164: 1700 | F164: =SUM(B164:E164) -> 18792
A165: 45820 | F165: =SUM(B165:E165) -> 0
A166: 45821 | F166: =SUM(B166:E166) -> 0
A167: 45822 | F167: =SUM(B167:E167) -> 0
A168: 45823 | F168: =SUM(B168:E168) -> 0
A169: 45824 | F169: =SUM(B169:E169) -> 0
A170: 45825 | F170: =SUM(B170:E170) -> 0
A171: 45826 | F171: =SUM(B171:E171) -> 0
A172: 45827 | F172: =SUM(B172:E172) -> 0
A173: 45828 | F173: =SUM(B173:E173) -> 0
F174: =SUM(B174:E174) -> 0
